Workbook
Name Année: 'Listes déroulantes, autres'!$D$9:$D$4979
Name CO2_: #REF!,#REF!,#REF!,#REF!,#REF!
Name Debut_1A1: Calculs!$B$10
Name Équipements_fixes: FÉ!$B$9:$B$21
Name Équipements_mobiles: FÉ!$B$41:$B$59
Name Fin_1A1: Calculs!$B$31
Name Grid: FÉ!$B$385:$B$437
Name Intensité_type_bâtiments: FÉ!$B$26:$B$36
Name Liste_Véhicules_Compagnie: 'Détails Entreprise'!$O$9:$O$20
Name Marque: 'Listes déroulantes, autres'!$E$9:$E$4979
Name Modèle: 'Listes déroulantes, autres'!$F$9:$F$4979
Name Moyennes_de_transport: FÉ!$B$64:$B$74
Name Oui_Non: 'Listes déroulantes, autres'!$C$9:$C$10
Name Sites: #REF!,#REF!,#REF!,#REF!,#REF!
Name Transmission: 'Listes déroulantes, autres'!$G$9:$G$10

Sheet Page d'accueil
C4: Back-end du logiciel d'inventaire GES
C5: Logiciel co-produit par la collaboration de Carbone Québec et i-GES
C6: Version 2.1.0
E14: Contact i-GES
E15: Pierre-Emile Leblanc Comtois
E16: pe.leblanc-comtois@i-ges.ca
E17: Sherbrooke, Qc
C19: Ce calculateur permet de se conformer à la norme ISO 14064-1. | M19: Tous droits réservés 2025
B21: Mises à jours
B22: Mise à jour | C22: date | D22: Description
B23: 2.1.0 | C23: 45992 | D23: - Réorganisation des postes d'émissions pour répondre à la nouvelle norme ISO 14064-4 (2025) "Application de la norme ISO 14064-1 (2013)" sortie en novembre 2025.

Sheet ISO 14064-4
B2: Bilan (Détaillé par catégorie) | Q2: CO2 Biogénique | S2: État d'inventaire
B3: Categorie | I3: Description | J3: CO2 [tCO2e] | K3: CH4 [tCO2e] | L3: N2O [tCO2e] | M3: Total tCO2e | N3: % | O3: Bar %
B4: Catégorie 1 | D4: Émissions directs | I4: Émissions directes | J4: =SUMIFS(J$42:J$154,$C$42:$C$154,$B4) -> 13.252841 | K4: =SUMIFS(K$42:K$154,$C$42:$C$154,$B4) -> 0.090484535 | L4: =SUMIFS(L$42:L$154,$C$42:$C$154,$B4) -> 0.094192804 | M4: =SUMIFS(M$42:M$154,$C$42:$C$154,$B4) -> 20.371226 | N4: =M4/$M$10 -> 0.11470822 | O4: =REPT("|",N4*(100/MAX($N$4:$N$9))) -> |||||||||||||||||| | Q4: =SUMIFS(Q$42:Q$154,$C$42:$C$154,$B4) -> 2.6985
B5: Catégorie 2 | D5: Émissions indirects de l'énergie importée | I5: Émissions indirectes liées à l'énergie importée | J5: =SUMIFS(J$42:J$154,$C$42:$C$154,$B5) -> 27.880882 | K5: =SUMIFS(K$42:K$154,$C$42:$C$154,$B5) -> 0.016389352 | L5: =SUMIFS(L$42:L$154,$C$42:$C$154,$B5) -> 0.13090095 | M5: =SUMIFS(M$42:M$154,$C$42:$C$154,$B5) -> 28.028172 | N5: =M5/$M$10 -> 0.15782368 | O5: =REPT("|",N5*(100/MAX($N$4:$N$9))) -> ||||||||||||||||||||||||| | Q5: =SUMIFS(Q$42:Q$154,$C$42:$C$154,$B5) -> 0
B6: Catégorie 3 | D6: Émissions indirects des transports | I6: Émissions indirectes des déplacements et des transports | J6: =SUMIFS(J$42:J$154,$C$42:$C$154,$B6) -> 19.802851 | K6: =SUMIFS(K$42:K$154,$C$42:$C$154,$B6) -> 0.014693907 | L6: =SUMIFS(L$42:L$154,$C$42:$C$154,$B6) -> 0.19019935 | M6: =SUMIFS(M$42:M$154,$C$42:$C$154,$B6) -> 20.007745 | N6: =M6/$M$10 -> 0.1126615 | O6: =REPT("|",N6*(100/MAX($N$4:$N$9))) -> |||||||||||||||||| | Q6: =SUMIFS(Q$42:Q$154,$C$42:$C$154,$B6) -> 0
B7: Catégorie 4 | D7: Émissions indirects des produits utilisés par l'organisation | I7: Émissions indirectes en amont (Biens et services, locations en amonts) | J7: =SUMIFS(J$42:J$154,$C$42:$C$154,$B7) -> 109.16114 | K7: =SUMIFS(K$42:K$154,$C$42:$C$154,$B7) -> 0.023397962 | L7: =SUMIFS(L$42:L$154,$C$42:$C$154,$B7) -> 0 | M7: =SUMIFS(M$42:M$154,$C$42:$C$154,$B7) -> 109.18453 | N7: =M7/$M$10 -> 0.61480659 | O7: =REPT("|",N7*(100/MAX($N$4:$N$9))) -> |||||||||||||||||||||||||||||||||||||||||||||||||||||||||||||||||||||||||||||||||||||||||||||||||||| | Q7: =SUMIFS(Q$42:Q$154,$C$42:$C$154,$B7) -> 0
B8: Catégorie 5 | D8: Émissions indirects à l'utilisation des produits de l'organisation | I8: Émissions indirectes en aval (Usage et fin de vie des produits, franchises et investissement) | J8: =SUMIFS(J$42:J$154,$C$42:$C$154,$B8) -> 0 | K8: =SUMIFS(K$42:K$154,$C$42:$C$154,$B8) -> 0 | L8: =SUMIFS(L$42:L$154,$C$42:$C$154,$B8) -> 0 | M8: =SUMIFS(M$42:M$154,$C$42:$C$154,$B8) -> 0 | N8: =M8/$M$10 -> 0 | O8: =REPT("|",N8*(100/MAX($N$4:$N$9))) | Q8: =SUMIFS(Q$42:Q$154,$C$42:$C$154,$B8) -> 0
B9: Catégorie 6 | D9: Autres émissions indirects | I9: Autres sources d'émissions indirectes | J9: =SUMIFS(J$42:J$154,$C$42:$C$154,$B9) -> 0 | K9: =SUMIFS(K$42:K$154,$C$42:$C$154,$B9) -> 0 | L9: =SUMIFS(L$42:L$154,$C$42:$C$154,$B9) -> 0 | M9: =SUMIFS(M$42:M$154,$C$42:$C$154,$B9) -> 0 | N9: =M9/$M$10 -> 0 | O9: =REPT("|",N9*(100/MAX($N$4:$N$9))) | Q9: =SUMIFS(Q$42:Q$154,$C$42:$C$154,$B9) -> 0
I10: Totaux : | J10: =SUM(J4:J9) -> 170.09771 | K10: =SUM(K4:K9) -> 0.14496576 | L10: =SUM(L4:L9) -> 0.41529311 | M10: =SUM(M4:M9) -> 177.59168 | N10: tCO2e | Q10: =SUM(Q4:Q9) -> 2.6985
B12: Bilan (Détaillé par poste d'émissions) | Q12: CO2 Biogénique | S12: État d'inventaire
B13: Categorie | E13: Poste d'émissions | I13: Description | J13: CO2 [tCO2e] | K13: CH4 [tCO2e] | L13: N2O [tCO2e] | M13: Total tCO2e | N13: % | O13: Bar %
B14: Catégorie 1 | D14: Émissions directs | E14: 1.1 | G14: Combustions fixes | I14: Émissions directes des sources de combustions fixes | J14: =SUMIFS(J$42:J$154,$F$42:$F$154,$E14) -> 4.268 | K14: =SUMIFS(K$42:K$154,$F$42:$F$154,$E14) -> 0.0319158 | L14: =SUMIFS(L$42:L$154,$F$42:$F$154,$E14) -> 0.0694785 | M14: =SUMIFS(M$42:M$154,$F$42:$F$154,$E14) -> 4.3693943 | N14: =M14/$M$36 -> 0.024603598 | O14: =REPT("|",N14*(100/MAX($N$14:$N$35))) -> |||| | Q14: =SUMIFS(Q$42:Q$154,$F$42:$F$154,$E14) -> 2.6985
E15: 1.2 | G15: Combustions mobiles | I15: Émissions directes des sources de combustions mobiles | J15: =SUMIFS(J$42:J$154,$F$42:$F$154,$E15) -> 8.9848405 | K15: =SUMIFS(K$42:K$154,$F$42:$F$154,$E15) -> 0.058568735 | L15: =SUMIFS(L$42:L$154,$F$42:$F$154,$E15) -> 0.024714304 | M15: =SUMIFS(M$42:M$154,$F$42:$F$154,$E15) -> 9.0681236 | N15: =M15/$M$36 -> 0.051061647 | O15: =REPT("|",N15*(100/MAX($N$14:$N$35))) -> |||||||| | Q15: =SUMIFS(Q$42:Q$154,$F$42:$F$154,$E15) -> 0
E16: 1.3 | G16: Procédés | I16: Émissions directes provenant des procédés et élevages d'animaux | J16: =SUMIFS(J$42:J$154,$F$42:$F$154,$E16) -> 0 | K16: =SUMIFS(K$42:K$154,$F$42:$F$154,$E16) -> 0 | L16: =SUMIFS(L$42:L$154,$F$42:$F$154,$E16) -> 0 | M16: =SUMIFS(M$42:M$154,$F$42:$F$154,$E16) -> 0 | N16: =M16/$M$36 -> 0 | O16: =REPT("|",N16*(100/MAX($N$14:$N$35))) | Q16: =SUMIFS(Q$42:Q$154,$F$42:$F$154,$E16) -> 0
E17: 1.4 | G17: Émissions fugitives | I17: Émissions fugitives directes (Réfrigérants) | J17: =SUMIFS(J$42:J$154,$F$42:$F$154,$E17) -> 0 | K17: =SUMIFS(K$42:K$154,$F$42:$F$154,$E17) -> 0 | L17: =SUMIFS(L$42:L$154,$F$42:$F$154,$E17) -> 0 | M17: =SUMIFS(M$42:M$154,$F$42:$F$154,$E17) -> 6.9337082 | N17: =M17/$M$36 -> 0.039042979 | O17: =REPT("|",N17*(100/MAX($N$14:$N$35))) -> |||||| | Q17: =SUMIFS(Q$42:Q$154,$F$42:$F$154,$E17) -> 0
E18: 1.5 | G18: Usage des sols | I18: Émissions directes provenant de l'usage des sols (incluant agricoles) et de la foresterie | J18: =SUMIFS(J$42:J$154,$F$42:$F$154,$E18) -> 0 | K18: =SUMIFS(K$42:K$154,$F$42:$F$154,$E18) -> 0 | L18: =SUMIFS(L$42:L$154,$F$42:$F$154,$E18) -> 0 | M18: =SUMIFS(M$42:M$154,$F$42:$F$154,$E18) -> 0 | N18: =M18/$M$36 -> 0 | O18: =REPT("|",N18*(100/MAX($N$14:$N$35))) | Q18: =SUMIFS(Q$42:Q$154,$F$42:$F$154,$E18) -> 0
B19: Catégorie 2 | D19: Émissions indirects de l'énergie importée | E19: 2.1 | G19: Électricités | I19: Émissions indirectes provenant de la consommation d'électricité | J19: =SUMIFS(J$42:J$154,$F$42:$F$154,$E19) -> 1.5888821 | K19: =SUMIFS(K$42:K$154,$F$42:$F$154,$E19) -> 0.00095295221 | L19: =SUMIFS(L$42:L$154,$F$42:$F$154,$E19) -> 0.00095295221 | M19: =SUMIFS(M$42:M$154,$F$42:$F$154,$E19) -> 1.590788 | N19: =M19/$M$36 -> 0.0089575592 | O19: =REPT("|",N19*(100/MAX($N$14:$N$35))) -> | | Q19: =SUMIFS(Q$42:Q$154,$F$42:$F$154,$E19) -> 0
E20: 2.2 | G20: Autres énergies importées | I20: Émissions indirectes provenant de la consommation d'un réseau d'énergie (exclut l'électricité) | J20: =SUMIFS(J$42:J$154,$F$42:$F$154,$E20) -> 26.292 | K20: =SUMIFS(K$42:K$154,$F$42:$F$154,$E20) -> 0.0154364 | L20: =SUMIFS(L$42:L$154,$F$42:$F$154,$E20) -> 0.129948 | M20: =SUMIFS(M$42:M$154,$F$42:$F$154,$E20) -> 26.437384 | N20: =M20/$M$36 -> 0.14886612 | O20: =REPT("|",N20*(100/MAX($N$14:$N$35))) -> |||||||||||||||||||||||| | Q20: =SUMIFS(Q$42:Q$154,$F$42:$F$154,$E20) -> 0
B21: Catégorie 3 | D21: Émissions indirects des transports | E21: 3.1 | G21: Transport en amont | I21: Transport et distribution en amont | J21: =SUMIFS(J$42:J$154,$F$42:$F$154,$E21) -> 0 | K21: =SUMIFS(K$42:K$154,$F$42:$F$154,$E21) -> 0 | L21: =SUMIFS(L$42:L$154,$F$42:$F$154,$E21) -> 0 | M21: =SUMIFS(M$42:M$154,$F$42:$F$154,$E21) -> 0 | N21: =M21/$M$36 -> 0 | O21: =REPT("|",N21*(100/MAX($N$14:$N$35))) | Q21: =SUMIFS(Q$42:Q$154,$F$42:$F$154,$E21) -> 0
E22: 3.2 | G22: Transport en aval | I22: Transport et distribution des produits en aval | J22: =SUMIFS(J$42:J$154,$F$42:$F$154,$E22) -> 0 | K22: =SUMIFS(K$42:K$154,$F$42:$F$154,$E22) -> 0 | L22: =SUMIFS(L$42:L$154,$F$42:$F$154,$E22) -> 0 | M22: =SUMIFS(M$42:M$154,$F$42:$F$154,$E22) -> 0 | N22: =M22/$M$36 -> 0 | O22: =REPT("|",N22*(100/MAX($N$14:$N$35))) | Q22: =SUMIFS(Q$42:Q$154,$F$42:$F$154,$E22) -> 0
E23: 3.3 | G23: Navettage des employés | I23: Navettage des employés | J23: =SUMIFS(J$42:J$154,$F$42:$F$154,$E23) -> 5.3790753 | K23: =SUMIFS(K$42:K$154,$F$42:$F$154,$E23) -> 0.009721809 | L23: =SUMIFS(L$42:L$154,$F$42:$F$154,$E23) -> 0.014100091 | M23: =SUMIFS(M$42:M$154,$F$42:$F$154,$E23) -> 5.4028972 | N23: =M23/$M$36 -> 0.030423144 | O23: =REPT("|",N23*(100/MAX($N$14:$N$35))) -> |||| | Q23: =SUMIFS(Q$42:Q$154,$F$42:$F$154,$E23) -> 0
E24: 3.4 | G24: Déplacement des clients | I24: Déplacements des clients et des visiteurs | J24: =SUMIFS(J$42:J$154,$F$42:$F$154,$E24) -> 6.89053 | K24: =SUMIFS(K$42:K$154,$F$42:$F$154,$E24) -> 0.0020442082 | L24: =SUMIFS(L$42:L$154,$F$42:$F$154,$E24) -> 0.085885023 | M24: =SUMIFS(M$42:M$154,$F$42:$F$154,$E24) -> 6.9784593 | N24: =M24/$M$36 -> 0.039294968 | O24: =REPT("|",N24*(100/MAX($N$14:$N$35))) -> |||||| | Q24: =SUMIFS(Q$42:Q$154,$F$42:$F$154,$E24) -> 0
E25: 3.5 | G25: Déplacement d'affaires | I25: Déplacements d'affaires | J25: =SUMIFS(J$42:J$154,$F$42:$F$154,$E25) -> 7.5332462 | K25: =SUMIFS(K$42:K$154,$F$42:$F$154,$E25) -> 0.0029278893 | L25: =SUMIFS(L$42:L$154,$F$42:$F$154,$E25) -> 0.090214239 | M25: =SUMIFS(M$42:M$154,$F$42:$F$154,$E25) -> 7.6263883 | N25: =M25/$M$36 -> 0.042943388 | O25: =REPT("|",N25*(100/MAX($N$14:$N$35))) -> |||||| | Q25: =SUMIFS(Q$42:Q$154,$F$42:$F$154,$E25) -> 0
B26: Catégorie 4 | D26: Émissions indirects des produits utilisés par l'organisation | E26: 4.1 | G26: Biens et matière première | I26: Biens, matière première et énergie | J26: =SUMIFS(J$42:J$154,$F$42:$F$154,$E26) -> 109.16114 | K26: =SUMIFS(K$42:K$154,$F$42:$F$154,$E26) -> 0 | L26: =SUMIFS(L$42:L$154,$F$42:$F$154,$E26) -> 0 | M26: =SUMIFS(M$42:M$154,$F$42:$F$154,$E26) -> 109.16114 | N26: =M26/$M$36 -> 0.61467484 | O26: =REPT("|",N26*(100/MAX($N$14:$N$35))) -> |||||||||||||||||||||||||||||||||||||||||||||||||||||||||||||||||||||||||||||||||||||||||||||||||||| | Q26: =SUMIFS(Q$42:Q$154,$F$42:$F$154,$E26) -> 0
E27: 4.2 | G27: Biens immobiliés | I27: Biens immobiliers | J27: =SUMIFS(J$42:J$154,$F$42:$F$154,$E27) -> 0 | K27: =SUMIFS(K$42:K$154,$F$42:$F$154,$E27) -> 0 | L27: =SUMIFS(L$42:L$154,$F$42:$F$154,$E27) -> 0 | M27: =SUMIFS(M$42:M$154,$F$42:$F$154,$E27) -> 0 | N27: =M27/$M$36 -> 0 | O27: =REPT("|",N27*(100/MAX($N$14:$N$35))) | Q27: =SUMIFS(Q$42:Q$154,$F$42:$F$154,$E27) -> 0
E28: 4.3 | G28: Déchets | I28: Déchets | J28: =SUMIFS(J$42:J$154,$F$42:$F$154,$E28) -> 0 | K28: =SUMIFS(K$42:K$154,$F$42:$F$154,$E28) -> 0.023397962 | L28: =SUMIFS(L$42:L$154,$F$42:$F$154,$E28) -> 0 | M28: =SUMIFS(M$42:M$154,$F$42:$F$154,$E28) -> 0.023397962 | N28: =M28/$M$36 -> 0.00013175146 | O28: =REPT("|",N28*(100/MAX($N$14:$N$35))) | Q28: =SUMIFS(Q$42:Q$154,$F$42:$F$154,$E28) -> 0
E29: 4.4 | G29: Location d'actifs en amont | I29: Location d'actif en amont | J29: =SUMIFS(J$42:J$154,$F$42:$F$154,$E29) -> 0 | K29: =SUMIFS(K$42:K$154,$F$42:$F$154,$E29) -> 0 | L29: =SUMIFS(L$42:L$154,$F$42:$F$154,$E29) -> 0 | M29: =SUMIFS(M$42:M$154,$F$42:$F$154,$E29) -> 0 | N29: =M29/$M$36 -> 0 | O29: =REPT("|",N29*(100/MAX($N$14:$N$35))) | Q29: =SUMIFS(Q$42:Q$154,$F$42:$F$154,$E29) -> 0
E30: 4.5 | G30: Services | I30: Services | J30: =SUMIFS(J$42:J$154,$F$42:$F$154,$E30) -> 0 | K30: =SUMIFS(K$42:K$154,$F$42:$F$154,$E30) -> 0 | L30: =SUMIFS(L$42:L$154,$F$42:$F$154,$E30) -> 0 | M30: =SUMIFS(M$42:M$154,$F$42:$F$154,$E30) -> 0 | N30: =M30/$M$36 -> 0 | O30: =REPT("|",N30*(100/MAX($N$14:$N$35))) | Q30: =SUMIFS(Q$42:Q$154,$F$42:$F$154,$E30) -> 0
B31: Catégorie5 | D31: Émissions indirects à l'utilisation des produits de l'organisation | E31: 5.1 | G31: Utilisation des produits | I31: Utilisation des produits vendus | J31: =SUMIFS(J$42:J$154,$F$42:$F$154,$E31) -> 0 | K31: =SUMIFS(K$42:K$154,$F$42:$F$154,$E31) -> 0 | L31: =SUMIFS(L$42:L$154,$F$42:$F$154,$E31) -> 0 | M31: =SUMIFS(M$42:M$154,$F$42:$F$154,$E31) -> 0 | N31: =M31/$M$36 -> 0 | O31: =REPT("|",N31*(100/MAX($N$14:$N$35))) | Q31: =SUMIFS(Q$42:Q$154,$F$42:$F$154,$E31) -> 0
E32: 5.2 | G32: Location d'actifs en aval | I32: Location d'actif en aval | J32: =SUMIFS(J$42:J$154,$F$42:$F$154,$E32) -> 0 | K32: =SUMIFS(K$42:K$154,$F$42:$F$154,$E32) -> 0 | L32: =SUMIFS(L$42:L$154,$F$42:$F$154,$E32) -> 0 | M32: =SUMIFS(M$42:M$154,$F$42:$F$154,$E32) -> 0 | N32: =M32/$M$36 -> 0 | O32: =REPT("|",N32*(100/MAX($N$14:$N$35))) | Q32: =SUMIFS(Q$42:Q$154,$F$42:$F$154,$E32) -> 0
E33: 5.3 | G33: Fin de vie des produits | I33: Fin de vie des produits | J33: =SUMIFS(J$42:J$154,$F$42:$F$154,$E33) -> 0 | K33: =SUMIFS(K$42:K$154,$F$42:$F$154,$E33) -> 0 | L33: =SUMIFS(L$42:L$154,$F$42:$F$154,$E33) -> 0 | M33: =SUMIFS(M$42:M$154,$F$42:$F$154,$E33) -> 0 | N33: =M33/$M$36 -> 0 | O33: =REPT("|",N33*(100/MAX($N$14:$N$35))) | Q33: =SUMIFS(Q$42:Q$154,$F$42:$F$154,$E33) -> 0
E34: 5.4 | G34: Investissements | I34: Investissement | J34: =SUMIFS(J$42:J$154,$F$42:$F$154,$E34) -> 0 | K34: =SUMIFS(K$42:K$154,$F$42:$F$154,$E34) -> 0 | L34: =SUMIFS(L$42:L$154,$F$42:$F$154,$E34) -> 0 | M34: =SUMIFS(M$42:M$154,$F$42:$F$154,$E34) -> 0 | N34: =M34/$M$36 -> 0 | O34: =REPT("|",N34*(100/MAX($N$14:$N$35))) | Q34: =SUMIFS(Q$42:Q$154,$F$42:$F$154,$E34) -> 0
B35: Catégorie 6 | D35: Autres émissions indirects | E35: 6 | G35: Autres | I35: Autres | J35: =SUMIFS(J$42:J$154,$F$42:$F$154,$E35) -> 0 | K35: =SUMIFS(K$42:K$154,$F$42:$F$154,$E35) -> 0 | L35: =SUMIFS(L$42:L$154,$F$42:$F$154,$E35) -> 0 | M35: =SUMIFS(M$42:M$154,$F$42:$F$154,$E35) -> 0 | N35: =M35/$M$36 -> 0 | O35: =REPT("|",N35*(100/MAX($N$14:$N$35))) | Q35: =SUMIFS(Q$42:Q$154,$F$42:$F$154,$E35) -> 0
I36: Totaux : | J36: =SUM(J14:J35) -> 170.09771 | K36: =SUM(K14:K35) -> 0.14496576 | L36: =SUM(L14:L35) -> 0.41529311 | M36: =SUM(M14:M35) -> 177.59168 | N36: tCO2e | Q36: =SUM(Q14:Q35) -> 2.6985
B38: Bilan (Détaillé par méthodologie) | Q38: CO2 Biogénique | S38: État d'inventaire | V38: Bilan détaillé par mois, site et/ou produit
V39: Mois | W39: Site | X39: Produit ou service
V40: Tous | W40: Bureau | X40: Tous
B41: Categorie | E41: Sous-catégorie | H41: # de méthode | I41: Description | J41: CO2 [tCO2e] | K41: CH4 [tCO2e] | L41: N2O [tCO2e] | M41: Total tCO2e | N41: % | O41: Bar % | W41: Total tCO2e | X41: % | Y41: Bar %
B42: Catégorie 1 | C42: =IF(B42=0,C41,B42) -> Catégorie 1 | D42: Émissions directs | E42: 1.1 | F42: =IF(E42=0,F41,E42) -> 1.1 | G42: Combustions fixes | H42: 1.1A1 | I42: =Calculs!B5 -> 1.1A1 - Chauffage des bâtiments et équipements fixes | J42: =SUMIFS(Calculs!BY$11:BY$1338,Calculs!$B$11:$B$1338,$H42)/10^6 -> 4.268 | K42: =SUMIFS(Calculs!BZ$11:BZ$1338,Calculs!$B$11:$B$1338,$H42)/10^6 -> 0.0319158 | L42: =SUMIFS(Calculs!CA$11:CA$1338,Calculs!$B$11:$B$1338,$H42)/10^6 -> 0.0694785 | M42: =SUMIFS(Calculs!CB$11:CB$1338,Calculs!$B$11:$B$1338,$H42)/10^6 -> 4.3693943 | N42: =M42/$M$155 -> 0.024603598 | O42: =REPT("|",N42*(100/MAX($N$14:$N$35))) -> |||| | Q42: =Calculs!CF31 -> 2.6985 | W42: =(SUMIFS(Calculs!CB$11:CB$1338,Calculs!$B$11:$B$1338,$H42,Calculs!$F$11:$F$1338,IF($V$40="Tous","<>0",VLOOKUP($V$40,'Listes déroulantes, autres'!$H$9:$I$21,2,FALSE)),Calculs!$G$11:$G$1338,IF($W$40="Tous","<>0",$W$40),Calculs!$H$11:$H$1338,IF($X$40="Tous","<>0",$X$40) )/10^6) -> 0.0572787 | X42: =W42/$M$155 -> 0.00032253032 | Y42: =REPT("|",X42*(100/MAX($N$14:$N$35)))
C43: =IF(B43=0,C42,B43) -> Catégorie 1 | F43: =IF(E43=0,F42,E43) -> 1.1 | H43: 1.1A2 | J43: =SUMIFS(Calculs!BY$11:BY$1338,Calculs!$B$11:$B$1338,$H43)/10^6 -> 0 | K43: =SUMIFS(Calculs!BZ$11:BZ$1338,Calculs!$B$11:$B$1338,$H43)/10^6 -> 0 | L43: =SUMIFS(Calculs!CA$11:CA$1338,Calculs!$B$11:$B$1338,$H43)/10^6 -> 0 | M43: =SUMIFS(Calculs!CB$11:CB$1338,Calculs!$B$11:$B$1338,$H43)/10^6 -> 0 | N43: =M43/$M$155 -> 0 | O43: =REPT("|",N43*(100/MAX($N$14:$N$35))) | W43: =(SUMIFS(Calculs!CB$11:CB$1338,Calculs!$B$11:$B$1338,$H43,Calculs!$F$11:$F$1338,IF($V$40="Tous","<>0",VLOOKUP($V$40,'Listes déroulantes, autres'!$H$9:$I$21,2,FALSE)),Calculs!$G$11:$G$1338,IF($W$40="Tous","<>0",$W$40),Calculs!$H$11:$H$1338,IF($X$40="Tous","<>0",$X$40) )/10^6) -> 0 | X43: =W43/$M$155 -> 0 | Y43: =REPT("|",X43*(100/MAX($N$14:$N$35)))
C44: =IF(B44=0,C43,B44) -> Catégorie 1 | E44: 1.2 | F44: =IF(E44=0,F43,E44) -> 1.2 | G44: Combustions mobiles | H44: 1.2A1 | I44: =Calculs!B33 -> 1.2A1 - Véhicules (Par la quantité de combustible consommée) | J44: =SUMIFS(Calculs!BY$11:BY$1338,Calculs!$B$11:$B$1338,$H44)/10^6 -> 2.4447387 | K44: =SUMIFS(Calculs!BZ$11:BZ$1338,Calculs!$B$11:$B$1338,$H44)/10^6 -> 0.0050379848 | L44: =SUMIFS(Calculs!CA$11:CA$1338,Calculs!$B$11:$B$1338,$H44)/10^6 -> 0.0026044528 | M44: =SUMIFS(Calculs!CB$11:CB$1338,Calculs!$B$11:$B$1338,$H44)/10^6 -> 2.4523811 | N44: =M44/$M$155 -> 0.013809099 | O44: =REPT("|",N44*(100/MAX($N$14:$N$35))) -> || | W44: =(SUMIFS(Calculs!CB$11:CB$1338,Calculs!$B$11:$B$1338,$H44,Calculs!$F$11:$F$1338,IF($V$40="Tous","<>0",VLOOKUP($V$40,'Listes déroulantes, autres'!$H$9:$I$21,2,FALSE)),Calculs!$G$11:$G$1338,IF($W$40="Tous","<>0",$W$40),Calculs!$H$11:$H$1338,IF($X$40="Tous","<>0",$X$40) )/10^6) -> 2.3125188 | X44: =W44/$M$155 -> 0.013021549 | Y44: =REPT("|",X44*(100/MAX($N$14:$N$35))) -> ||
C45: =IF(B45=0,C44,B45) -> Catégorie 1 | F45: =IF(E45=0,F44,E45) -> 1.2 | H45: 1.2A2 | I45: =Calculs!B58 -> 1.2A2 - Véhicules (Par la distance parcourue; Consommation L/100km) | J45: =SUMIFS(Calculs!BY$11:BY$1338,Calculs!$B$11:$B$1338,$H45)/10^6 -> 5.5125363 | K45: =SUMIFS(Calculs!BZ$11:BZ$1338,Calculs!$B$11:$B$1338,$H45)/10^6 -> 0.04623164 | L45: =SUMIFS(Calculs!CA$11:CA$1338,Calculs!$B$11:$B$1338,$H45)/10^6 -> 0.019056221 | M45: =SUMIFS(Calculs!CB$11:CB$1338,Calculs!$B$11:$B$1338,$H45)/10^6 -> 5.5778241 | N45: =M45/$M$155 -> 0.031408139 | O45: =REPT("|",N45*(100/MAX($N$14:$N$35))) -> ||||| | W45: =(SUMIFS(Calculs!CB$11:CB$1338,Calculs!$B$11:$B$1338,$H45,Calculs!$F$11:$F$1338,IF($V$40="Tous","<>0",VLOOKUP($V$40,'Listes déroulantes, autres'!$H$9:$I$21,2,FALSE)),Calculs!$G$11:$G$1338,IF($W$40="Tous","<>0",$W$40),Calculs!$H$11:$H$1338,IF($X$40="Tous","<>0",$X$40) )/10^6) -> 0 | X45: =W45/$M$155 -> 0 | Y45: =REPT("|",X45*(100/MAX($N$14:$N$35)))
C46: =IF(B46=0,C45,B46) -> Catégorie 1 | F46: =IF(E46=0,F45,E46) -> 1.2 | H46: 1.2A3 | I46: =Calculs!B76 -> 1.2A3 - Véhicules (Par les coûts de carburants) | J46: =SUMIFS(Calculs!BY$11:BY$1338,Calculs!$B$11:$B$1338,$H46)/10^6 -> 1.0275656 | K46: =SUMIFS(Calculs!BZ$11:BZ$1338,Calculs!$B$11:$B$1338,$H46)/10^6 -> 0.0072991104 | L46: =SUMIFS(Calculs!CA$11:CA$1338,Calculs!$B$11:$B$1338,$H46)/10^6 -> 0.0030536298 | M46: =SUMIFS(Calculs!CB$11:CB$1338,Calculs!$B$11:$B$1338,$H46)/10^6 -> 1.0379183 | N46: =M46/$M$155 -> 0.0058444085 | O46: =REPT("|",N46*(100/MAX($N$14:$N$35))) | W46: =(SUMIFS(Calculs!CB$11:CB$1338,Calculs!$B$11:$B$1338,$H46,Calculs!$F$11:$F$1338,IF($V$40="Tous","<>0",VLOOKUP($V$40,'Listes déroulantes, autres'!$H$9:$I$21,2,FALSE)),Calculs!$G$11:$G$1338,IF($W$40="Tous","<>0",$W$40),Calculs!$H$11:$H$1338,IF($X$40="Tous","<>0",$X$40) )/10^6) -> 0 | X46: =W46/$M$155 -> 0 | Y46: =REPT("|",X46*(100/MAX($N$14:$N$35)))
C47: =IF(B47=0,C46,B47) -> Catégorie 1 | F47: =IF(E47=0,F46,E47) -> 1.2 | H47: 1.2B1 | I47: =Calculs!B94 -> 1.2B1 - Véhicules (Par la distance parcourue; Données Canadiennes) | J47: =SUMIFS(Calculs!BY$11:BY$1338,Calculs!$B$11:$B$1338,$H47)/10^6 -> 0 | K47: =SUMIFS(Calculs!BZ$11:BZ$1338,Calculs!$B$11:$B$1338,$H47)/10^6 -> 0 | L47: =SUMIFS(Calculs!CA$11:CA$1338,Calculs!$B$11:$B$1338,$H47)/10^6 -> 0 | M47: =SUMIFS(Calculs!CB$11:CB$1338,Calculs!$B$11:$B$1338,$H47)/10^6 -> 0 | N47: =M47/$M$155 -> 0 | O47: =REPT("|",N47*(100/MAX($N$14:$N$35))) | W47: =(SUMIFS(Calculs!CB$11:CB$1338,Calculs!$B$11:$B$1338,$H47,Calculs!$F$11:$F$1338,IF($V$40="Tous","<>0",VLOOKUP($V$40,'Listes déroulantes, autres'!$H$9:$I$21,2,FALSE)),Calculs!$G$11:$G$1338,IF($W$40="Tous","<>0",$W$40),Calculs!$H$11:$H$1338,IF($X$40="Tous","<>0",$X$40) )/10^6) -> 0 | X47: =W47/$M$155 -> 0 | Y47: =REPT("|",X47*(100/MAX($N$14:$N$35)))
C48: =IF(B48=0,C47,B48) -> Catégorie 1 | E48: 1.3 | F48: =IF(E48=0,F47,E48) -> 1.3 | G48: Procédés | H48: 1.3A1 | I48: (Déplacer vers 1.4) | J48: =SUMIFS(Calculs!BY$11:BY$1338,Calculs!$B$11:$B$1338,$H48)/10^6 -> 0 | K48: =SUMIFS(Calculs!BZ$11:BZ$1338,Calculs!$B$11:$B$1338,$H48)/10^6 -> 0 | L48: =SUMIFS(Calculs!CA$11:CA$1338,Calculs!$B$11:$B$1338,$H48)/10^6 -> 0 | M48: =SUMIFS(Calculs!CB$11:CB$1338,Calculs!$B$11:$B$1338,$H48)/10^6 -> 0 | N48: =M48/$M$155 -> 0 | O48: =REPT("|",N48*(100/MAX($N$14:$N$35))) | W48: =(SUMIFS(Calculs!CB$11:CB$1338,Calculs!$B$11:$B$1338,$H48,Calculs!$F$11:$F$1338,IF($V$40="Tous","<>0",VLOOKUP($V$40,'Listes déroulantes, autres'!$H$9:$I$21,2,FALSE)),Calculs!$G$11:$G$1338,IF($W$40="Tous","<>0",$W$40),Calculs!$H$11:$H$1338,IF($X$40="Tous","<>0",$X$40) )/10^6) -> 0 | X48: =W48/$M$155 -> 0 | Y48: =REPT("|",X48*(100/MAX($N$14:$N$35)))
C49: =IF(B49=0,C48,B49) -> Catégorie 1 | F49: =IF(E49=0,F48,E49) -> 1.3 | H49: 1.3B1 | I49: (Déplacer vers 1.4) | J49: =SUMIFS(Calculs!BY$11:BY$1338,Calculs!$B$11:$B$1338,$H49)/10^6 -> 0 | K49: =SUMIFS(Calculs!BZ$11:BZ$1338,Calculs!$B$11:$B$1338,$H49)/10^6 -> 0 | L49: =SUMIFS(Calculs!CA$11:CA$1338,Calculs!$B$11:$B$1338,$H49)/10^6 -> 0 | M49: =SUMIFS(Calculs!CB$11:CB$1338,Calculs!$B$11:$B$1338,$H49)/10^6 -> 0 | N49: =M49/$M$155 -> 0 | O49: =REPT("|",N49*(100/MAX($N$14:$N$35))) | W49: =(SUMIFS(Calculs!CB$11:CB$1338,Calculs!$B$11:$B$1338,$H49,Calculs!$F$11:$F$1338,IF($V$40="Tous","<>0",VLOOKUP($V$40,'Listes déroulantes, autres'!$H$9:$I$21,2,FALSE)),Calculs!$G$11:$G$1338,IF($W$40="Tous","<>0",$W$40),Calculs!$H$11:$H$1338,IF($X$40="Tous","<>0",$X$40) )/10^6) -> 0 | X49: =W49/$M$155 -> 0 | Y49: =REPT("|",X49*(100/MAX($N$14:$N$35)))
C50: =IF(B50=0,C49,B50) -> Catégorie 1 | F50: =IF(E50=0,F49,E50) -> 1.3 | H50: 1.3B2 | I50: (Déplacer vers 1.4) | J50: =SUMIFS(Calculs!BY$11:BY$1338,Calculs!$B$11:$B$1338,$H50)/10^6 -> 0 | K50: =SUMIFS(Calculs!BZ$11:BZ$1338,Calculs!$B$11:$B$1338,$H50)/10^6 -> 0 | L50: =SUMIFS(Calculs!CA$11:CA$1338,Calculs!$B$11:$B$1338,$H50)/10^6 -> 0 | M50: =SUMIFS(Calculs!CB$11:CB$1338,Calculs!$B$11:$B$1338,$H50)/10^6 -> 0 | N50: =M50/$M$155 -> 0 | O50: =REPT("|",N50*(100/MAX($N$14:$N$35))) | W50: =(SUMIFS(Calculs!CB$11:CB$1338,Calculs!$B$11:$B$1338,$H50,Calculs!$F$11:$F$1338,IF($V$40="Tous","<>0",VLOOKUP($V$40,'Listes déroulantes, autres'!$H$9:$I$21,2,FALSE)),Calculs!$G$11:$G$1338,IF($W$40="Tous","<>0",$W$40),Calculs!$H$11:$H$1338,IF($X$40="Tous","<>0",$X$40) )/10^6) -> 0 | X50: =W50/$M$155 -> 0 | Y50: =REPT("|",X50*(100/MAX($N$14:$N$35)))
C51: =IF(B51=0,C50,B51) -> Catégorie 1 | F51: =IF(E51=0,F50,E51) -> 1.3 | H51: 1.3C1 | I51: (Déplacer vers 1.4) | J51: =SUMIFS(Calculs!BY$11:BY$1338,Calculs!$B$11:$B$1338,$H51)/10^6 -> 0 | K51: =SUMIFS(Calculs!BZ$11:BZ$1338,Calculs!$B$11:$B$1338,$H51)/10^6 -> 0 | L51: =SUMIFS(Calculs!CA$11:CA$1338,Calculs!$B$11:$B$1338,$H51)/10^6 -> 0 | M51: =SUMIFS(Calculs!CB$11:CB$1338,Calculs!$B$11:$B$1338,$H51)/10^6 -> 0 | N51: =M51/$M$155 -> 0 | O51: =REPT("|",N51*(100/MAX($N$14:$N$35))) | W51: =(SUMIFS(Calculs!CB$11:CB$1338,Calculs!$B$11:$B$1338,$H51,Calculs!$F$11:$F$1338,IF($V$40="Tous","<>0",VLOOKUP($V$40,'Listes déroulantes, autres'!$H$9:$I$21,2,FALSE)),Calculs!$G$11:$G$1338,IF($W$40="Tous","<>0",$W$40),Calculs!$H$11:$H$1338,IF($X$40="Tous","<>0",$X$40) )/10^6) -> 0 | X51: =W51/$M$155 -> 0 | Y51: =REPT("|",X51*(100/MAX($N$14:$N$35)))
C52: =IF(B52=0,C51,B52) -> Catégorie 1 | F52: =IF(E52=0,F51,E52) -> 1.3 | H52: 1.3D1 | J52: =SUMIFS(Calculs!BY$11:BY$1338,Calculs!$B$11:$B$1338,$H52)/10^6 -> 0 | K52: =SUMIFS(Calculs!BZ$11:BZ$1338,Calculs!$B$11:$B$1338,$H52)/10^6 -> 0 | L52: =SUMIFS(Calculs!CA$11:CA$1338,Calculs!$B$11:$B$1338,$H52)/10^6 -> 0 | M52: =SUMIFS(Calculs!CB$11:CB$1338,Calculs!$B$11:$B$1338,$H52)/10^6 -> 0 | N52: =M52/$M$155 -> 0 | O52: =REPT("|",N52*(100/MAX($N$14:$N$35))) | W52: =(SUMIFS(Calculs!CB$11:CB$1338,Calculs!$B$11:$B$1338,$H52,Calculs!$F$11:$F$1338,IF($V$40="Tous","<>0",VLOOKUP($V$40,'Listes déroulantes, autres'!$H$9:$I$21,2,FALSE)),Calculs!$G$11:$G$1338,IF($W$40="Tous","<>0",$W$40),Calculs!$H$11:$H$1338,IF($X$40="Tous","<>0",$X$40) )/10^6) -> 0 | X52: =W52/$M$155 -> 0 | Y52: =REPT("|",X52*(100/MAX($N$14:$N$35)))
C53: =IF(B53=0,C52,B53) -> Catégorie 1 | E53: 1.4 | F53: =IF(E53=0,F52,E53) -> 1.4 | G53: Émissions fugitives | H53: 1.4A1 | I53: =Calculs!B112 -> 1.4A1 - Équipement de réfrigération et de climatisation fixe | J53: =SUMIFS(Calculs!BY$11:BY$1338,Calculs!$B$11:$B$1338,$H53)/10^6 -> 0 | K53: =SUMIFS(Calculs!BZ$11:BZ$1338,Calculs!$B$11:$B$1338,$H53)/10^6 -> 0 | L53: =SUMIFS(Calculs!CA$11:CA$1338,Calculs!$B$11:$B$1338,$H53)/10^6 -> 0 | M53: =SUMIFS(Calculs!CB$11:CB$1338,Calculs!$B$11:$B$1338,$H53)/10^6 -> 6.6568354 | N53: =M53/$M$155 -> 0.037483938 | O53: =REPT("|",N53*(100/MAX($N$14:$N$35))) -> |||||| | W53: =(SUMIFS(Calculs!CB$11:CB$1338,Calculs!$B$11:$B$1338,$H53,Calculs!$F$11:$F$1338,IF($V$40="Tous","<>0",VLOOKUP($V$40,'Listes déroulantes, autres'!$H$9:$I$21,2,FALSE)),Calculs!$G$11:$G$1338,IF($W$40="Tous","<>0",$W$40),Calculs!$H$11:$H$1338,IF($X$40="Tous","<>0",$X$40) )/10^6) -> 0.16266276 | X53: =W53/$M$155 -> 0.00091593684 | Y53: =REPT("|",X53*(100/MAX($N$14:$N$35)))
C54: =IF(B54=0,C53,B54) -> Catégorie 1 | F54: =IF(E54=0,F53,E54) -> 1.4 | H54: 1.4A2 | J54: =SUMIFS(Calculs!BY$11:BY$1338,Calculs!$B$11:$B$1338,$H54)/10^6 -> 0 | K54: =SUMIFS(Calculs!BZ$11:BZ$1338,Calculs!$B$11:$B$1338,$H54)/10^6 -> 0 | L54: =SUMIFS(Calculs!CA$11:CA$1338,Calculs!$B$11:$B$1338,$H54)/10^6 -> 0 | M54: =SUMIFS(Calculs!CB$11:CB$1338,Calculs!$B$11:$B$1338,$H54)/10^6 -> 0 | N54: =M54/$M$155 -> 0 | O54: =REPT("|",N54*(100/MAX($N$14:$N$35))) | W54: =(SUMIFS(Calculs!CB$11:CB$1338,Calculs!$B$11:$B$1338,$H54,Calculs!$F$11:$F$1338,IF($V$40="Tous","<>0",VLOOKUP($V$40,'Listes déroulantes, autres'!$H$9:$I$21,2,FALSE)),Calculs!$G$11:$G$1338,IF($W$40="Tous","<>0",$W$40),Calculs!$H$11:$H$1338,IF($X$40="Tous","<>0",$X$40) )/10^6) -> 0 | X54: =W54/$M$155 -> 0 | Y54: =REPT("|",X54*(100/MAX($N$14:$N$35)))
C55: =IF(B55=0,C54,B55) -> Catégorie 1 | F55: =IF(E55=0,F54,E55) -> 1.4 | H55: 1.4B1 | I55: =Calculs!B130 -> 1.4B1 - Climatisation du flotte de véhicules | J55: =SUMIFS(Calculs!BY$11:BY$1338,Calculs!$B$11:$B$1338,$H55)/10^6 -> 0 | K55: =SUMIFS(Calculs!BZ$11:BZ$1338,Calculs!$B$11:$B$1338,$H55)/10^6 -> 0 | L55: =SUMIFS(Calculs!CA$11:CA$1338,Calculs!$B$11:$B$1338,$H55)/10^6 -> 0 | M55: =SUMIFS(Calculs!CB$11:CB$1338,Calculs!$B$11:$B$1338,$H55)/10^6 -> 0 | N55: =M55/$M$155 -> 0 | O55: =REPT("|",N55*(100/MAX($N$14:$N$35))) | W55: =(SUMIFS(Calculs!CB$11:CB$1338,Calculs!$B$11:$B$1338,$H55,Calculs!$F$11:$F$1338,IF($V$40="Tous","<>0",VLOOKUP($V$40,'Listes déroulantes, autres'!$H$9:$I$21,2,FALSE)),Calculs!$G$11:$G$1338,IF($W$40="Tous","<>0",$W$40),Calculs!$H$11:$H$1338,IF($X$40="Tous","<>0",$X$40) )/10^6) -> 0 | X55: =W55/$M$155 -> 0 | Y55: =REPT("|",X55*(100/MAX($N$14:$N$35)))
C56: =IF(B56=0,C55,B56) -> Catégorie 1 | F56: =IF(E56=0,F55,E56) -> 1.4 | H56: 1.4B2 | I56: =Calculs!B139 -> 1.4B2 - Climatisation des véhicules | J56: =SUMIFS(Calculs!BY$11:BY$1338,Calculs!$B$11:$B$1338,$H56)/10^6 -> 0 | K56: =SUMIFS(Calculs!BZ$11:BZ$1338,Calculs!$B$11:$B$1338,$H56)/10^6 -> 0 | L56: =SUMIFS(Calculs!CA$11:CA$1338,Calculs!$B$11:$B$1338,$H56)/10^6 -> 0 | M56: =SUMIFS(Calculs!CB$11:CB$1338,Calculs!$B$11:$B$1338,$H56)/10^6 -> 0.27687278 | N56: =M56/$M$155 -> 0.0015590414 | O56: =REPT("|",N56*(100/MAX($N$14:$N$35))) | W56: =(SUMIFS(Calculs!CB$11:CB$1338,Calculs!$B$11:$B$1338,$H56,Calculs!$F$11:$F$1338,IF($V$40="Tous","<>0",VLOOKUP($V$40,'Listes déroulantes, autres'!$H$9:$I$21,2,FALSE)),Calculs!$G$11:$G$1338,IF($W$40="Tous","<>0",$W$40),Calculs!$H$11:$H$1338,IF($X$40="Tous","<>0",$X$40) )/10^6) -> 0 | X56: =W56/$M$155 -> 0 | Y56: =REPT("|",X56*(100/MAX($N$14:$N$35)))
C57: =IF(B57=0,C56,B57) -> Catégorie 1 | F57: =IF(E57=0,F56,E57) -> 1.4 | H57: 1.4C1 | I57: (Ancien 3A1) | J57: =SUMIFS(Calculs!BY$11:BY$1338,Calculs!$B$11:$B$1338,$H57)/10^6 -> 0 | K57: =SUMIFS(Calculs!BZ$11:BZ$1338,Calculs!$B$11:$B$1338,$H57)/10^6 -> 0 | L57: =SUMIFS(Calculs!CA$11:CA$1338,Calculs!$B$11:$B$1338,$H57)/10^6 -> 0 | M57: =SUMIFS(Calculs!CB$11:CB$1338,Calculs!$B$11:$B$1338,$H57)/10^6 -> 0 | N57: =M57/$M$155 -> 0 | O57: =REPT("|",N57*(100/MAX($N$14:$N$35))) | W57: =(SUMIFS(Calculs!CB$11:CB$1338,Calculs!$B$11:$B$1338,$H57,Calculs!$F$11:$F$1338,IF($V$40="Tous","<>0",VLOOKUP($V$40,'Listes déroulantes, autres'!$H$9:$I$21,2,FALSE)),Calculs!$G$11:$G$1338,IF($W$40="Tous","<>0",$W$40),Calculs!$H$11:$H$1338,IF($X$40="Tous","<>0",$X$40) )/10^6) -> 0 | X57: =W57/$M$155 -> 0 | Y57: =REPT("|",X57*(100/MAX($N$14:$N$35)))
C58: =IF(B58=0,C57,B58) -> Catégorie 1 | F58: =IF(E58=0,F57,E58) -> 1.4 | H58: 1.4D1 | I58: (Ancien 3B1) | J58: =SUMIFS(Calculs!BY$11:BY$1338,Calculs!$B$11:$B$1338,$H58)/10^6 -> 0 | K58: =SUMIFS(Calculs!BZ$11:BZ$1338,Calculs!$B$11:$B$1338,$H58)/10^6 -> 0 | L58: =SUMIFS(Calculs!CA$11:CA$1338,Calculs!$B$11:$B$1338,$H58)/10^6 -> 0 | M58: =SUMIFS(Calculs!CB$11:CB$1338,Calculs!$B$11:$B$1338,$H58)/10^6 -> 0 | N58: =M58/$M$155 -> 0 | O58: =REPT("|",N58*(100/MAX($N$14:$N$35))) | W58: =(SUMIFS(Calculs!CB$11:CB$1338,Calculs!$B$11:$B$1338,$H58,Calculs!$F$11:$F$1338,IF($V$40="Tous","<>0",VLOOKUP($V$40,'Listes déroulantes, autres'!$H$9:$I$21,2,FALSE)),Calculs!$G$11:$G$1338,IF($W$40="Tous","<>0",$W$40),Calculs!$H$11:$H$1338,IF($X$40="Tous","<>0",$X$40) )/10^6) -> 0 | X58: =W58/$M$155 -> 0 | Y58: =REPT("|",X58*(100/MAX($N$14:$N$35)))
C59: =IF(B59=0,C58,B59) -> Catégorie 1 | F59: =IF(E59=0,F58,E59) -> 1.4 | H59: 1.4D2 | I59: (Ancien 3B2) | J59: =SUMIFS(Calculs!BY$11:BY$1338,Calculs!$B$11:$B$1338,$H59)/10^6 -> 0 | K59: =SUMIFS(Calculs!BZ$11:BZ$1338,Calculs!$B$11:$B$1338,$H59)/10^6 -> 0 | L59: =SUMIFS(Calculs!CA$11:CA$1338,Calculs!$B$11:$B$1338,$H59)/10^6 -> 0 | M59: =SUMIFS(Calculs!CB$11:CB$1338,Calculs!$B$11:$B$1338,$H59)/10^6 -> 0 | N59: =M59/$M$155 -> 0 | O59: =REPT("|",N59*(100/MAX($N$14:$N$35))) | W59: =(SUMIFS(Calculs!CB$11:CB$1338,Calculs!$B$11:$B$1338,$H59,Calculs!$F$11:$F$1338,IF($V$40="Tous","<>0",VLOOKUP($V$40,'Listes déroulantes, autres'!$H$9:$I$21,2,FALSE)),Calculs!$G$11:$G$1338,IF($W$40="Tous","<>0",$W$40),Calculs!$H$11:$H$1338,IF($X$40="Tous","<>0",$X$40) )/10^6) -> 0 | X59: =W59/$M$155 -> 0 | Y59: =REPT("|",X59*(100/MAX($N$14:$N$35)))
C60: =IF(B60=0,C59,B60) -> Catégorie 1 | F60: =IF(E60=0,F59,E60) -> 1.4 | H60: 1.4E1 | I60: (Ancien 3C1) | J60: =SUMIFS(Calculs!BY$11:BY$1338,Calculs!$B$11:$B$1338,$H60)/10^6 -> 0 | K60: =SUMIFS(Calculs!BZ$11:BZ$1338,Calculs!$B$11:$B$1338,$H60)/10^6 -> 0 | L60: =SUMIFS(Calculs!CA$11:CA$1338,Calculs!$B$11:$B$1338,$H60)/10^6 -> 0 | M60: =SUMIFS(Calculs!CB$11:CB$1338,Calculs!$B$11:$B$1338,$H60)/10^6 -> 0 | N60: =M60/$M$155 -> 0 | O60: =REPT("|",N60*(100/MAX($N$14:$N$35))) | W60: =(SUMIFS(Calculs!CB$11:CB$1338,Calculs!$B$11:$B$1338,$H60,Calculs!$F$11:$F$1338,IF($V$40="Tous","<>0",VLOOKUP($V$40,'Listes déroulantes, autres'!$H$9:$I$21,2,FALSE)),Calculs!$G$11:$G$1338,IF($W$40="Tous","<>0",$W$40),Calculs!$H$11:$H$1338,IF($X$40="Tous","<>0",$X$40) )/10^6) -> 0 | X60: =W60/$M$155 -> 0 | Y60: =REPT("|",X60*(100/MAX($N$14:$N$35)))
C61: =IF(B61=0,C55,B61) -> Catégorie 1 | E61: 1.5 | F61: =IF(E61=0,F56,E61) -> 1.5 | G61: Usage des sols | H61: 1.5A1 | J61: =SUMIFS(Calculs!BY$11:BY$1338,Calculs!$B$11:$B$1338,$H61)/10^6 -> 0 | K61: =SUMIFS(Calculs!BZ$11:BZ$1338,Calculs!$B$11:$B$1338,$H61)/10^6 -> 0 | L61: =SUMIFS(Calculs!CA$11:CA$1338,Calculs!$B$11:$B$1338,$H61)/10^6 -> 0 | M61: =SUMIFS(Calculs!CB$11:CB$1338,Calculs!$B$11:$B$1338,$H61)/10^6 -> 0 | N61: =M61/$M$155 -> 0 | O61: =REPT("|",N61*(100/MAX($N$14:$N$35))) | W61: =(SUMIFS(Calculs!CB$11:CB$1338,Calculs!$B$11:$B$1338,$H61,Calculs!$F$11:$F$1338,IF($V$40="Tous","<>0",VLOOKUP($V$40,'Listes déroulantes, autres'!$H$9:$I$21,2,FALSE)),Calculs!$G$11:$G$1338,IF($W$40="Tous","<>0",$W$40),Calculs!$H$11:$H$1338,IF($X$40="Tous","<>0",$X$40) )/10^6) -> 0 | X61: =W61/$M$155 -> 0 | Y61: =REPT("|",X61*(100/MAX($N$14:$N$35)))
C62: =IF(B62=0,C61,B62) -> Catégorie 1 | F62: =IF(E62=0,F61,E62) -> 1.5 | H62: 1.5B1 | J62: =SUMIFS(Calculs!BY$11:BY$1338,Calculs!$B$11:$B$1338,$H62)/10^6 -> 0 | K62: =SUMIFS(Calculs!BZ$11:BZ$1338,Calculs!$B$11:$B$1338,$H62)/10^6 -> 0 | L62: =SUMIFS(Calculs!CA$11:CA$1338,Calculs!$B$11:$B$1338,$H62)/10^6 -> 0 | M62: =SUMIFS(Calculs!CB$11:CB$1338,Calculs!$B$11:$B$1338,$H62)/10^6 -> 0 | N62: =M62/$M$155 -> 0 | O62: =REPT("|",N62*(100/MAX($N$14:$N$35))) | W62: =(SUMIFS(Calculs!CB$11:CB$1338,Calculs!$B$11:$B$1338,$H62,Calculs!$F$11:$F$1338,IF($V$40="Tous","<>0",VLOOKUP($V$40,'Listes déroulantes, autres'!$H$9:$I$21,2,FALSE)),Calculs!$G$11:$G$1338,IF($W$40="Tous","<>0",$W$40),Calculs!$H$11:$H$1338,IF($X$40="Tous","<>0",$X$40) )/10^6) -> 0 | X62: =W62/$M$155 -> 0 | Y62: =REPT("|",X62*(100/MAX($N$14:$N$35)))
C63: =IF(B63=0,C62,B63) -> Catégorie 1 | F63: =IF(E63=0,F62,E63) -> 1.5 | H63: 1.5B2 | J63: =SUMIFS(Calculs!BY$11:BY$1338,Calculs!$B$11:$B$1338,$H63)/10^6 -> 0 | K63: =SUMIFS(Calculs!BZ$11:BZ$1338,Calculs!$B$11:$B$1338,$H63)/10^6 -> 0 | L63: =SUMIFS(Calculs!CA$11:CA$1338,Calculs!$B$11:$B$1338,$H63)/10^6 -> 0 | M63: =SUMIFS(Calculs!CB$11:CB$1338,Calculs!$B$11:$B$1338,$H63)/10^6 -> 0 | N63: =M63/$M$155 -> 0 | O63: =REPT("|",N63*(100/MAX($N$14:$N$35))) | W63: =(SUMIFS(Calculs!CB$11:CB$1338,Calculs!$B$11:$B$1338,$H63,Calculs!$F$11:$F$1338,IF($V$40="Tous","<>0",VLOOKUP($V$40,'Listes déroulantes, autres'!$H$9:$I$21,2,FALSE)),Calculs!$G$11:$G$1338,IF($W$40="Tous","<>0",$W$40),Calculs!$H$11:$H$1338,IF($X$40="Tous","<>0",$X$40) )/10^6) -> 0 | X63: =W63/$M$155 -> 0 | Y63: =REPT("|",X63*(100/MAX($N$14:$N$35)))
C64: =IF(B64=0,C63,B64) -> Catégorie 1 | F64: =IF(E64=0,F63,E64) -> 1.5 | H64: 1.5C1 | J64: =SUMIFS(Calculs!BY$11:BY$1338,Calculs!$B$11:$B$1338,$H64)/10^6 -> 0 | K64: =SUMIFS(Calculs!BZ$11:BZ$1338,Calculs!$B$11:$B$1338,$H64)/10^6 -> 0 | L64: =SUMIFS(Calculs!CA$11:CA$1338,Calculs!$B$11:$B$1338,$H64)/10^6 -> 0 | M64: =SUMIFS(Calculs!CB$11:CB$1338,Calculs!$B$11:$B$1338,$H64)/10^6 -> 0 | N64: =M64/$M$155 -> 0 | O64: =REPT("|",N64*(100/MAX($N$14:$N$35))) | W64: =(SUMIFS(Calculs!CB$11:CB$1338,Calculs!$B$11:$B$1338,$H64,Calculs!$F$11:$F$1338,IF($V$40="Tous","<>0",VLOOKUP($V$40,'Listes déroulantes, autres'!$H$9:$I$21,2,FALSE)),Calculs!$G$11:$G$1338,IF($W$40="Tous","<>0",$W$40),Calculs!$H$11:$H$1338,IF($X$40="Tous","<>0",$X$40) )/10^6) -> 0 | X64: =W64/$M$155 -> 0 | Y64: =REPT("|",X64*(100/MAX($N$14:$N$35)))
C65: =IF(B65=0,C64,B65) -> Catégorie 1 | F65: =IF(E65=0,F64,E65) -> 1.5 | H65: 1.5C2 | J65: =SUMIFS(Calculs!BY$11:BY$1338,Calculs!$B$11:$B$1338,$H65)/10^6 -> 0 | K65: =SUMIFS(Calculs!BZ$11:BZ$1338,Calculs!$B$11:$B$1338,$H65)/10^6 -> 0 | L65: =SUMIFS(Calculs!CA$11:CA$1338,Calculs!$B$11:$B$1338,$H65)/10^6 -> 0 | M65: =SUMIFS(Calculs!CB$11:CB$1338,Calculs!$B$11:$B$1338,$H65)/10^6 -> 0 | N65: =M65/$M$155 -> 0 | O65: =REPT("|",N65*(100/MAX($N$14:$N$35))) | W65: =(SUMIFS(Calculs!CB$11:CB$1338,Calculs!$B$11:$B$1338,$H65,Calculs!$F$11:$F$1338,IF($V$40="Tous","<>0",VLOOKUP($V$40,'Listes déroulantes, autres'!$H$9:$I$21,2,FALSE)),Calculs!$G$11:$G$1338,IF($W$40="Tous","<>0",$W$40),Calculs!$H$11:$H$1338,IF($X$40="Tous","<>0",$X$40) )/10^6) -> 0 | X65: =W65/$M$155 -> 0 | Y65: =REPT("|",X65*(100/MAX($N$14:$N$35)))
B66: Catégorie 2 | C66: =IF(B66=0,C65,B66) -> Catégorie 2 | D66: Émissions indirects de l'énergie importée | E66: 2.1 | F66: =IF(E66=0,F65,E66) -> 2.1 | G66: Électricités | H66: 2.1A1 | I66: =Calculs!B157 -> 2.1A1 - Électricité provenant du réseaux électrique (Location based) | J66: =SUMIFS(Calculs!BY$11:BY$1338,Calculs!$B$11:$B$1338,$H66)/10^6 -> 1.5080321 | K66: =SUMIFS(Calculs!BZ$11:BZ$1338,Calculs!$B$11:$B$1338,$H66)/10^6 -> 0.00095295221 | L66: =SUMIFS(Calculs!CA$11:CA$1338,Calculs!$B$11:$B$1338,$H66)/10^6 -> 0.00095295221 | M66: =SUMIFS(Calculs!CB$11:CB$1338,Calculs!$B$11:$B$1338,$H66)/10^6 -> 1.509938 | N66: =M66/$M$155 -> 0.0085023013 | O66: =REPT("|",N66*(100/MAX($N$14:$N$35))) -> | | W66: =(SUMIFS(Calculs!CB$11:CB$1338,Calculs!$B$11:$B$1338,$H66,Calculs!$F$11:$F$1338,IF($V$40="Tous","<>0",VLOOKUP($V$40,'Listes déroulantes, autres'!$H$9:$I$21,2,FALSE)),Calculs!$G$11:$G$1338,IF($W$40="Tous","<>0",$W$40),Calculs!$H$11:$H$1338,IF($X$40="Tous","<>0",$X$40) )/10^6) -> 0.00195 | X66: =W66/$M$155 -> 1.0980244e-05 | Y66: =REPT("|",X66*(100/MAX($N$14:$N$35)))
C67: =IF(B67=0,C66,B67) -> Catégorie 2 | F67: =IF(E67=0,F66,E67) -> 2.1 | H67: 2.1A2 | J67: =SUMIFS(Calculs!BY$11:BY$1338,Calculs!$B$11:$B$1338,$H67)/10^6 -> 0 | K67: =SUMIFS(Calculs!BZ$11:BZ$1338,Calculs!$B$11:$B$1338,$H67)/10^6 -> 0 | L67: =SUMIFS(Calculs!CA$11:CA$1338,Calculs!$B$11:$B$1338,$H67)/10^6 -> 0 | M67: =SUMIFS(Calculs!CB$11:CB$1338,Calculs!$B$11:$B$1338,$H67)/10^6 -> 0 | N67: =M67/$M$155 -> 0 | O67: =REPT("|",N67*(100/MAX($N$14:$N$35))) | W67: =(SUMIFS(Calculs!CB$11:CB$1338,Calculs!$B$11:$B$1338,$H67,Calculs!$F$11:$F$1338,IF($V$40="Tous","<>0",VLOOKUP($V$40,'Listes déroulantes, autres'!$H$9:$I$21,2,FALSE)),Calculs!$G$11:$G$1338,IF($W$40="Tous","<>0",$W$40),Calculs!$H$11:$H$1338,IF($X$40="Tous","<>0",$X$40) )/10^6) -> 0 | X67: =W67/$M$155 -> 0 | Y67: =REPT("|",X67*(100/MAX($N$14:$N$35)))
C68: =IF(B68=0,C67,B68) -> Catégorie 2 | F68: =IF(E68=0,F67,E68) -> 2.1 | H68: 2.1B1 | I68: =Calculs!B175 -> 2.1B1 - Électricité provenant du réseaux électrique (Market based) | J68: =SUMIFS(Calculs!BY$11:BY$1338,Calculs!$B$11:$B$1338,$H68)/10^6 -> 0.08085 | K68: =SUMIFS(Calculs!BZ$11:BZ$1338,Calculs!$B$11:$B$1338,$H68)/10^6 -> 0 | L68: =SUMIFS(Calculs!CA$11:CA$1338,Calculs!$B$11:$B$1338,$H68)/10^6 -> 0 | M68: =SUMIFS(Calculs!CB$11:CB$1338,Calculs!$B$11:$B$1338,$H68)/10^6 -> 0.08085 | N68: =M68/$M$155 -> 0.00045525782 | O68: =REPT("|",N68*(100/MAX($N$14:$N$35))) | W68: =(SUMIFS(Calculs!CB$11:CB$1338,Calculs!$B$11:$B$1338,$H68,Calculs!$F$11:$F$1338,IF($V$40="Tous","<>0",VLOOKUP($V$40,'Listes déroulantes, autres'!$H$9:$I$21,2,FALSE)),Calculs!$G$11:$G$1338,IF($W$40="Tous","<>0",$W$40),Calculs!$H$11:$H$1338,IF($X$40="Tous","<>0",$X$40) )/10^6) -> 0.00195 | X68: =W68/$M$155 -> 1.0980244e-05 | Y68: =REPT("|",X68*(100/MAX($N$14:$N$35)))
C69: =IF(B69=0,C67,B69) -> Catégorie 2 | E69: 2.2 | F69: =IF(E69=0,F67,E69) -> 2.2 | G69: Autres énergies importées | H69: 2.2A1 | J69: =SUMIFS(Calculs!BY$11:BY$1338,Calculs!$B$11:$B$1338,$H69)/10^6 -> 0 | K69: =SUMIFS(Calculs!BZ$11:BZ$1338,Calculs!$B$11:$B$1338,$H69)/10^6 -> 0 | L69: =SUMIFS(Calculs!CA$11:CA$1338,Calculs!$B$11:$B$1338,$H69)/10^6 -> 0 | M69: =SUMIFS(Calculs!CB$11:CB$1338,Calculs!$B$11:$B$1338,$H69)/10^6 -> 0 | N69: =M69/$M$155 -> 0 | O69: =REPT("|",N69*(100/MAX($N$14:$N$35))) | W69: =(SUMIFS(Calculs!CB$11:CB$1338,Calculs!$B$11:$B$1338,$H69,Calculs!$F$11:$F$1338,IF($V$40="Tous","<>0",VLOOKUP($V$40,'Listes déroulantes, autres'!$H$9:$I$21,2,FALSE)),Calculs!$G$11:$G$1338,IF($W$40="Tous","<>0",$W$40),Calculs!$H$11:$H$1338,IF($X$40="Tous","<>0",$X$40) )/10^6) -> 0 | X69: =W69/$M$155 -> 0 | Y69: =REPT("|",X69*(100/MAX($N$14:$N$35)))
C70: =IF(B70=0,C69,B70) -> Catégorie 2 | F70: =IF(E70=0,F69,E70) -> 2.2 | H70: 2.2A2 | I70: =Calculs!B193 -> 2.2A2 -Importation d'énergie (Chaleur) en équivalent de combustible | J70: =SUMIFS(Calculs!BY$11:BY$1338,Calculs!$B$11:$B$1338,$H70)/10^6 -> 26.292 | K70: =SUMIFS(Calculs!BZ$11:BZ$1338,Calculs!$B$11:$B$1338,$H70)/10^6 -> 0.0154364 | L70: =SUMIFS(Calculs!CA$11:CA$1338,Calculs!$B$11:$B$1338,$H70)/10^6 -> 0.129948 | M70: =SUMIFS(Calculs!CB$11:CB$1338,Calculs!$B$11:$B$1338,$H70)/10^6 -> 26.437384 | N70: =M70/$M$155 -> 0.14886612 | O70: =REPT("|",N70*(100/MAX($N$14:$N$35))) -> |||||||||||||||||||||||| | W70: =(SUMIFS(Calculs!CB$11:CB$1338,Calculs!$B$11:$B$1338,$H70,Calculs!$F$11:$F$1338,IF($V$40="Tous","<>0",VLOOKUP($V$40,'Listes déroulantes, autres'!$H$9:$I$21,2,FALSE)),Calculs!$G$11:$G$1338,IF($W$40="Tous","<>0",$W$40),Calculs!$H$11:$H$1338,IF($X$40="Tous","<>0",$X$40) )/10^6) -> 0 | X70: =W70/$M$155 -> 0 | Y70: =REPT("|",X70*(100/MAX($N$14:$N$35)))
C71: =IF(B71=0,C70,B71) -> Catégorie 2 | F71: =IF(E71=0,F70,E71) -> 2.2 | H71: 2.2A3 | J71: =SUMIFS(Calculs!BY$11:BY$1338,Calculs!$B$11:$B$1338,$H71)/10^6 -> 0 | K71: =SUMIFS(Calculs!BZ$11:BZ$1338,Calculs!$B$11:$B$1338,$H71)/10^6 -> 0 | L71: =SUMIFS(Calculs!CA$11:CA$1338,Calculs!$B$11:$B$1338,$H71)/10^6 -> 0 | M71: =SUMIFS(Calculs!CB$11:CB$1338,Calculs!$B$11:$B$1338,$H71)/10^6 -> 0 | N71: =M71/$M$155 -> 0 | O71: =REPT("|",N71*(100/MAX($N$14:$N$35))) | W71: =(SUMIFS(Calculs!CB$11:CB$1338,Calculs!$B$11:$B$1338,$H71,Calculs!$F$11:$F$1338,IF($V$40="Tous","<>0",VLOOKUP($V$40,'Listes déroulantes, autres'!$H$9:$I$21,2,FALSE)),Calculs!$G$11:$G$1338,IF($W$40="Tous","<>0",$W$40),Calculs!$H$11:$H$1338,IF($X$40="Tous","<>0",$X$40) )/10^6) -> 0 | X71: =W71/$M$155 -> 0 | Y71: =REPT("|",X71*(100/MAX($N$14:$N$35)))
C72: =IF(B72=0,C71,B72) -> Catégorie 2 | F72: =IF(E72=0,F71,E72) -> 2.2 | H72: 2.2B1 | J72: =SUMIFS(Calculs!BY$11:BY$1338,Calculs!$B$11:$B$1338,$H72)/10^6 -> 0 | K72: =SUMIFS(Calculs!BZ$11:BZ$1338,Calculs!$B$11:$B$1338,$H72)/10^6 -> 0 | L72: =SUMIFS(Calculs!CA$11:CA$1338,Calculs!$B$11:$B$1338,$H72)/10^6 -> 0 | M72: =SUMIFS(Calculs!CB$11:CB$1338,Calculs!$B$11:$B$1338,$H72)/10^6 -> 0 | N72: =M72/$M$155 -> 0 | O72: =REPT("|",N72*(100/MAX($N$14:$N$35))) | W72: =(SUMIFS(Calculs!CB$11:CB$1338,Calculs!$B$11:$B$1338,$H72,Calculs!$F$11:$F$1338,IF($V$40="Tous","<>0",VLOOKUP($V$40,'Listes déroulantes, autres'!$H$9:$I$21,2,FALSE)),Calculs!$G$11:$G$1338,IF($W$40="Tous","<>0",$W$40),Calculs!$H$11:$H$1338,IF($X$40="Tous","<>0",$X$40) )/10^6) -> 0 | X72: =W72/$M$155 -> 0 | Y72: =REPT("|",X72*(100/MAX($N$14:$N$35)))
B73: Catégorie 3 | C73: =IF(B73=0,C72,B73) -> Catégorie 3 | D73: Émissions indirects des transports | E73: 3.1 | F73: =IF(E73=0,F72,E73) -> 3.1 | G73: Transport en amont | H73: 3.1A1 | J73: =SUMIFS(Calculs!BY$11:BY$1338,Calculs!$B$11:$B$1338,$H73)/10^6 -> 0 | K73: =SUMIFS(Calculs!BZ$11:BZ$1338,Calculs!$B$11:$B$1338,$H73)/10^6 -> 0 | L73: =SUMIFS(Calculs!CA$11:CA$1338,Calculs!$B$11:$B$1338,$H73)/10^6 -> 0 | M73: =SUMIFS(Calculs!CB$11:CB$1338,Calculs!$B$11:$B$1338,$H73)/10^6 -> 0 | N73: =M73/$M$155 -> 0 | O73: =REPT("|",N73*(100/MAX($N$14:$N$35))) | W73: =(SUMIFS(Calculs!CB$11:CB$1338,Calculs!$B$11:$B$1338,$H73,Calculs!$F$11:$F$1338,IF($V$40="Tous","<>0",VLOOKUP($V$40,'Listes déroulantes, autres'!$H$9:$I$21,2,FALSE)),Calculs!$G$11:$G$1338,IF($W$40="Tous","<>0",$W$40),Calculs!$H$11:$H$1338,IF($X$40="Tous","<>0",$X$40) )/10^6) -> 0 | X73: =W73/$M$155 -> 0 | Y73: =REPT("|",X73*(100/MAX($N$14:$N$35)))
C74: =IF(B74=0,C73,B74) -> Catégorie 3 | F74: =IF(E74=0,F73,E74) -> 3.1 | H74: 3.1A2 | J74: =SUMIFS(Calculs!BY$11:BY$1338,Calculs!$B$11:$B$1338,$H74)/10^6 -> 0 | K74: =SUMIFS(Calculs!BZ$11:BZ$1338,Calculs!$B$11:$B$1338,$H74)/10^6 -> 0 | L74: =SUMIFS(Calculs!CA$11:CA$1338,Calculs!$B$11:$B$1338,$H74)/10^6 -> 0 | M74: =SUMIFS(Calculs!CB$11:CB$1338,Calculs!$B$11:$B$1338,$H74)/10^6 -> 0 | N74: =M74/$M$155 -> 0 | O74: =REPT("|",N74*(100/MAX($N$14:$N$35))) | W74: =(SUMIFS(Calculs!CB$11:CB$1338,Calculs!$B$11:$B$1338,$H74,Calculs!$F$11:$F$1338,IF($V$40="Tous","<>0",VLOOKUP($V$40,'Listes déroulantes, autres'!$H$9:$I$21,2,FALSE)),Calculs!$G$11:$G$1338,IF($W$40="Tous","<>0",$W$40),Calculs!$H$11:$H$1338,IF($X$40="Tous","<>0",$X$40) )/10^6) -> 0 | X74: =W74/$M$155 -> 0 | Y74: =REPT("|",X74*(100/MAX($N$14:$N$35)))
C75: =IF(B75=0,C74,B75) -> Catégorie 3 | E75: 3.2 | F75: =IF(E75=0,F74,E75) -> 3.2 | G75: Transport en aval | H75: 3.2A1 | J75: =SUMIFS(Calculs!BY$11:BY$1338,Calculs!$B$11:$B$1338,$H75)/10^6 -> 0 | K75: =SUMIFS(Calculs!BZ$11:BZ$1338,Calculs!$B$11:$B$1338,$H75)/10^6 -> 0 | L75: =SUMIFS(Calculs!CA$11:CA$1338,Calculs!$B$11:$B$1338,$H75)/10^6 -> 0 | M75: =SUMIFS(Calculs!CB$11:CB$1338,Calculs!$B$11:$B$1338,$H75)/10^6 -> 0 | N75: =M75/$M$155 -> 0 | O75: =REPT("|",N75*(100/MAX($N$14:$N$35))) | W75: =(SUMIFS(Calculs!CB$11:CB$1338,Calculs!$B$11:$B$1338,$H75,Calculs!$F$11:$F$1338,IF($V$40="Tous","<>0",VLOOKUP($V$40,'Listes déroulantes, autres'!$H$9:$I$21,2,FALSE)),Calculs!$G$11:$G$1338,IF($W$40="Tous","<>0",$W$40),Calculs!$H$11:$H$1338,IF($X$40="Tous","<>0",$X$40) )/10^6) -> 0 | X75: =W75/$M$155 -> 0 | Y75: =REPT("|",X75*(100/MAX($N$14:$N$35)))
C76: =IF(B76=0,C75,B76) -> Catégorie 3 | F76: =IF(E76=0,F75,E76) -> 3.2 | H76: 3.2B1 | J76: =SUMIFS(Calculs!BY$11:BY$1338,Calculs!$B$11:$B$1338,$H76)/10^6 -> 0 | K76: =SUMIFS(Calculs!BZ$11:BZ$1338,Calculs!$B$11:$B$1338,$H76)/10^6 -> 0 | L76: =SUMIFS(Calculs!CA$11:CA$1338,Calculs!$B$11:$B$1338,$H76)/10^6 -> 0 | M76: =SUMIFS(Calculs!CB$11:CB$1338,Calculs!$B$11:$B$1338,$H76)/10^6 -> 0 | N76: =M76/$M$155 -> 0 | O76: =REPT("|",N76*(100/MAX($N$14:$N$35))) | W76: =(SUMIFS(Calculs!CB$11:CB$1338,Calculs!$B$11:$B$1338,$H76,Calculs!$F$11:$F$1338,IF($V$40="Tous","<>0",VLOOKUP($V$40,'Listes déroulantes, autres'!$H$9:$I$21,2,FALSE)),Calculs!$G$11:$G$1338,IF($W$40="Tous","<>0",$W$40),Calculs!$H$11:$H$1338,IF($X$40="Tous","<>0",$X$40) )/10^6) -> 0 | X76: =W76/$M$155 -> 0 | Y76: =REPT("|",X76*(100/MAX($N$14:$N$35)))
C77: =IF(B77=0,C76,B77) -> Catégorie 3 | E77: 3.3 | F77: =IF(E77=0,F76,E77) -> 3.3 | G77: Navettage des employés | H77: 3.3A1 | I77: =Calculs!B211 -> 3.3A1 - Navettage des employés | J77: =SUMIFS(Calculs!BY$11:BY$1338,Calculs!$B$11:$B$1338,$H77)/10^6 -> 5.3790753 | K77: =SUMIFS(Calculs!BZ$11:BZ$1338,Calculs!$B$11:$B$1338,$H77)/10^6 -> 0.009721809 | L77: =SUMIFS(Calculs!CA$11:CA$1338,Calculs!$B$11:$B$1338,$H77)/10^6 -> 0.014100091 | M77: =SUMIFS(Calculs!CB$11:CB$1338,Calculs!$B$11:$B$1338,$H77)/10^6 -> 5.4028972 | N77: =M77/$M$155 -> 0.030423144 | O77: =REPT("|",N77*(100/MAX($N$14:$N$35))) -> |||| | W77: =(SUMIFS(Calculs!CB$11:CB$1338,Calculs!$B$11:$B$1338,$H77,Calculs!$F$11:$F$1338,IF($V$40="Tous","<>0",VLOOKUP($V$40,'Listes déroulantes, autres'!$H$9:$I$21,2,FALSE)),Calculs!$G$11:$G$1338,IF($W$40="Tous","<>0",$W$40),Calculs!$H$11:$H$1338,IF($X$40="Tous","<>0",$X$40) )/10^6) -> 0.0078084018 | X77: =W77/$M$155 -> 4.3968287e-05 | Y77: =REPT("|",X77*(100/MAX($N$14:$N$35)))
C78: =IF(B78=0,C77,B78) -> Catégorie 3 | F78: =IF(E78=0,F77,E78) -> 3.3 | H78: 3.3A2 | J78: =SUMIFS(Calculs!BY$11:BY$1338,Calculs!$B$11:$B$1338,$H78)/10^6 -> 0 | K78: =SUMIFS(Calculs!BZ$11:BZ$1338,Calculs!$B$11:$B$1338,$H78)/10^6 -> 0 | L78: =SUMIFS(Calculs!CA$11:CA$1338,Calculs!$B$11:$B$1338,$H78)/10^6 -> 0 | M78: =SUMIFS(Calculs!CB$11:CB$1338,Calculs!$B$11:$B$1338,$H78)/10^6 -> 0 | N78: =M78/$M$155 -> 0 | O78: =REPT("|",N78*(100/MAX($N$14:$N$35))) | W78: =(SUMIFS(Calculs!CB$11:CB$1338,Calculs!$B$11:$B$1338,$H78,Calculs!$F$11:$F$1338,IF($V$40="Tous","<>0",VLOOKUP($V$40,'Listes déroulantes, autres'!$H$9:$I$21,2,FALSE)),Calculs!$G$11:$G$1338,IF($W$40="Tous","<>0",$W$40),Calculs!$H$11:$H$1338,IF($X$40="Tous","<>0",$X$40) )/10^6) -> 0 | X78: =W78/$M$155 -> 0 | Y78: =REPT("|",X78*(100/MAX($N$14:$N$35)))
C79: =IF(B79=0,C78,B79) -> Catégorie 3 | F79: =IF(E79=0,F78,E79) -> 3.3 | H79: 3.3A3 | J79: =SUMIFS(Calculs!BY$11:BY$1338,Calculs!$B$11:$B$1338,$H79)/10^6 -> 0 | K79: =SUMIFS(Calculs!BZ$11:BZ$1338,Calculs!$B$11:$B$1338,$H79)/10^6 -> 0 | L79: =SUMIFS(Calculs!CA$11:CA$1338,Calculs!$B$11:$B$1338,$H79)/10^6 -> 0 | M79: =SUMIFS(Calculs!CB$11:CB$1338,Calculs!$B$11:$B$1338,$H79)/10^6 -> 0 | N79: =M79/$M$155 -> 0 | O79: =REPT("|",N79*(100/MAX($N$14:$N$35))) | W79: =(SUMIFS(Calculs!CB$11:CB$1338,Calculs!$B$11:$B$1338,$H79,Calculs!$F$11:$F$1338,IF($V$40="Tous","<>0",VLOOKUP($V$40,'Listes déroulantes, autres'!$H$9:$I$21,2,FALSE)),Calculs!$G$11:$G$1338,IF($W$40="Tous","<>0",$W$40),Calculs!$H$11:$H$1338,IF($X$40="Tous","<>0",$X$40) )/10^6) -> 0 | X79: =W79/$M$155 -> 0 | Y79: =REPT("|",X79*(100/MAX($N$14:$N$35)))
C80: =IF(B80=0,C79,B80) -> Catégorie 3 | F80: =IF(E80=0,F79,E80) -> 3.3 | H80: 3.3B1 | I80: (Déplacer vers 4.5) | J80: =SUMIFS(Calculs!BY$11:BY$1338,Calculs!$B$11:$B$1338,$H80)/10^6 -> 0 | K80: =SUMIFS(Calculs!BZ$11:BZ$1338,Calculs!$B$11:$B$1338,$H80)/10^6 -> 0 | L80: =SUMIFS(Calculs!CA$11:CA$1338,Calculs!$B$11:$B$1338,$H80)/10^6 -> 0 | M80: =SUMIFS(Calculs!CB$11:CB$1338,Calculs!$B$11:$B$1338,$H80)/10^6 -> 0 | N80: =M80/$M$155 -> 0 | O80: =REPT("|",N80*(100/MAX($N$14:$N$35))) | W80: =(SUMIFS(Calculs!CB$11:CB$1338,Calculs!$B$11:$B$1338,$H80,Calculs!$F$11:$F$1338,IF($V$40="Tous","<>0",VLOOKUP($V$40,'Listes déroulantes, autres'!$H$9:$I$21,2,FALSE)),Calculs!$G$11:$G$1338,IF($W$40="Tous","<>0",$W$40),Calculs!$H$11:$H$1338,IF($X$40="Tous","<>0",$X$40) )/10^6) -> 0 | X80: =W80/$M$155 -> 0 | Y80: =REPT("|",X80*(100/MAX($N$14:$N$35)))
C81: =IF(B81=0,C80,B81) -> Catégorie 3 | F81: =IF(E81=0,F80,E81) -> 3.3 | H81: 3.3B2 | I81: (Déplacer vers 4.5) | J81: =SUMIFS(Calculs!BY$11:BY$1338,Calculs!$B$11:$B$1338,$H81)/10^6 -> 0 | K81: =SUMIFS(Calculs!BZ$11:BZ$1338,Calculs!$B$11:$B$1338,$H81)/10^6 -> 0 | L81: =SUMIFS(Calculs!CA$11:CA$1338,Calculs!$B$11:$B$1338,$H81)/10^6 -> 0 | M81: =SUMIFS(Calculs!CB$11:CB$1338,Calculs!$B$11:$B$1338,$H81)/10^6 -> 0 | N81: =M81/$M$155 -> 0 | O81: =REPT("|",N81*(100/MAX($N$14:$N$35))) | W81: =(SUMIFS(Calculs!CB$11:CB$1338,Calculs!$B$11:$B$1338,$H81,Calculs!$F$11:$F$1338,IF($V$40="Tous","<>0",VLOOKUP($V$40,'Listes déroulantes, autres'!$H$9:$I$21,2,FALSE)),Calculs!$G$11:$G$1338,IF($W$40="Tous","<>0",$W$40),Calculs!$H$11:$H$1338,IF($X$40="Tous","<>0",$X$40) )/10^6) -> 0 | X81: =W81/$M$155 -> 0 | Y81: =REPT("|",X81*(100/MAX($N$14:$N$35)))
C82: =IF(B82=0,C81,B82) -> Catégorie 3 | E82: 3.4 | F82: =IF(E82=0,F81,E82) -> 3.4 | G82: Déplacement des clients | H82: 3.4A1 | I82: =Calculs!B229 -> 3.4A1 - Déplacements des visiteurs en voiture | J82: =SUMIFS(Calculs!BY$11:BY$1338,Calculs!$B$11:$B$1338,$H82)/10^6 -> 1.917075 | K82: =SUMIFS(Calculs!BZ$11:BZ$1338,Calculs!$B$11:$B$1338,$H82)/10^6 -> 0.0012665 | L82: =SUMIFS(Calculs!CA$11:CA$1338,Calculs!$B$11:$B$1338,$H82)/10^6 -> 0.04368 | M82: =SUMIFS(Calculs!CB$11:CB$1338,Calculs!$B$11:$B$1338,$H82)/10^6 -> 1.9620215 | N82: =M82/$M$155 -> 0.011047936 | O82: =REPT("|",N82*(100/MAX($N$14:$N$35))) -> | | W82: =(SUMIFS(Calculs!CB$11:CB$1338,Calculs!$B$11:$B$1338,$H82,Calculs!$F$11:$F$1338,IF($V$40="Tous","<>0",VLOOKUP($V$40,'Listes déroulantes, autres'!$H$9:$I$21,2,FALSE)),Calculs!$G$11:$G$1338,IF($W$40="Tous","<>0",$W$40),Calculs!$H$11:$H$1338,IF($X$40="Tous","<>0",$X$40) )/10^6) -> 0 | X82: =W82/$M$155 -> 0 | Y82: =REPT("|",X82*(100/MAX($N$14:$N$35)))
C83: =IF(B83=0,C82,B83) -> Catégorie 3 | F83: =IF(E83=0,F82,E83) -> 3.4 | H83: 3.4A2 | J83: =SUMIFS(Calculs!BY$11:BY$1338,Calculs!$B$11:$B$1338,$H83)/10^6 -> 0 | K83: =SUMIFS(Calculs!BZ$11:BZ$1338,Calculs!$B$11:$B$1338,$H83)/10^6 -> 0 | L83: =SUMIFS(Calculs!CA$11:CA$1338,Calculs!$B$11:$B$1338,$H83)/10^6 -> 0 | M83: =SUMIFS(Calculs!CB$11:CB$1338,Calculs!$B$11:$B$1338,$H83)/10^6 -> 0 | N83: =M83/$M$155 -> 0 | O83: =REPT("|",N83*(100/MAX($N$14:$N$35))) | W83: =(SUMIFS(Calculs!CB$11:CB$1338,Calculs!$B$11:$B$1338,$H83,Calculs!$F$11:$F$1338,IF($V$40="Tous","<>0",VLOOKUP($V$40,'Listes déroulantes, autres'!$H$9:$I$21,2,FALSE)),Calculs!$G$11:$G$1338,IF($W$40="Tous","<>0",$W$40),Calculs!$H$11:$H$1338,IF($X$40="Tous","<>0",$X$40) )/10^6) -> 0 | X83: =W83/$M$155 -> 0 | Y83: =REPT("|",X83*(100/MAX($N$14:$N$35)))
C84: =IF(B84=0,C83,B84) -> Catégorie 3 | F84: =IF(E84=0,F83,E84) -> 3.4 | H84: 3.4A3 | J84: =SUMIFS(Calculs!BY$11:BY$1338,Calculs!$B$11:$B$1338,$H84)/10^6 -> 0 | K84: =SUMIFS(Calculs!BZ$11:BZ$1338,Calculs!$B$11:$B$1338,$H84)/10^6 -> 0 | L84: =SUMIFS(Calculs!CA$11:CA$1338,Calculs!$B$11:$B$1338,$H84)/10^6 -> 0 | M84: =SUMIFS(Calculs!CB$11:CB$1338,Calculs!$B$11:$B$1338,$H84)/10^6 -> 0 | N84: =M84/$M$155 -> 0 | O84: =REPT("|",N84*(100/MAX($N$14:$N$35))) | W84: =(SUMIFS(Calculs!CB$11:CB$1338,Calculs!$B$11:$B$1338,$H84,Calculs!$F$11:$F$1338,IF($V$40="Tous","<>0",VLOOKUP($V$40,'Listes déroulantes, autres'!$H$9:$I$21,2,FALSE)),Calculs!$G$11:$G$1338,IF($W$40="Tous","<>0",$W$40),Calculs!$H$11:$H$1338,IF($X$40="Tous","<>0",$X$40) )/10^6) -> 0 | X84: =W84/$M$155 -> 0 | Y84: =REPT("|",X84*(100/MAX($N$14:$N$35)))
C85: =IF(B85=0,C84,B85) -> Catégorie 3 | F85: =IF(E85=0,F84,E85) -> 3.4 | H85: 3.4B1 | I85: =Calculs!B247 -> 3.4B1 - Déplacements des visiteurs en avion, train ou bus | J85: =SUMIFS(Calculs!BY$11:BY$1338,Calculs!$B$11:$B$1338,$H85)/10^6 -> 4.973455 | K85: =SUMIFS(Calculs!BZ$11:BZ$1338,Calculs!$B$11:$B$1338,$H85)/10^6 -> 0.00077770818 | L85: =SUMIFS(Calculs!CA$11:CA$1338,Calculs!$B$11:$B$1338,$H85)/10^6 -> 0.042205023 | M85: =SUMIFS(Calculs!CB$11:CB$1338,Calculs!$B$11:$B$1338,$H85)/10^6 -> 5.0164378 | N85: =M85/$M$155 -> 0.028247032 | O85: =REPT("|",N85*(100/MAX($N$14:$N$35))) -> |||| | W85: =(SUMIFS(Calculs!CB$11:CB$1338,Calculs!$B$11:$B$1338,$H85,Calculs!$F$11:$F$1338,IF($V$40="Tous","<>0",VLOOKUP($V$40,'Listes déroulantes, autres'!$H$9:$I$21,2,FALSE)),Calculs!$G$11:$G$1338,IF($W$40="Tous","<>0",$W$40),Calculs!$H$11:$H$1338,IF($X$40="Tous","<>0",$X$40) )/10^6) -> 0 | X85: =W85/$M$155 -> 0 | Y85: =REPT("|",X85*(100/MAX($N$14:$N$35)))
C86: =IF(B86=0,C85,B86) -> Catégorie 3 | E86: 3.5 | F86: =IF(E86=0,F85,E86) -> 3.5 | G86: Déplacement d'affaires | H86: 3.5A1 | I86: =Calculs!B265 -> 3.5A1 - Déplacements d'affaires en voiture | J86: =SUMIFS(Calculs!BY$11:BY$1338,Calculs!$B$11:$B$1338,$H86)/10^6 -> 1.917075 | K86: =SUMIFS(Calculs!BZ$11:BZ$1338,Calculs!$B$11:$B$1338,$H86)/10^6 -> 0.0012665 | L86: =SUMIFS(Calculs!CA$11:CA$1338,Calculs!$B$11:$B$1338,$H86)/10^6 -> 0.04368 | M86: =SUMIFS(Calculs!CB$11:CB$1338,Calculs!$B$11:$B$1338,$H86)/10^6 -> 1.9620215 | N86: =M86/$M$155 -> 0.011047936 | O86: =REPT("|",N86*(100/MAX($N$14:$N$35))) -> | | W86: =(SUMIFS(Calculs!CB$11:CB$1338,Calculs!$B$11:$B$1338,$H86,Calculs!$F$11:$F$1338,IF($V$40="Tous","<>0",VLOOKUP($V$40,'Listes déroulantes, autres'!$H$9:$I$21,2,FALSE)),Calculs!$G$11:$G$1338,IF($W$40="Tous","<>0",$W$40),Calculs!$H$11:$H$1338,IF($X$40="Tous","<>0",$X$40) )/10^6) -> 0 | X86: =W86/$M$155 -> 0 | Y86: =REPT("|",X86*(100/MAX($N$14:$N$35)))
C87: =IF(B87=0,C86,B87) -> Catégorie 3 | F87: =IF(E87=0,F86,E87) -> 3.5 | H87: 3.5A2 | J87: =SUMIFS(Calculs!BY$11:BY$1338,Calculs!$B$11:$B$1338,$H87)/10^6 -> 0 | K87: =SUMIFS(Calculs!BZ$11:BZ$1338,Calculs!$B$11:$B$1338,$H87)/10^6 -> 0 | L87: =SUMIFS(Calculs!CA$11:CA$1338,Calculs!$B$11:$B$1338,$H87)/10^6 -> 0 | M87: =SUMIFS(Calculs!CB$11:CB$1338,Calculs!$B$11:$B$1338,$H87)/10^6 -> 0 | N87: =M87/$M$155 -> 0 | O87: =REPT("|",N87*(100/MAX($N$14:$N$35))) | W87: =(SUMIFS(Calculs!CB$11:CB$1338,Calculs!$B$11:$B$1338,$H87,Calculs!$F$11:$F$1338,IF($V$40="Tous","<>0",VLOOKUP($V$40,'Listes déroulantes, autres'!$H$9:$I$21,2,FALSE)),Calculs!$G$11:$G$1338,IF($W$40="Tous","<>0",$W$40),Calculs!$H$11:$H$1338,IF($X$40="Tous","<>0",$X$40) )/10^6) -> 0 | X87: =W87/$M$155 -> 0 | Y87: =REPT("|",X87*(100/MAX($N$14:$N$35)))
C88: =IF(B88=0,C87,B88) -> Catégorie 3 | F88: =IF(E88=0,F87,E88) -> 3.5 | H88: 3.5A3 | J88: =SUMIFS(Calculs!BY$11:BY$1338,Calculs!$B$11:$B$1338,$H88)/10^6 -> 0 | K88: =SUMIFS(Calculs!BZ$11:BZ$1338,Calculs!$B$11:$B$1338,$H88)/10^6 -> 0 | L88: =SUMIFS(Calculs!CA$11:CA$1338,Calculs!$B$11:$B$1338,$H88)/10^6 -> 0 | M88: =SUMIFS(Calculs!CB$11:CB$1338,Calculs!$B$11:$B$1338,$H88)/10^6 -> 0 | N88: =M88/$M$155 -> 0 | O88: =REPT("|",N88*(100/MAX($N$14:$N$35))) | W88: =(SUMIFS(Calculs!CB$11:CB$1338,Calculs!$B$11:$B$1338,$H88,Calculs!$F$11:$F$1338,IF($V$40="Tous","<>0",VLOOKUP($V$40,'Listes déroulantes, autres'!$H$9:$I$21,2,FALSE)),Calculs!$G$11:$G$1338,IF($W$40="Tous","<>0",$W$40),Calculs!$H$11:$H$1338,IF($X$40="Tous","<>0",$X$40) )/10^6) -> 0 | X88: =W88/$M$155 -> 0 | Y88: =REPT("|",X88*(100/MAX($N$14:$N$35)))
C89: =IF(B89=0,C88,B89) -> Catégorie 3 | F89: =IF(E89=0,F88,E89) -> 3.5 | H89: 3.5B1 | I89: =Calculs!B283 -> 3.5B1 - Déplacements d'affaires en avion, train ou bus | J89: =SUMIFS(Calculs!BY$11:BY$1338,Calculs!$B$11:$B$1338,$H89)/10^6 -> 5.4258133 | K89: =SUMIFS(Calculs!BZ$11:BZ$1338,Calculs!$B$11:$B$1338,$H89)/10^6 -> 0.0011480454 | L89: =SUMIFS(Calculs!CA$11:CA$1338,Calculs!$B$11:$B$1338,$H89)/10^6 -> 0.045190587 | M89: =SUMIFS(Calculs!CB$11:CB$1338,Calculs!$B$11:$B$1338,$H89)/10^6 -> 5.4721519 | N89: =M89/$M$155 -> 0.03081311 | O89: =REPT("|",N89*(100/MAX($N$14:$N$35))) -> ||||| | W89: =(SUMIFS(Calculs!CB$11:CB$1338,Calculs!$B$11:$B$1338,$H89,Calculs!$F$11:$F$1338,IF($V$40="Tous","<>0",VLOOKUP($V$40,'Listes déroulantes, autres'!$H$9:$I$21,2,FALSE)),Calculs!$G$11:$G$1338,IF($W$40="Tous","<>0",$W$40),Calculs!$H$11:$H$1338,IF($X$40="Tous","<>0",$X$40) )/10^6) -> 0 | X89: =W89/$M$155 -> 0 | Y89: =REPT("|",X89*(100/MAX($N$14:$N$35)))
C90: =IF(B90=0,C89,B90) -> Catégorie 3 | F90: =IF(E90=0,F89,E90) -> 3.5 | H90: 3.5B2 | J90: =SUMIFS(Calculs!BY$11:BY$1338,Calculs!$B$11:$B$1338,$H90)/10^6 -> 0 | K90: =SUMIFS(Calculs!BZ$11:BZ$1338,Calculs!$B$11:$B$1338,$H90)/10^6 -> 0 | L90: =SUMIFS(Calculs!CA$11:CA$1338,Calculs!$B$11:$B$1338,$H90)/10^6 -> 0 | M90: =SUMIFS(Calculs!CB$11:CB$1338,Calculs!$B$11:$B$1338,$H90)/10^6 -> 0 | N90: =M90/$M$155 -> 0 | O90: =REPT("|",N90*(100/MAX($N$14:$N$35))) | W90: =(SUMIFS(Calculs!CB$11:CB$1338,Calculs!$B$11:$B$1338,$H90,Calculs!$F$11:$F$1338,IF($V$40="Tous","<>0",VLOOKUP($V$40,'Listes déroulantes, autres'!$H$9:$I$21,2,FALSE)),Calculs!$G$11:$G$1338,IF($W$40="Tous","<>0",$W$40),Calculs!$H$11:$H$1338,IF($X$40="Tous","<>0",$X$40) )/10^6) -> 0 | X90: =W90/$M$155 -> 0 | Y90: =REPT("|",X90*(100/MAX($N$14:$N$35)))
C91: =IF(B91=0,C90,B91) -> Catégorie 3 | F91: =IF(E91=0,F90,E91) -> 3.5 | H91: 3.5C1 | I91: =Calculs!B301 -> 3.5C1 - Déplacements d'affaires en traversier | J91: =SUMIFS(Calculs!BY$11:BY$1338,Calculs!$B$11:$B$1338,$H91)/10^6 -> 0.19035792 | K91: =SUMIFS(Calculs!BZ$11:BZ$1338,Calculs!$B$11:$B$1338,$H91)/10^6 -> 0.00051334392 | L91: =SUMIFS(Calculs!CA$11:CA$1338,Calculs!$B$11:$B$1338,$H91)/10^6 -> 0.0013436519 | M91: =SUMIFS(Calculs!CB$11:CB$1338,Calculs!$B$11:$B$1338,$H91)/10^6 -> 0.19221491 | N91: =M91/$M$155 -> 0.0010823419 | O91: =REPT("|",N91*(100/MAX($N$14:$N$35))) | W91: =(SUMIFS(Calculs!CB$11:CB$1338,Calculs!$B$11:$B$1338,$H91,Calculs!$F$11:$F$1338,IF($V$40="Tous","<>0",VLOOKUP($V$40,'Listes déroulantes, autres'!$H$9:$I$21,2,FALSE)),Calculs!$G$11:$G$1338,IF($W$40="Tous","<>0",$W$40),Calculs!$H$11:$H$1338,IF($X$40="Tous","<>0",$X$40) )/10^6) -> 0 | X91: =W91/$M$155 -> 0 | Y91: =REPT("|",X91*(100/MAX($N$14:$N$35)))
C92: =IF(B92=0,C91,B92) -> Catégorie 3 | F92: =IF(E92=0,F91,E92) -> 3.5 | H92: 3.5D1 | J92: =SUMIFS(Calculs!BY$11:BY$1338,Calculs!$B$11:$B$1338,$H92)/10^6 -> 0 | K92: =SUMIFS(Calculs!BZ$11:BZ$1338,Calculs!$B$11:$B$1338,$H92)/10^6 -> 0 | L92: =SUMIFS(Calculs!CA$11:CA$1338,Calculs!$B$11:$B$1338,$H92)/10^6 -> 0 | M92: =SUMIFS(Calculs!CB$11:CB$1338,Calculs!$B$11:$B$1338,$H92)/10^6 -> 0 | N92: =M92/$M$155 -> 0 | O92: =REPT("|",N92*(100/MAX($N$14:$N$35))) | W92: =(SUMIFS(Calculs!CB$11:CB$1338,Calculs!$B$11:$B$1338,$H92,Calculs!$F$11:$F$1338,IF($V$40="Tous","<>0",VLOOKUP($V$40,'Listes déroulantes, autres'!$H$9:$I$21,2,FALSE)),Calculs!$G$11:$G$1338,IF($W$40="Tous","<>0",$W$40),Calculs!$H$11:$H$1338,IF($X$40="Tous","<>0",$X$40) )/10^6) -> 0 | X92: =W92/$M$155 -> 0 | Y92: =REPT("|",X92*(100/MAX($N$14:$N$35)))
C93: =IF(B93=0,C92,B93) -> Catégorie 3 | F93: =IF(E93=0,F92,E93) -> 3.5 | H93: 3.5E1 | J93: =SUMIFS(Calculs!BY$11:BY$1338,Calculs!$B$11:$B$1338,$H93)/10^6 -> 0 | K93: =SUMIFS(Calculs!BZ$11:BZ$1338,Calculs!$B$11:$B$1338,$H93)/10^6 -> 0 | L93: =SUMIFS(Calculs!CA$11:CA$1338,Calculs!$B$11:$B$1338,$H93)/10^6 -> 0 | M93: =SUMIFS(Calculs!CB$11:CB$1338,Calculs!$B$11:$B$1338,$H93)/10^6 -> 0 | N93: =M93/$M$155 -> 0 | O93: =REPT("|",N93*(100/MAX($N$14:$N$35))) | W93: =(SUMIFS(Calculs!CB$11:CB$1338,Calculs!$B$11:$B$1338,$H93,Calculs!$F$11:$F$1338,IF($V$40="Tous","<>0",VLOOKUP($V$40,'Listes déroulantes, autres'!$H$9:$I$21,2,FALSE)),Calculs!$G$11:$G$1338,IF($W$40="Tous","<>0",$W$40),Calculs!$H$11:$H$1338,IF($X$40="Tous","<>0",$X$40) )/10^6) -> 0 | X93: =W93/$M$155 -> 0 | Y93: =REPT("|",X93*(100/MAX($N$14:$N$35)))
C94: =IF(B94=0,C93,B94) -> Catégorie 3 | F94: =IF(E94=0,F93,E94) -> 3.5 | H94: 3.5F1 | J94: =SUMIFS(Calculs!BY$11:BY$1338,Calculs!$B$11:$B$1338,$H94)/10^6 -> 0 | K94: =SUMIFS(Calculs!BZ$11:BZ$1338,Calculs!$B$11:$B$1338,$H94)/10^6 -> 0 | L94: =SUMIFS(Calculs!CA$11:CA$1338,Calculs!$B$11:$B$1338,$H94)/10^6 -> 0 | M94: =SUMIFS(Calculs!CB$11:CB$1338,Calculs!$B$11:$B$1338,$H94)/10^6 -> 0 | N94: =M94/$M$155 -> 0 | O94: =REPT("|",N94*(100/MAX($N$14:$N$35))) | W94: =(SUMIFS(Calculs!CB$11:CB$1338,Calculs!$B$11:$B$1338,$H94,Calculs!$F$11:$F$1338,IF($V$40="Tous","<>0",VLOOKUP($V$40,'Listes déroulantes, autres'!$H$9:$I$21,2,FALSE)),Calculs!$G$11:$G$1338,IF($W$40="Tous","<>0",$W$40),Calculs!$H$11:$H$1338,IF($X$40="Tous","<>0",$X$40) )/10^6) -> 0 | X94: =W94/$M$155 -> 0 | Y94: =REPT("|",X94*(100/MAX($N$14:$N$35)))
B95: Catégorie 4 | C95: =IF(B95=0,C94,B95) -> Catégorie 4 | D95: Émissions indirects des produits utilisés par l'organisation | E95: 4.1 | F95: =IF(E95=0,F94,E95) -> 4.1 | G95: Biens et matière première | H95: 4.1A1 | I95: Appareils numériques Amorties (Va être déplacé dans 4.2) | J95: =SUMIFS(Calculs!BY$11:BY$1338,Calculs!$B$11:$B$1338,$H95)/10^6 -> 0 | K95: =SUMIFS(Calculs!BZ$11:BZ$1338,Calculs!$B$11:$B$1338,$H95)/10^6 -> 0 | L95: =SUMIFS(Calculs!CA$11:CA$1338,Calculs!$B$11:$B$1338,$H95)/10^6 -> 0 | M95: =SUMIFS(Calculs!CB$11:CB$1338,Calculs!$B$11:$B$1338,$H95)/10^6 -> 0 | N95: =M95/$M$155 -> 0 | O95: =REPT("|",N95*(100/MAX($N$14:$N$35))) | W95: =(SUMIFS(Calculs!CB$11:CB$1338,Calculs!$B$11:$B$1338,$H95,Calculs!$F$11:$F$1338,IF($V$40="Tous","<>0",VLOOKUP($V$40,'Listes déroulantes, autres'!$H$9:$I$21,2,FALSE)),Calculs!$G$11:$G$1338,IF($W$40="Tous","<>0",$W$40),Calculs!$H$11:$H$1338,IF($X$40="Tous","<>0",$X$40) )/10^6) -> 0 | X95: =W95/$M$155 -> 0 | Y95: =REPT("|",X95*(100/MAX($N$14:$N$35)))
C96: =IF(B96=0,C95,B96) -> Catégorie 4 | F96: =IF(E96=0,F95,E96) -> 4.1 | H96: 4.1A2 | I96: =Calculs!B319 -> 4.1A2 - Appareils numérique (non-amortie) | J96: =SUMIFS(Calculs!BY$11:BY$1338,Calculs!$B$11:$B$1338,$H96)/10^6 -> 0.0378272 | K96: =SUMIFS(Calculs!BZ$11:BZ$1338,Calculs!$B$11:$B$1338,$H96)/10^6 -> 0 | L96: =SUMIFS(Calculs!CA$11:CA$1338,Calculs!$B$11:$B$1338,$H96)/10^6 -> 0 | M96: =SUMIFS(Calculs!CB$11:CB$1338,Calculs!$B$11:$B$1338,$H96)/10^6 -> 0.0378272 | N96: =M96/$M$155 -> 0.00021300097 | O96: =REPT("|",N96*(100/MAX($N$14:$N$35))) | W96: =(SUMIFS(Calculs!CB$11:CB$1338,Calculs!$B$11:$B$1338,$H96,Calculs!$F$11:$F$1338,IF($V$40="Tous","<>0",VLOOKUP($V$40,'Listes déroulantes, autres'!$H$9:$I$21,2,FALSE)),Calculs!$G$11:$G$1338,IF($W$40="Tous","<>0",$W$40),Calculs!$H$11:$H$1338,IF($X$40="Tous","<>0",$X$40) )/10^6) -> 0.0045715 | X96: =W96/$M$155 -> 2.5741634e-05 | Y96: =REPT("|",X96*(100/MAX($N$14:$N$35)))
C97: =IF(B97=0,C96,B97) -> Catégorie 4 | F97: =IF(E97=0,F96,E97) -> 4.1 | H97: 4.1A3 | I97: Appareils numériques Amorties (Va être déplacé dans 4.2) | J97: =SUMIFS(Calculs!BY$11:BY$1338,Calculs!$B$11:$B$1338,$H97)/10^6 -> 0 | K97: =SUMIFS(Calculs!BZ$11:BZ$1338,Calculs!$B$11:$B$1338,$H97)/10^6 -> 0 | L97: =SUMIFS(Calculs!CA$11:CA$1338,Calculs!$B$11:$B$1338,$H97)/10^6 -> 0 | M97: =SUMIFS(Calculs!CB$11:CB$1338,Calculs!$B$11:$B$1338,$H97)/10^6 -> 0 | N97: =M97/$M$155 -> 0 | O97: =REPT("|",N97*(100/MAX($N$14:$N$35))) | W97: =(SUMIFS(Calculs!CB$11:CB$1338,Calculs!$B$11:$B$1338,$H97,Calculs!$F$11:$F$1338,IF($V$40="Tous","<>0",VLOOKUP($V$40,'Listes déroulantes, autres'!$H$9:$I$21,2,FALSE)),Calculs!$G$11:$G$1338,IF($W$40="Tous","<>0",$W$40),Calculs!$H$11:$H$1338,IF($X$40="Tous","<>0",$X$40) )/10^6) -> 0 | X97: =W97/$M$155 -> 0 | Y97: =REPT("|",X97*(100/MAX($N$14:$N$35)))
C98: =IF(B98=0,C97,B98) -> Catégorie 4 | F98: =IF(E98=0,F97,E98) -> 4.1 | H98: 4.1B1 | I98: =Calculs!B337 -> 4.1B1 - Réseaux et transfert de données | J98: =SUMIFS(Calculs!BY$11:BY$1338,Calculs!$B$11:$B$1338,$H98)/10^6 -> 0.13905 | K98: =SUMIFS(Calculs!BZ$11:BZ$1338,Calculs!$B$11:$B$1338,$H98)/10^6 -> 0 | L98: =SUMIFS(Calculs!CA$11:CA$1338,Calculs!$B$11:$B$1338,$H98)/10^6 -> 0 | M98: =SUMIFS(Calculs!CB$11:CB$1338,Calculs!$B$11:$B$1338,$H98)/10^6 -> 0.13905 | N98: =M98/$M$155 -> 0.00078297588 | O98: =REPT("|",N98*(100/MAX($N$14:$N$35))) | W98: =(SUMIFS(Calculs!CB$11:CB$1338,Calculs!$B$11:$B$1338,$H98,Calculs!$F$11:$F$1338,IF($V$40="Tous","<>0",VLOOKUP($V$40,'Listes déroulantes, autres'!$H$9:$I$21,2,FALSE)),Calculs!$G$11:$G$1338,IF($W$40="Tous","<>0",$W$40),Calculs!$H$11:$H$1338,IF($X$40="Tous","<>0",$X$40) )/10^6) -> 0 | X98: =W98/$M$155 -> 0 | Y98: =REPT("|",X98*(100/MAX($N$14:$N$35)))
C99: =IF(B99=0,C98,B99) -> Catégorie 4 | F99: =IF(E99=0,F98,E99) -> 4.1 | H99: 4.1C1 | I99: =Calculs!B355 -> 4.1C1 - Salles de serveurs | J99: =SUMIFS(Calculs!BY$11:BY$1338,Calculs!$B$11:$B$1338,$H99)/10^6 -> 97.94935 | K99: =SUMIFS(Calculs!BZ$11:BZ$1338,Calculs!$B$11:$B$1338,$H99)/10^6 -> 0 | L99: =SUMIFS(Calculs!CA$11:CA$1338,Calculs!$B$11:$B$1338,$H99)/10^6 -> 0 | M99: =SUMIFS(Calculs!CB$11:CB$1338,Calculs!$B$11:$B$1338,$H99)/10^6 -> 97.94935 | N99: =M99/$M$155 -> 0.55154246 | O99: =REPT("|",N99*(100/MAX($N$14:$N$35))) -> ||||||||||||||||||||||||||||||||||||||||||||||||||||||||||||||||||||||||||||||||||||||||| | W99: =(SUMIFS(Calculs!CB$11:CB$1338,Calculs!$B$11:$B$1338,$H99,Calculs!$F$11:$F$1338,IF($V$40="Tous","<>0",VLOOKUP($V$40,'Listes déroulantes, autres'!$H$9:$I$21,2,FALSE)),Calculs!$G$11:$G$1338,IF($W$40="Tous","<>0",$W$40),Calculs!$H$11:$H$1338,IF($X$40="Tous","<>0",$X$40) )/10^6) -> 47.247902 | X99: =W99/$M$155 -> 0.26604795 | Y99: =REPT("|",X99*(100/MAX($N$14:$N$35))) -> |||||||||||||||||||||||||||||||||||||||||||
C100: =IF(B100=0,C99,B100) -> Catégorie 4 | F100: =IF(E100=0,F99,E100) -> 4.1 | H100: 4.1D1 | I100: =Calculs!B373 -> 4.1D1 - Émissions liées à la production de papier d'imprimante | J100: =SUMIFS(Calculs!BY$11:BY$1338,Calculs!$B$11:$B$1338,$H100)/10^6 -> 0.0059094 | K100: =SUMIFS(Calculs!BZ$11:BZ$1338,Calculs!$B$11:$B$1338,$H100)/10^6 -> 0 | L100: =SUMIFS(Calculs!CA$11:CA$1338,Calculs!$B$11:$B$1338,$H100)/10^6 -> 0 | M100: =SUMIFS(Calculs!CB$11:CB$1338,Calculs!$B$11:$B$1338,$H100)/10^6 -> 0.0059094 | N100: =M100/$M$155 -> 3.3275208e-05 | O100: =REPT("|",N100*(100/MAX($N$14:$N$35))) | W100: =(SUMIFS(Calculs!CB$11:CB$1338,Calculs!$B$11:$B$1338,$H100,Calculs!$F$11:$F$1338,IF($V$40="Tous","<>0",VLOOKUP($V$40,'Listes déroulantes, autres'!$H$9:$I$21,2,FALSE)),Calculs!$G$11:$G$1338,IF($W$40="Tous","<>0",$W$40),Calculs!$H$11:$H$1338,IF($X$40="Tous","<>0",$X$40) )/10^6) -> 0.0024114 | X100: =W100/$M$155 -> 1.3578339e-05 | Y100: =REPT("|",X100*(100/MAX($N$14:$N$35)))
C101: =IF(B101=0,C100,B101) -> Catégorie 4 | F101: =IF(E101=0,F100,E101) -> 4.1 | H101: 4.1D2 | J101: =SUMIFS(Calculs!BY$11:BY$1338,Calculs!$B$11:$B$1338,$H101)/10^6 -> 0 | K101: =SUMIFS(Calculs!BZ$11:BZ$1338,Calculs!$B$11:$B$1338,$H101)/10^6 -> 0 | L101: =SUMIFS(Calculs!CA$11:CA$1338,Calculs!$B$11:$B$1338,$H101)/10^6 -> 0 | M101: =SUMIFS(Calculs!CB$11:CB$1338,Calculs!$B$11:$B$1338,$H101)/10^6 -> 0 | N101: =M101/$M$155 -> 0 | O101: =REPT("|",N101*(100/MAX($N$14:$N$35))) | W101: =(SUMIFS(Calculs!CB$11:CB$1338,Calculs!$B$11:$B$1338,$H101,Calculs!$F$11:$F$1338,IF($V$40="Tous","<>0",VLOOKUP($V$40,'Listes déroulantes, autres'!$H$9:$I$21,2,FALSE)),Calculs!$G$11:$G$1338,IF($W$40="Tous","<>0",$W$40),Calculs!$H$11:$H$1338,IF($X$40="Tous","<>0",$X$40) )/10^6) -> 0 | X101: =W101/$M$155 -> 0 | Y101: =REPT("|",X101*(100/MAX($N$14:$N$35)))
C102: =IF(B102=0,C101,B102) -> Catégorie 4 | F102: =IF(E102=0,F101,E102) -> 4.1 | H102: 4.1E1 | I102: =Calculs!B391 -> 4.1E1 - Production des aliments | J102: =SUMIFS(Calculs!BY$11:BY$1338,Calculs!$B$11:$B$1338,$H102)/10^6 -> 10.264 | K102: =SUMIFS(Calculs!BZ$11:BZ$1338,Calculs!$B$11:$B$1338,$H102)/10^6 -> 0 | L102: =SUMIFS(Calculs!CA$11:CA$1338,Calculs!$B$11:$B$1338,$H102)/10^6 -> 0 | M102: =SUMIFS(Calculs!CB$11:CB$1338,Calculs!$B$11:$B$1338,$H102)/10^6 -> 10.264 | N102: =M102/$M$155 -> 0.057795501 | O102: =REPT("|",N102*(100/MAX($N$14:$N$35))) -> ||||||||| | W102: =(SUMIFS(Calculs!CB$11:CB$1338,Calculs!$B$11:$B$1338,$H102,Calculs!$F$11:$F$1338,IF($V$40="Tous","<>0",VLOOKUP($V$40,'Listes déroulantes, autres'!$H$9:$I$21,2,FALSE)),Calculs!$G$11:$G$1338,IF($W$40="Tous","<>0",$W$40),Calculs!$H$11:$H$1338,IF($X$40="Tous","<>0",$X$40) )/10^6) -> 10.264 | X102: =W102/$M$155 -> 0.057795501 | Y102: =REPT("|",X102*(100/MAX($N$14:$N$35))) -> |||||||||
C103: =IF(B103=0,C102,B103) -> Catégorie 4 | F103: =IF(E103=0,F102,E103) -> 4.1 | H103: 4.1E2 | I103: =Calculs!B409 -> 4.1E2 - Production des repas et des boissons | J103: =SUMIFS(Calculs!BY$11:BY$1338,Calculs!$B$11:$B$1338,$H103)/10^6 -> 0.765 | K103: =SUMIFS(Calculs!BZ$11:BZ$1338,Calculs!$B$11:$B$1338,$H103)/10^6 -> 0 | L103: =SUMIFS(Calculs!CA$11:CA$1338,Calculs!$B$11:$B$1338,$H103)/10^6 -> 0 | M103: =SUMIFS(Calculs!CB$11:CB$1338,Calculs!$B$11:$B$1338,$H103)/10^6 -> 0.765 | N103: =M103/$M$155 -> 0.0043076343 | O103: =REPT("|",N103*(100/MAX($N$14:$N$35))) | W103: =(SUMIFS(Calculs!CB$11:CB$1338,Calculs!$B$11:$B$1338,$H103,Calculs!$F$11:$F$1338,IF($V$40="Tous","<>0",VLOOKUP($V$40,'Listes déroulantes, autres'!$H$9:$I$21,2,FALSE)),Calculs!$G$11:$G$1338,IF($W$40="Tous","<>0",$W$40),Calculs!$H$11:$H$1338,IF($X$40="Tous","<>0",$X$40) )/10^6) -> 0.765 | X103: =W103/$M$155 -> 0.0043076343 | Y103: =REPT("|",X103*(100/MAX($N$14:$N$35)))
...

Sheet GHG Protocol

Sheet MACF-CBAM

Sheet Détails Entreprise
B2: Détails sur l'entreprise et ses actifs
B4: Nom de l'entreprise : | C4: EntrepTest
B5: Adresse de la maison mère : | C5: 1234 St-Montréal road, Saguenay
B7: Liste des lieux de production | H7: Produits et services | O7: Liste de la flotte de véhicule
B8: Nom du lieu | C8: Description | D8: Adresse | E8: GES par Site [tCO2e] | H8: Nom du produit ou service | I8: Description | J8: GES par unité [kgCO2e/unité] | K8: Quantité | L8: unité | M8: GES pour toute la game de produit [tCO2e] | O8: Nom ou numéro du véhicule | P8: Année | Q8: Marque | R8: Modèle | S8: Type de véhicule | T8: Climatisation
B9: Bureau | D9: 1234 St-Montréal road, Saguenay | E9: =SUMIFS(Calculs!$CC$11:$CC$1338,Calculs!$G$11:$G$1338,$B9) -> 60.851452 | H9: Nettoyage | I9: Service de nettoyage | J9: =IF(K9=0,,M9*1000/(K9)) -> 0.54363265 | K9: 2500 | L9: h | M9: =SUMIFS(Calculs!$CC$11:$CC$1338,Calculs!$H$11:$H$1338,$H9) -> 1.3590816 | O9: Petit camion #1 | S9: Camion léger - Essence [L] | T9: Oui
B10: Usine #1 | D10: 555 boul. industriel | E10: =SUMIFS(Calculs!$CC$11:$CC$1338,Calculs!$G$11:$G$1338,$B10) -> 64.164545 | H10: Balais | I10: Fabrication de balais | J10: =IF(K10=0,,M10*1000/(K10)) -> 6.5104525 | K10: 1500 | L10: nb | M10: =SUMIFS(Calculs!$CC$11:$CC$1338,Calculs!$H$11:$H$1338,$H10) -> 9.7656788 | O10: Gros camion #2 | S10: Camion lourd - Diesel [L] | T10: Oui
B11: Usine #2 | D11: 556 boul. Industriel | E11: =SUMIFS(Calculs!$CC$11:$CC$1338,Calculs!$G$11:$G$1338,$B11) -> 29.713885 | J11: =IF(K11=0,,M11*1000/(K11)) -> 0 | M11: =SUMIFS(Calculs!$CC$11:$CC$1338,Calculs!$H$11:$H$1338,$H11) -> 0
B12: Shop | D12: 111 rue principale | E12: =SUMIFS(Calculs!$CC$11:$CC$1338,Calculs!$G$11:$G$1338,$B12) -> 17.972081 | J12: =IF(K12=0,,M12*1000/(K12)) -> 0 | M12: =SUMIFS(Calculs!$CC$11:$CC$1338,Calculs!$H$11:$H$1338,$H12) -> 0
E13: =SUMIFS(Calculs!$CC$11:$CC$1338,Calculs!$G$11:$G$1338,$B13) -> 0 | J13: =IF(K13=0,,M13*1000/(K13)) -> 0 | M13: =SUMIFS(Calculs!$CC$11:$CC$1338,Calculs!$H$11:$H$1338,$H13) -> 0
E14: =SUMIFS(Calculs!$CC$11:$CC$1338,Calculs!$G$11:$G$1338,$B14) -> 0 | J14: =IF(K14=0,,M14*1000/(K14)) -> 0 | M14: =SUMIFS(Calculs!$CC$11:$CC$1338,Calculs!$H$11:$H$1338,$H14) -> 0
E15: =SUMIFS(Calculs!$CC$11:$CC$1338,Calculs!$G$11:$G$1338,$B15) -> 0 | J15: =IF(K15=0,,M15*1000/(K15)) -> 0 | M15: =SUMIFS(Calculs!$CC$11:$CC$1338,Calculs!$H$11:$H$1338,$H15) -> 0
E16: =SUMIFS(Calculs!$CC$11:$CC$1338,Calculs!$G$11:$G$1338,$B16) -> 0 | J16: =IF(K16=0,,M16*1000/(K16)) -> 0 | M16: =SUMIFS(Calculs!$CC$11:$CC$1338,Calculs!$H$11:$H$1338,$H16) -> 0
E17: =SUMIFS(Calculs!$CC$11:$CC$1338,Calculs!$G$11:$G$1338,$B17) -> 0 | J17: =IF(K17=0,,M17*1000/(K17)) -> 0 | M17: =SUMIFS(Calculs!$CC$11:$CC$1338,Calculs!$H$11:$H$1338,$H17) -> 0
E18: =SUMIFS(Calculs!$CC$11:$CC$1338,Calculs!$G$11:$G$1338,$B18) -> 0 | J18: =IF(K18=0,,M18*1000/(K18)) -> 0 | M18: =SUMIFS(Calculs!$CC$11:$CC$1338,Calculs!$H$11:$H$1338,$H18) -> 0
E19: =SUMIFS(Calculs!$CC$11:$CC$1338,Calculs!$G$11:$G$1338,$B19) -> 0 | J19: =IF(K19=0,,M19*1000/(K19)) -> 0 | M19: =SUMIFS(Calculs!$CC$11:$CC$1338,Calculs!$H$11:$H$1338,$H19) -> 0
B20: ="" | C20: GES non attribué | E20: =SUMIFS(Calculs!$CC$11:$CC$1338,Calculs!$G$11:$G$1338,$B20) -> 4.8897152 | H20: ="" | I20: GES non attribué | M20: =SUMIFS(Calculs!$CC$11:$CC$1338,Calculs!$H$11:$H$1338,$H20) -> 166.46692
B21: Tous | E21: =SUM(E9:E20) -> 177.59168 | H21: Tous | K21: =SUM(K9:K20) -> 4000 | M21: =SUM(M9:M20) -> 177.59168 | T21: =COUNTIF(T9:T20,"oui") -> 2

Sheet Calculs
B1: Calculs | BQ1: Résultats
B3: # méthode | C3: Liste | D3: Description | E3: Date | F3: mois | G3: Site | H3: Produit | I3: Références | J3: Utilisation et Combustible | K3: Quantité combustible (équipements fixes) | M3: Type de véhicule et type de carburant | N3: Coûts en carburants | O3: Prix moyenne du carburant | P3: Année | Q3: Marque | R3: Modèle | S3: Transmission | T3: Distance parcourus | U3: Véhicule | V3: Consommation moyenne de carburant | W3: Quantité de carburant (Équipements mobiles) | Y3: Province | Z3: Consommation moyenne [kWh] | AA3: Estimation | AC3: Type d'équipement de réfrigéation | AD3: Type de réfrigérant | AE3: Quantité dans l'équipement | AF3: Fuites constaté par le frigoriste | AG3: Climatisation des véhicules (oui/non) | AH3: Réseaux électrique | AI3: Quantité d'électricité | AJ3: Intensité carbone du marché | AK3: Type d'aliment | AL3: Type de repas | AM3: Quantité | AO3: Événement | AP3: Mode de transport | AQ3: Consommation | AR3: Distance | AT3: Quantité de carburant | AU3: Nombre de passagers | AV3: Nombre de véhicules | AW3: Origine et destination | AX3: Aller et retour ? | AY3: Nombre de jours de travail par années | AZ3: Nombre de déplacements identiques | BA3: Type d'appareil numérique | BB3: Quantité | BC3: Type de réseau internet | BD3: Qunatité de données | BE3: Type de salle de serveurs | BF3: Superficie | BG3: Taille du papier | BH3: Proportion de papier recyclé | BI3: Quantité | BJ3: Type de traitement des eaux usées | BK3: Quantité | BQ3: Probabilité de fuite | BR3: Fuite estimé à partir des probabilité | BS3: Fuites calculée | BT3: PRP | BU3: Distances | BV3: Qte de carburant | BY3: CO2 | BZ3: CH4 | CA3: N2O | CB3: Total GES : | CE3: Total CO2 Biogénique : | CH3: Énergie équivalente
B5: 1.1A1 - Chauffage des bâtiments et équipements fixes
B7: Données d'activité | BQ7: Calculs et résultats
B8: # méthode | C8: Liste d'équipements ou de groupes d'équipements fixes | D8: Description | E8: Date | F8: mois | G8: Site | H8: Produit | I8: Références | J8: Utilisation et Combustible | K8: Quantité Totale | BY8: Émissions GES | CB8: Total GES : | CE8: Total CO2 Biogénique : | CH8: Énergie équivalente
BY9: CO2 | BZ9: CH4 | CA9: N2O
D10: (Facultatif) | E10: (Facultatif) | G10: (Facultatif) | H10: (Facultatif) | I10: (Facultatif) | J10: (Sélectionner) | K10: Qte | BY10: [gCO2e] | BZ10: [gCO2e] | CA10: [gCO2e] | CB10: [gCO2e] | CC10: [tCO2e] | CE10: [gCO2e] | CF10: [tCO2e] | CH10: [kWh]
B11: 1.1A1 | F11: =IF(E11=0,"",MONTH(E11)) | L11: =IFERROR(VLOOKUP(J11,FÉ!$B$10:$L$22,5,FALSE),"") | BY11: =IF($J11=0, ,VLOOKUP($J11,FÉ!$B$9:$K$22,8,FALSE)*$K11*PRP!$J$8) -> 0 | BZ11: =IF($J11=0, ,VLOOKUP($J11,FÉ!$B$9:$K$22,9,FALSE)*$K11*PRP!$J$9) -> 0 | CA11: =IF($J11=0, ,VLOOKUP($J11,FÉ!$B$9:$K$22,10,FALSE)*$K11*PRP!$J$10) -> 0 | CB11: =SUM(BY11:CA11) -> 0 | CC11: =CB11/(10^6) -> 0 | CE11: =IF(J11=FÉ!$B$12,K11* FÉ!$Q$12,) -> 0 | CF11: =CE11/(10^6) -> 0 | CH11: =IF($J11=0, ,VLOOKUP($J11,FÉ!$B$9:$K$22,7,FALSE))*K11 -> 0
B12: =B11 -> 1.1A1 | C12: Chaudière #1 | E12: 45658 | F12: =IF(E12=0,"",MONTH(E12)) -> 1 | G12: Usine #1 | H12: Balais | J12: Génératrice - Mazout [L] | K12: 1000 | L12: =IFERROR(VLOOKUP(J12,FÉ!$B$10:$L$22,5,FALSE),"") -> L | BY12: =IF($J12=0, ,VLOOKUP($J12,FÉ!$B$9:$K$22,8,FALSE)*$K12*PRP!$J$8) -> 2753000 | BZ12: =IF($J12=0, ,VLOOKUP($J12,FÉ!$B$9:$K$22,9,FALSE)*$K12*PRP!$J$9) -> 5364 | CA12: =IF($J12=0, ,VLOOKUP($J12,FÉ!$B$9:$K$22,10,FALSE)*$K12*PRP!$J$10) -> 8463 | CB12: =SUM(BY12:CA12) -> 2766827 | CC12: =CB12/(10^6) -> 2.766827 | CE12: =IF(J12=FÉ!$B$12,K12* FÉ!$Q$12,) -> 0 | CF12: =CE12/(10^6) -> 0 | CH12: =IF($J12=0, ,VLOOKUP($J12,FÉ!$B$9:$K$22,7,FALSE))*K12 -> 10770
B13: =B12 -> 1.1A1 | C13: Poêle à bois | F13: =IF(E13=0,"",MONTH(E13)) | G13: Bureau | J13: Chauffage - Bois [kg] | K13: 1500 | L13: =IFERROR(VLOOKUP(J13,FÉ!$B$10:$L$22,5,FALSE),"") -> kg | BY13: =IF($J13=0, ,VLOOKUP($J13,FÉ!$B$9:$K$22,8,FALSE)*$K13*PRP!$J$8) -> 0 | BZ13: =IF($J13=0, ,VLOOKUP($J13,FÉ!$B$9:$K$22,9,FALSE)*$K13*PRP!$J$9) -> 25747.2 | CA13: =IF($J13=0, ,VLOOKUP($J13,FÉ!$B$9:$K$22,10,FALSE)*$K13*PRP!$J$10) -> 31531.5 | CB13: =SUM(BY13:CA13) -> 57278.7 | CC13: =CB13/(10^6) -> 0.0572787 | CE13: =IF(J13=FÉ!$B$12,K13* FÉ!$Q$12,) -> 2698500 | CF13: =CE13/(10^6) -> 2.6985 | CH13: =IF($J13=0, ,VLOOKUP($J13,FÉ!$B$9:$K$22,7,FALSE))*K13 -> 7995
B14: =B13 -> 1.1A1 | F14: =IF(E14=0,"",MONTH(E14)) | G14: Usine #1 | J14: Chauffage - Propane [L] | K14: 1000 | L14: =IFERROR(VLOOKUP(J14,FÉ!$B$10:$L$22,5,FALSE),"") -> L | BY14: =IF($J14=0, ,VLOOKUP($J14,FÉ!$B$9:$K$22,8,FALSE)*$K14*PRP!$J$8) -> 1515000 | BZ14: =IF($J14=0, ,VLOOKUP($J14,FÉ!$B$9:$K$22,9,FALSE)*$K14*PRP!$J$9) -> 804.6 | CA14: =IF($J14=0, ,VLOOKUP($J14,FÉ!$B$9:$K$22,10,FALSE)*$K14*PRP!$J$10) -> 29484 | CB14: =SUM(BY14:CA14) -> 1545288.6 | CC14: =CB14/(10^6) -> 1.5452886 | CE14: =IF(J14=FÉ!$B$12,K14* FÉ!$Q$12,) -> 0 | CF14: =CE14/(10^6) -> 0 | CH14: =IF($J14=0, ,VLOOKUP($J14,FÉ!$B$9:$K$22,7,FALSE))*K14 -> 7030
B15: =B14 -> 1.1A1 | F15: =IF(E15=0,"",MONTH(E15)) | L15: =IFERROR(VLOOKUP(J15,FÉ!$B$10:$L$22,5,FALSE),"") | BY15: =IF($J15=0, ,VLOOKUP($J15,FÉ!$B$9:$K$22,8,FALSE)*$K15*PRP!$J$8) -> 0 | BZ15: =IF($J15=0, ,VLOOKUP($J15,FÉ!$B$9:$K$22,9,FALSE)*$K15*PRP!$J$9) -> 0 | CA15: =IF($J15=0, ,VLOOKUP($J15,FÉ!$B$9:$K$22,10,FALSE)*$K15*PRP!$J$10) -> 0 | CB15: =SUM(BY15:CA15) -> 0 | CC15: =CB15/(10^6) -> 0 | CE15: =IF(J15=FÉ!$B$12,K15* FÉ!$Q$12,) -> 0 | CF15: =CE15/(10^6) -> 0 | CH15: =IF($J15=0, ,VLOOKUP($J15,FÉ!$B$9:$K$22,7,FALSE))*K15 -> 0
B16: =B15 -> 1.1A1 | F16: =IF(E16=0,"",MONTH(E16)) | L16: =IFERROR(VLOOKUP(J16,FÉ!$B$10:$L$22,5,FALSE),"") | BY16: =IF($J16=0, ,VLOOKUP($J16,FÉ!$B$9:$K$22,8,FALSE)*$K16*PRP!$J$8) -> 0 | BZ16: =IF($J16=0, ,VLOOKUP($J16,FÉ!$B$9:$K$22,9,FALSE)*$K16*PRP!$J$9) -> 0 | CA16: =IF($J16=0, ,VLOOKUP($J16,FÉ!$B$9:$K$22,10,FALSE)*$K16*PRP!$J$10) -> 0 | CB16: =SUM(BY16:CA16) -> 0 | CC16: =CB16/(10^6) -> 0 | CE16: =IF(J16=FÉ!$B$12,K16* FÉ!$Q$12,) -> 0 | CF16: =CE16/(10^6) -> 0 | CH16: =IF($J16=0, ,VLOOKUP($J16,FÉ!$B$9:$K$22,7,FALSE))*K16 -> 0
B17: =B16 -> 1.1A1 | F17: =IF(E17=0,"",MONTH(E17)) | L17: =IFERROR(VLOOKUP(J17,FÉ!$B$10:$L$22,5,FALSE),"") | BY17: =IF($J17=0, ,VLOOKUP($J17,FÉ!$B$9:$K$22,8,FALSE)*$K17*PRP!$J$8) -> 0 | BZ17: =IF($J17=0, ,VLOOKUP($J17,FÉ!$B$9:$K$22,9,FALSE)*$K17*PRP!$J$9) -> 0 | CA17: =IF($J17=0, ,VLOOKUP($J17,FÉ!$B$9:$K$22,10,FALSE)*$K17*PRP!$J$10) -> 0 | CB17: =SUM(BY17:CA17) -> 0 | CC17: =CB17/(10^6) -> 0 | CE17: =IF(J17=FÉ!$B$12,K17* FÉ!$Q$12,) -> 0 | CF17: =CE17/(10^6) -> 0 | CH17: =IF($J17=0, ,VLOOKUP($J17,FÉ!$B$9:$K$22,7,FALSE))*K17 -> 0
B18: =B17 -> 1.1A1 | F18: =IF(E18=0,"",MONTH(E18)) | L18: =IFERROR(VLOOKUP(J18,FÉ!$B$10:$L$22,5,FALSE),"") | BY18: =IF($J18=0, ,VLOOKUP($J18,FÉ!$B$9:$K$22,8,FALSE)*$K18*PRP!$J$8) -> 0 | BZ18: =IF($J18=0, ,VLOOKUP($J18,FÉ!$B$9:$K$22,9,FALSE)*$K18*PRP!$J$9) -> 0 | CA18: =IF($J18=0, ,VLOOKUP($J18,FÉ!$B$9:$K$22,10,FALSE)*$K18*PRP!$J$10) -> 0 | CB18: =SUM(BY18:CA18) -> 0 | CC18: =CB18/(10^6) -> 0 | CE18: =IF(J18=FÉ!$B$12,K18* FÉ!$Q$12,) -> 0 | CF18: =CE18/(10^6) -> 0 | CH18: =IF($J18=0, ,VLOOKUP($J18,FÉ!$B$9:$K$22,7,FALSE))*K18 -> 0
B19: =B18 -> 1.1A1 | F19: =IF(E19=0,"",MONTH(E19)) | L19: =IFERROR(VLOOKUP(J19,FÉ!$B$10:$L$22,5,FALSE),"") | BY19: =IF($J19=0, ,VLOOKUP($J19,FÉ!$B$9:$K$22,8,FALSE)*$K19*PRP!$J$8) -> 0 | BZ19: =IF($J19=0, ,VLOOKUP($J19,FÉ!$B$9:$K$22,9,FALSE)*$K19*PRP!$J$9) -> 0 | CA19: =IF($J19=0, ,VLOOKUP($J19,FÉ!$B$9:$K$22,10,FALSE)*$K19*PRP!$J$10) -> 0 | CB19: =SUM(BY19:CA19) -> 0 | CC19: =CB19/(10^6) -> 0 | CE19: =IF(J19=FÉ!$B$12,K19* FÉ!$Q$12,) -> 0 | CF19: =CE19/(10^6) -> 0 | CH19: =IF($J19=0, ,VLOOKUP($J19,FÉ!$B$9:$K$22,7,FALSE))*K19 -> 0
B20: =B19 -> 1.1A1 | F20: =IF(E20=0,"",MONTH(E20)) | L20: =IFERROR(VLOOKUP(J20,FÉ!$B$10:$L$22,5,FALSE),"") | BY20: =IF($J20=0, ,VLOOKUP($J20,FÉ!$B$9:$K$22,8,FALSE)*$K20*PRP!$J$8) -> 0 | BZ20: =IF($J20=0, ,VLOOKUP($J20,FÉ!$B$9:$K$22,9,FALSE)*$K20*PRP!$J$9) -> 0 | CA20: =IF($J20=0, ,VLOOKUP($J20,FÉ!$B$9:$K$22,10,FALSE)*$K20*PRP!$J$10) -> 0 | CB20: =SUM(BY20:CA20) -> 0 | CC20: =CB20/(10^6) -> 0 | CE20: =IF(J20=FÉ!$B$12,K20* FÉ!$Q$12,) -> 0 | CF20: =CE20/(10^6) -> 0 | CH20: =IF($J20=0, ,VLOOKUP($J20,FÉ!$B$9:$K$22,7,FALSE))*K20 -> 0
B21: =B20 -> 1.1A1 | F21: =IF(E21=0,"",MONTH(E21)) | L21: =IFERROR(VLOOKUP(J21,FÉ!$B$10:$L$22,5,FALSE),"") | BY21: =IF($J21=0, ,VLOOKUP($J21,FÉ!$B$9:$K$22,8,FALSE)*$K21*PRP!$J$8) -> 0 | BZ21: =IF($J21=0, ,VLOOKUP($J21,FÉ!$B$9:$K$22,9,FALSE)*$K21*PRP!$J$9) -> 0 | CA21: =IF($J21=0, ,VLOOKUP($J21,FÉ!$B$9:$K$22,10,FALSE)*$K21*PRP!$J$10) -> 0 | CB21: =SUM(BY21:CA21) -> 0 | CC21: =CB21/(10^6) -> 0 | CE21: =IF(J21=FÉ!$B$12,K21* FÉ!$Q$12,) -> 0 | CF21: =CE21/(10^6) -> 0 | CH21: =IF($J21=0, ,VLOOKUP($J21,FÉ!$B$9:$K$22,7,FALSE))*K21 -> 0
B22: =B21 -> 1.1A1 | F22: =IF(E22=0,"",MONTH(E22)) | L22: =IFERROR(VLOOKUP(J22,FÉ!$B$10:$L$22,5,FALSE),"") | BY22: =IF($J22=0, ,VLOOKUP($J22,FÉ!$B$9:$K$22,8,FALSE)*$K22*PRP!$J$8) -> 0 | BZ22: =IF($J22=0, ,VLOOKUP($J22,FÉ!$B$9:$K$22,9,FALSE)*$K22*PRP!$J$9) -> 0 | CA22: =IF($J22=0, ,VLOOKUP($J22,FÉ!$B$9:$K$22,10,FALSE)*$K22*PRP!$J$10) -> 0 | CB22: =SUM(BY22:CA22) -> 0 | CC22: =CB22/(10^6) -> 0 | CE22: =IF(J22=FÉ!$B$12,K22* FÉ!$Q$12,) -> 0 | CF22: =CE22/(10^6) -> 0 | CH22: =IF($J22=0, ,VLOOKUP($J22,FÉ!$B$9:$K$22,7,FALSE))*K22 -> 0
B23: =B22 -> 1.1A1 | F23: =IF(E23=0,"",MONTH(E23)) | L23: =IFERROR(VLOOKUP(J23,FÉ!$B$10:$L$22,5,FALSE),"") | BY23: =IF($J23=0, ,VLOOKUP($J23,FÉ!$B$9:$K$22,8,FALSE)*$K23*PRP!$J$8) -> 0 | BZ23: =IF($J23=0, ,VLOOKUP($J23,FÉ!$B$9:$K$22,9,FALSE)*$K23*PRP!$J$9) -> 0 | CA23: =IF($J23=0, ,VLOOKUP($J23,FÉ!$B$9:$K$22,10,FALSE)*$K23*PRP!$J$10) -> 0 | CB23: =SUM(BY23:CA23) -> 0 | CC23: =CB23/(10^6) -> 0 | CE23: =IF(J23=FÉ!$B$12,K23* FÉ!$Q$12,) -> 0 | CF23: =CE23/(10^6) -> 0 | CH23: =IF($J23=0, ,VLOOKUP($J23,FÉ!$B$9:$K$22,7,FALSE))*K23 -> 0
B24: =B23 -> 1.1A1 | F24: =IF(E24=0,"",MONTH(E24)) | L24: =IFERROR(VLOOKUP(J24,FÉ!$B$10:$L$22,5,FALSE),"") | BY24: =IF($J24=0, ,VLOOKUP($J24,FÉ!$B$9:$K$22,8,FALSE)*$K24*PRP!$J$8) -> 0 | BZ24: =IF($J24=0, ,VLOOKUP($J24,FÉ!$B$9:$K$22,9,FALSE)*$K24*PRP!$J$9) -> 0 | CA24: =IF($J24=0, ,VLOOKUP($J24,FÉ!$B$9:$K$22,10,FALSE)*$K24*PRP!$J$10) -> 0 | CB24: =SUM(BY24:CA24) -> 0 | CC24: =CB24/(10^6) -> 0 | CE24: =IF(J24=FÉ!$B$12,K24* FÉ!$Q$12,) -> 0 | CF24: =CE24/(10^6) -> 0 | CH24: =IF($J24=0, ,VLOOKUP($J24,FÉ!$B$9:$K$22,7,FALSE))*K24 -> 0
B25: =B24 -> 1.1A1 | F25: =IF(E25=0,"",MONTH(E25)) | L25: =IFERROR(VLOOKUP(J25,FÉ!$B$10:$L$22,5,FALSE),"") | BY25: =IF($J25=0, ,VLOOKUP($J25,FÉ!$B$9:$K$22,8,FALSE)*$K25*PRP!$J$8) -> 0 | BZ25: =IF($J25=0, ,VLOOKUP($J25,FÉ!$B$9:$K$22,9,FALSE)*$K25*PRP!$J$9) -> 0 | CA25: =IF($J25=0, ,VLOOKUP($J25,FÉ!$B$9:$K$22,10,FALSE)*$K25*PRP!$J$10) -> 0 | CB25: =SUM(BY25:CA25) -> 0 | CC25: =CB25/(10^6) -> 0 | CE25: =IF(J25=FÉ!$B$12,K25* FÉ!$Q$12,) -> 0 | CF25: =CE25/(10^6) -> 0 | CH25: =IF($J25=0, ,VLOOKUP($J25,FÉ!$B$9:$K$22,7,FALSE))*K25 -> 0
B26: =B25 -> 1.1A1 | F26: =IF(E26=0,"",MONTH(E26)) | L26: =IFERROR(VLOOKUP(J26,FÉ!$B$10:$L$22,5,FALSE),"") | BY26: =IF($J26=0, ,VLOOKUP($J26,FÉ!$B$9:$K$22,8,FALSE)*$K26*PRP!$J$8) -> 0 | BZ26: =IF($J26=0, ,VLOOKUP($J26,FÉ!$B$9:$K$22,9,FALSE)*$K26*PRP!$J$9) -> 0 | CA26: =IF($J26=0, ,VLOOKUP($J26,FÉ!$B$9:$K$22,10,FALSE)*$K26*PRP!$J$10) -> 0 | CB26: =SUM(BY26:CA26) -> 0 | CC26: =CB26/(10^6) -> 0 | CE26: =IF(J26=FÉ!$B$12,K26* FÉ!$Q$12,) -> 0 | CF26: =CE26/(10^6) -> 0 | CH26: =IF($J26=0, ,VLOOKUP($J26,FÉ!$B$9:$K$22,7,FALSE))*K26 -> 0
... B30: =B29 -> 1.1A1 | F30: =IF(E30=0,"",MONTH(E30)) | L30: =IFERROR(VLOOKUP(J30,FÉ!$B$10:$L$22,5,FALSE),"") | BY30: =IF($J30=0, ,VLOOKUP($J30,FÉ!$B$9:$K$22,8,FALSE)*$K30*PRP!$J$8) -> 0 | BZ30: =IF($J30=0, ,VLOOKUP($J30,FÉ!$B$9:$K$22,9,FALSE)*$K30*PRP!$J$9) -> 0 | CA30: =IF($J30=0, ,VLOOKUP($J30,FÉ!$B$9:$K$22,10,FALSE)*$K30*PRP!$J$10) -> 0 | CB30: =SUM(BY30:CA30) -> 0 | CC30: =CB30/(10^6) -> 0 | CE30: =IF(J30=FÉ!$B$12,K30* FÉ!$Q$12,) -> 0 | CF30: =CE30/(10^6) -> 0 | CH30: =IF($J30=0, ,VLOOKUP($J30,FÉ!$B$9:$K$22,7,FALSE))*K30 -> 0
F31: =$B11 -> 1.1A1 | G31: =$B11 -> 1.1A1 | H31: =$B11 -> 1.1A1 | K31: =SUM(K11:K30) -> 3500 | BY31: =SUM(BY11:BY30) -> 4268000 | BZ31: =SUM(BZ11:BZ30) -> 31915.8 | CA31: =SUM(CA11:CA30) -> 69478.5 | CB31: =SUM(CB11:CB30) -> 4369394.3 | CC31: =SUM(CC11:CC30) -> 4.3693943 | CE31: =SUM(CE11:CE30) -> 2698500 | CF31: =SUM(CF11:CF30) -> 2.6985 | CH31: =SUM(CH11:CH30) -> 25795
B33: 1.2A1 - Véhicules (Par la quantité de combustible consommée)
B35: Données d'activité | BQ35: Calculs et résultats
B36: # méthode | C36: Liste des véhicules ou des groupes de véhicules | D36: Description | E36: Date | F36: mois | G36: Site | H36: Produit | I36: Références | M36: Type de véhicule et type de carburant | W36: Quantité Totale | BY36: Émissions GES | CB36: Total GES : | CE36: Total CO2 Biogénique : | CH36: Énergie équivalente
BY37: CO2 | BZ37: CH4 | CA37: N2O
D38: (Facultatif) | E38: (Facultatif) | G38: (Facultatif) | H38: (Facultatif) | I38: (Facultatif) | M38: (Sélectionner) | W38: Qte | BY38: [gCO2e] | BZ38: [gCO2e] | CA38: [gCO2e] | CB38: [gCO2e] | CC38: [tCO2e] | CE38: [gCO2e] | CF38: [tCO2e] | CH38: [kWh]
B39: 1.2A1 | F39: =IF(E39=0,"",MONTH(E39)) | X39: =IFERROR(VLOOKUP(M39,FÉ!$B$41:$L$59,5,FALSE),"") | BY39: =IF($M39=0, ,VLOOKUP($M39,FÉ!$B$41:$L$59,8,FALSE)*$W39*PRP!$J$8) -> 0 | BZ39: =IF($M39=0, ,VLOOKUP($M39,FÉ!$B$41:$L$59,9,FALSE)*$W39*PRP!$J$9) -> 0 | CA39: =IF($M39=0, ,VLOOKUP($M39,FÉ!$B$41:$L$59,10,FALSE)*$W39*PRP!$J$10) -> 0 | CB39: =SUM(BY39:CA39) -> 0 | CC39: =CB39/(10^6) -> 0 | CH39: =IF($M39=0, ,VLOOKUP($M39,FÉ!$B$41:$K$59,7,FALSE))*W39 -> 0
B40: =B39 -> 1.2A1 | F40: =IF(E40=0,"",MONTH(E40)) | G40: Bureau | M40: Voiture légère - Essence [L] | W40: 1000 | X40: =IFERROR(VLOOKUP(M40,FÉ!$B$41:$L$59,5,FALSE),"") -> L | BY40: =IF($M40=0, ,VLOOKUP($M40,FÉ!$B$41:$L$59,8,FALSE)*$W40*PRP!$J$8) -> 2307300 | BZ40: =IF($M40=0, ,VLOOKUP($M40,FÉ!$B$41:$L$59,9,FALSE)*$W40*PRP!$J$9) -> 3307.8 | CA40: =IF($M40=0, ,VLOOKUP($M40,FÉ!$B$41:$L$59,10,FALSE)*$W40*PRP!$J$10) -> 1911 | CB40: =SUM(BY40:CA40) -> 2312518.8 | CC40: =CB40/(10^6) -> 2.3125188 | CH40: =IF($M40=0, ,VLOOKUP($M40,FÉ!$B$41:$K$59,7,FALSE))*W40 -> 9690
B41: =B40 -> 1.2A1 | F41: =IF(E41=0,"",MONTH(E41)) | G41: Usine #2 | M41: Véhicule - Propane [lbs] | W41: 100 | X41: =IFERROR(VLOOKUP(M41,FÉ!$B$41:$L$59,5,FALSE),"") -> lbs | BY41: =IF($M41=0, ,VLOOKUP($M41,FÉ!$B$41:$L$59,8,FALSE)*$W41*PRP!$J$8) -> 137438.65 | BZ41: =IF($M41=0, ,VLOOKUP($M41,FÉ!$B$41:$L$59,9,FALSE)*$W41*PRP!$J$9) -> 1730.1848 | CA41: =IF($M41=0, ,VLOOKUP($M41,FÉ!$B$41:$L$59,10,FALSE)*$W41*PRP!$J$10) -> 693.45284 | CB41: =SUM(BY41:CA41) -> 139862.29 | CC41: =CB41/(10^6) -> 0.13986229 | CH41: =IF($M41=0, ,VLOOKUP($M41,FÉ!$B$41:$K$59,7,FALSE))*W41 -> 637.75163
B42: =B41 -> 1.2A1 | F42: =IF(E42=0,"",MONTH(E42)) | X42: =IFERROR(VLOOKUP(M42,FÉ!$B$41:$L$59,5,FALSE),"") | BY42: =IF($M42=0, ,VLOOKUP($M42,FÉ!$B$41:$L$59,8,FALSE)*$W42*PRP!$J$8) -> 0 | BZ42: =IF($M42=0, ,VLOOKUP($M42,FÉ!$B$41:$L$59,9,FALSE)*$W42*PRP!$J$9) -> 0 | CA42: =IF($M42=0, ,VLOOKUP($M42,FÉ!$B$41:$L$59,10,FALSE)*$W42*PRP!$J$10) -> 0 | CB42: =SUM(BY42:CA42) -> 0 | CC42: =CB42/(10^6) -> 0 | CH42: =IF($M42=0, ,VLOOKUP($M42,FÉ!$B$41:$K$59,7,FALSE))*W42 -> 0
B43: =B42 -> 1.2A1 | F43: =IF(E43=0,"",MONTH(E43)) | X43: =IFERROR(VLOOKUP(M43,FÉ!$B$41:$L$59,5,FALSE),"") | BY43: =IF($M43=0, ,VLOOKUP($M43,FÉ!$B$41:$L$59,8,FALSE)*$W43*PRP!$J$8) -> 0 | BZ43: =IF($M43=0, ,VLOOKUP($M43,FÉ!$B$41:$L$59,9,FALSE)*$W43*PRP!$J$9) -> 0 | CA43: =IF($M43=0, ,VLOOKUP($M43,FÉ!$B$41:$L$59,10,FALSE)*$W43*PRP!$J$10) -> 0 | CB43: =SUM(BY43:CA43) -> 0 | CC43: =CB43/(10^6) -> 0 | CH43: =IF($M43=0, ,VLOOKUP($M43,FÉ!$B$41:$K$59,7,FALSE))*W43 -> 0
B44: =B43 -> 1.2A1 | F44: =IF(E44=0,"",MONTH(E44)) | X44: =IFERROR(VLOOKUP(M44,FÉ!$B$41:$L$59,5,FALSE),"") | BY44: =IF($M44=0, ,VLOOKUP($M44,FÉ!$B$41:$L$59,8,FALSE)*$W44*PRP!$J$8) -> 0 | BZ44: =IF($M44=0, ,VLOOKUP($M44,FÉ!$B$41:$L$59,9,FALSE)*$W44*PRP!$J$9) -> 0 | CA44: =IF($M44=0, ,VLOOKUP($M44,FÉ!$B$41:$L$59,10,FALSE)*$W44*PRP!$J$10) -> 0 | CB44: =SUM(BY44:CA44) -> 0 | CC44: =CB44/(10^6) -> 0 | CH44: =IF($M44=0, ,VLOOKUP($M44,FÉ!$B$41:$K$59,7,FALSE))*W44 -> 0
B45: =B44 -> 1.2A1 | F45: =IF(E45=0,"",MONTH(E45)) | X45: =IFERROR(VLOOKUP(M45,FÉ!$B$41:$L$59,5,FALSE),"") | BY45: =IF($M45=0, ,VLOOKUP($M45,FÉ!$B$41:$L$59,8,FALSE)*$W45*PRP!$J$8) -> 0 | BZ45: =IF($M45=0, ,VLOOKUP($M45,FÉ!$B$41:$L$59,9,FALSE)*$W45*PRP!$J$9) -> 0 | CA45: =IF($M45=0, ,VLOOKUP($M45,FÉ!$B$41:$L$59,10,FALSE)*$W45*PRP!$J$10) -> 0 | CB45: =SUM(BY45:CA45) -> 0 | CC45: =CB45/(10^6) -> 0 | CH45: =IF($M45=0, ,VLOOKUP($M45,FÉ!$B$41:$K$59,7,FALSE))*W45 -> 0
B46: =B45 -> 1.2A1 | F46: =IF(E46=0,"",MONTH(E46)) | X46: =IFERROR(VLOOKUP(M46,FÉ!$B$41:$L$59,5,FALSE),"") | BY46: =IF($M46=0, ,VLOOKUP($M46,FÉ!$B$41:$L$59,8,FALSE)*$W46*PRP!$J$8) -> 0 | BZ46: =IF($M46=0, ,VLOOKUP($M46,FÉ!$B$41:$L$59,9,FALSE)*$W46*PRP!$J$9) -> 0 | CA46: =IF($M46=0, ,VLOOKUP($M46,FÉ!$B$41:$L$59,10,FALSE)*$W46*PRP!$J$10) -> 0 | CB46: =SUM(BY46:CA46) -> 0 | CC46: =CB46/(10^6) -> 0 | CH46: =IF($M46=0, ,VLOOKUP($M46,FÉ!$B$41:$K$59,7,FALSE))*W46 -> 0
B47: =B46 -> 1.2A1 | F47: =IF(E47=0,"",MONTH(E47)) | X47: =IFERROR(VLOOKUP(M47,FÉ!$B$41:$L$59,5,FALSE),"") | BY47: =IF($M47=0, ,VLOOKUP($M47,FÉ!$B$41:$L$59,8,FALSE)*$W47*PRP!$J$8) -> 0 | BZ47: =IF($M47=0, ,VLOOKUP($M47,FÉ!$B$41:$L$59,9,FALSE)*$W47*PRP!$J$9) -> 0 | CA47: =IF($M47=0, ,VLOOKUP($M47,FÉ!$B$41:$L$59,10,FALSE)*$W47*PRP!$J$10) -> 0 | CB47: =SUM(BY47:CA47) -> 0 | CC47: =CB47/(10^6) -> 0 | CH47: =IF($M47=0, ,VLOOKUP($M47,FÉ!$B$41:$K$59,7,FALSE))*W47 -> 0
B48: =B47 -> 1.2A1 | F48: =IF(E48=0,"",MONTH(E48)) | X48: =IFERROR(VLOOKUP(M48,FÉ!$B$41:$L$59,5,FALSE),"") | BY48: =IF($M48=0, ,VLOOKUP($M48,FÉ!$B$41:$L$59,8,FALSE)*$W48*PRP!$J$8) -> 0 | BZ48: =IF($M48=0, ,VLOOKUP($M48,FÉ!$B$41:$L$59,9,FALSE)*$W48*PRP!$J$9) -> 0 | CA48: =IF($M48=0, ,VLOOKUP($M48,FÉ!$B$41:$L$59,10,FALSE)*$W48*PRP!$J$10) -> 0 | CB48: =SUM(BY48:CA48) -> 0 | CC48: =CB48/(10^6) -> 0 | CH48: =IF($M48=0, ,VLOOKUP($M48,FÉ!$B$41:$K$59,7,FALSE))*W48 -> 0
B49: =B48 -> 1.2A1 | F49: =IF(E49=0,"",MONTH(E49)) | X49: =IFERROR(VLOOKUP(M49,FÉ!$B$41:$L$59,5,FALSE),"") | BY49: =IF($M49=0, ,VLOOKUP($M49,FÉ!$B$41:$L$59,8,FALSE)*$W49*PRP!$J$8) -> 0 | BZ49: =IF($M49=0, ,VLOOKUP($M49,FÉ!$B$41:$L$59,9,FALSE)*$W49*PRP!$J$9) -> 0 | CA49: =IF($M49=0, ,VLOOKUP($M49,FÉ!$B$41:$L$59,10,FALSE)*$W49*PRP!$J$10) -> 0 | CB49: =SUM(BY49:CA49) -> 0 | CC49: =CB49/(10^6) -> 0 | CH49: =IF($M49=0, ,VLOOKUP($M49,FÉ!$B$41:$K$59,7,FALSE))*W49 -> 0
B50: =B49 -> 1.2A1 | F50: =IF(E50=0,"",MONTH(E50)) | X50: =IFERROR(VLOOKUP(M50,FÉ!$B$41:$L$59,5,FALSE),"") | BY50: =IF($M50=0, ,VLOOKUP($M50,FÉ!$B$41:$L$59,8,FALSE)*$W50*PRP!$J$8) -> 0 | BZ50: =IF($M50=0, ,VLOOKUP($M50,FÉ!$B$41:$L$59,9,FALSE)*$W50*PRP!$J$9) -> 0 | CA50: =IF($M50=0, ,VLOOKUP($M50,FÉ!$B$41:$L$59,10,FALSE)*$W50*PRP!$J$10) -> 0 | CB50: =SUM(BY50:CA50) -> 0 | CC50: =CB50/(10^6) -> 0 | CH50: =IF($M50=0, ,VLOOKUP($M50,FÉ!$B$41:$K$59,7,FALSE))*W50 -> 0
B51: =B43 -> 1.2A1 | F51: =IF(E51=0,"",MONTH(E51)) | X51: =IFERROR(VLOOKUP(M51,FÉ!$B$41:$L$59,5,FALSE),"") | BY51: =IF($M51=0, ,VLOOKUP($M51,FÉ!$B$41:$L$59,8,FALSE)*$W51*PRP!$J$8) -> 0 | BZ51: =IF($M51=0, ,VLOOKUP($M51,FÉ!$B$41:$L$59,9,FALSE)*$W51*PRP!$J$9) -> 0 | CA51: =IF($M51=0, ,VLOOKUP($M51,FÉ!$B$41:$L$59,10,FALSE)*$W51*PRP!$J$10) -> 0 | CB51: =SUM(BY51:CA51) -> 0 | CC51: =CB51/(10^6) -> 0 | CH51: =IF($M51=0, ,VLOOKUP($M51,FÉ!$B$41:$K$59,7,FALSE))*W51 -> 0
B52: =B51 -> 1.2A1 | F52: =IF(E52=0,"",MONTH(E52)) | X52: =IFERROR(VLOOKUP(M52,FÉ!$B$41:$L$59,5,FALSE),"") | BY52: =IF($M52=0, ,VLOOKUP($M52,FÉ!$B$41:$L$59,8,FALSE)*$W52*PRP!$J$8) -> 0 | BZ52: =IF($M52=0, ,VLOOKUP($M52,FÉ!$B$41:$L$59,9,FALSE)*$W52*PRP!$J$9) -> 0 | CA52: =IF($M52=0, ,VLOOKUP($M52,FÉ!$B$41:$L$59,10,FALSE)*$W52*PRP!$J$10) -> 0 | CB52: =SUM(BY52:CA52) -> 0 | CC52: =CB52/(10^6) -> 0 | CH52: =IF($M52=0, ,VLOOKUP($M52,FÉ!$B$41:$K$59,7,FALSE))*W52 -> 0
B53: =B52 -> 1.2A1 | F53: =IF(E53=0,"",MONTH(E53)) | X53: =IFERROR(VLOOKUP(M53,FÉ!$B$41:$L$59,5,FALSE),"") | BY53: =IF($M53=0, ,VLOOKUP($M53,FÉ!$B$41:$L$59,8,FALSE)*$W53*PRP!$J$8) -> 0 | BZ53: =IF($M53=0, ,VLOOKUP($M53,FÉ!$B$41:$L$59,9,FALSE)*$W53*PRP!$J$9) -> 0 | CA53: =IF($M53=0, ,VLOOKUP($M53,FÉ!$B$41:$L$59,10,FALSE)*$W53*PRP!$J$10) -> 0 | CB53: =SUM(BY53:CA53) -> 0 | CC53: =CB53/(10^6) -> 0 | CH53: =IF($M53=0, ,VLOOKUP($M53,FÉ!$B$41:$K$59,7,FALSE))*W53 -> 0
B54: =B53 -> 1.2A1 | F54: =IF(E54=0,"",MONTH(E54)) | X54: =IFERROR(VLOOKUP(M54,FÉ!$B$41:$L$59,5,FALSE),"") | BY54: =IF($M54=0, ,VLOOKUP($M54,FÉ!$B$41:$L$59,8,FALSE)*$W54*PRP!$J$8) -> 0 | BZ54: =IF($M54=0, ,VLOOKUP($M54,FÉ!$B$41:$L$59,9,FALSE)*$W54*PRP!$J$9) -> 0 | CA54: =IF($M54=0, ,VLOOKUP($M54,FÉ!$B$41:$L$59,10,FALSE)*$W54*PRP!$J$10) -> 0 | CB54: =SUM(BY54:CA54) -> 0 | CC54: =CB54/(10^6) -> 0 | CH54: =IF($M54=0, ,VLOOKUP($M54,FÉ!$B$41:$K$59,7,FALSE))*W54 -> 0
B55: =B54 -> 1.2A1 | F55: =IF(E55=0,"",MONTH(E55)) | X55: =IFERROR(VLOOKUP(M55,FÉ!$B$41:$L$59,5,FALSE),"") | BY55: =IF($M55=0, ,VLOOKUP($M55,FÉ!$B$41:$L$59,8,FALSE)*$W55*PRP!$J$8) -> 0 | BZ55: =IF($M55=0, ,VLOOKUP($M55,FÉ!$B$41:$L$59,9,FALSE)*$W55*PRP!$J$9) -> 0 | CA55: =IF($M55=0, ,VLOOKUP($M55,FÉ!$B$41:$L$59,10,FALSE)*$W55*PRP!$J$10) -> 0 | CB55: =SUM(BY55:CA55) -> 0 | CC55: =CB55/(10^6) -> 0 | CH55: =IF($M55=0, ,VLOOKUP($M55,FÉ!$B$41:$K$59,7,FALSE))*W55 -> 0
F56: =$B39 -> 1.2A1 | G56: =$B39 -> 1.2A1 | H56: =$B39 -> 1.2A1 | W56: =SUM(W39:W55) -> 1100 | BY56: =SUM(BY39:BY55) -> 2444738.7 | BZ56: =SUM(BZ39:BZ55) -> 5037.9848 | CA56: =SUM(CA39:CA55) -> 2604.4528 | CB56: =SUM(CB39:CB55) -> 2452381.1 | CC56: =SUM(CC39:CC55) -> 2.4523811 | CE56: =SUM(CE39:CE55) -> 0 | CF56: =SUM(CF39:CF55) -> 0 | CH56: =SUM(CH39:CH55) -> 10327.752
B58: 1.2A2 - Véhicules (Par la distance parcourue; Consommation L/100km)
B60: Données d'activité | BQ60: Calculs et résultats
B61: # méthode | C61: Liste des véhicules ou des groupes de véhicules | D61: Description | E61: Date | F61: mois | G61: Site | H61: Produit | I61: Références | M61: Type de véhicule et type de carburant | T61: Distance parcourus | V61: Consommation moyenne | W61: Estimation de la quantité de carburant | BY61: Émissions GES | CB61: Total GES : | CE61: Total CO2 Biogénique : | CH61: Énergie équivalente
BY62: CO2 | BZ62: CH4 | CA62: N2O
D63: (Facultatif) | E63: (Facultatif) | G63: (Facultatif) | H63: (Facultatif) | I63: (Facultatif) | M63: (Sélectionner) | T63: [km] | V63: [L/100km] | W63: Qte | BY63: [gCO2e] | BZ63: [gCO2e] | CA63: [gCO2e] | CB63: [gCO2e] | CC63: [tCO2e] | CE63: [gCO2e] | CF63: [tCO2e] | CH63: [kWh]
B64: 1.2A2 | F64: =IF(E64=0,"",MONTH(E64)) | W64: =T64*V64/100 -> 0 | X64: =IFERROR(VLOOKUP(M64,FÉ!$B$41:$L$59,5,FALSE),"") | BY64: =IF($M64=0, ,VLOOKUP($M64,FÉ!$B$41:$L$59,8,FALSE)*$W64*PRP!$J$8) -> 0 | BZ64: =IF($M64=0, ,VLOOKUP($M64,FÉ!$B$41:$L$59,9,FALSE)*$W64*PRP!$J$9) -> 0 | CA64: =IF($M64=0, ,VLOOKUP($M64,FÉ!$B$41:$L$59,10,FALSE)*$W64*PRP!$J$10) -> 0 | CB64: =SUM(BY64:CA64) -> 0 | CC64: =CB64/(10^6) -> 0 | CH64: =IF($M64=0, ,VLOOKUP($M64,FÉ!$B$41:$K$59,7,FALSE))*W64 -> 0
B65: =B64 -> 1.2A2 | F65: =IF(E65=0,"",MONTH(E65)) | M65: Voiture légère - Essence [L] | T65: 15000 | V65: 6 | W65: =T65*V65/100 -> 900 | X65: =IFERROR(VLOOKUP(M65,FÉ!$B$41:$L$59,5,FALSE),"") -> L | BY65: =IF($M65=0, ,VLOOKUP($M65,FÉ!$B$41:$L$59,8,FALSE)*$W65*PRP!$J$8) -> 2076570 | BZ65: =IF($M65=0, ,VLOOKUP($M65,FÉ!$B$41:$L$59,9,FALSE)*$W65*PRP!$J$9) -> 2977.02 | CA65: =IF($M65=0, ,VLOOKUP($M65,FÉ!$B$41:$L$59,10,FALSE)*$W65*PRP!$J$10) -> 1719.9 | CB65: =SUM(BY65:CA65) -> 2081266.9 | CC65: =CB65/(10^6) -> 2.0812669 | CH65: =IF($M65=0, ,VLOOKUP($M65,FÉ!$B$41:$K$59,7,FALSE))*W65 -> 8721
B66: =B65 -> 1.2A2 | E66: 45718 | F66: =IF(E66=0,"",MONTH(E66)) -> 3 | G66: Shop | M66: Véhicule - Propane [lbs] | T66: 25000 | V66: 10 | W66: =T66*V66/100 -> 2500 | X66: =IFERROR(VLOOKUP(M66,FÉ!$B$41:$L$59,5,FALSE),"") -> lbs | BY66: =IF($M66=0, ,VLOOKUP($M66,FÉ!$B$41:$L$59,8,FALSE)*$W66*PRP!$J$8) -> 3435966.3 | BZ66: =IF($M66=0, ,VLOOKUP($M66,FÉ!$B$41:$L$59,9,FALSE)*$W66*PRP!$J$9) -> 43254.62 | CA66: =IF($M66=0, ,VLOOKUP($M66,FÉ!$B$41:$L$59,10,FALSE)*$W66*PRP!$J$10) -> 17336.321 | CB66: =SUM(BY66:CA66) -> 3496557.2 | CC66: =CB66/(10^6) -> 3.4965572 | CH66: =IF($M66=0, ,VLOOKUP($M66,FÉ!$B$41:$K$59,7,FALSE))*W66 -> 15943.791
B67: =B66 -> 1.2A2 | F67: =IF(E67=0,"",MONTH(E67)) | W67: =T67*V67/100 -> 0 | X67: =IFERROR(VLOOKUP(M67,FÉ!$B$41:$L$59,5,FALSE),"") | BY67: =IF($M67=0, ,VLOOKUP($M67,FÉ!$B$41:$L$59,8,FALSE)*$W67*PRP!$J$8) -> 0 | BZ67: =IF($M67=0, ,VLOOKUP($M67,FÉ!$B$41:$L$59,9,FALSE)*$W67*PRP!$J$9) -> 0 | CA67: =IF($M67=0, ,VLOOKUP($M67,FÉ!$B$41:$L$59,10,FALSE)*$W67*PRP!$J$10) -> 0 | CB67: =SUM(BY67:CA67) -> 0 | CC67: =CB67/(10^6) -> 0 | CH67: =IF($M67=0, ,VLOOKUP($M67,FÉ!$B$41:$K$59,7,FALSE))*W67 -> 0
B68: =B67 -> 1.2A2 | F68: =IF(E68=0,"",MONTH(E68)) | W68: =T68*V68/100 -> 0 | X68: =IFERROR(VLOOKUP(M68,FÉ!$B$41:$L$59,5,FALSE),"") | BY68: =IF($M68=0, ,VLOOKUP($M68,FÉ!$B$41:$L$59,8,FALSE)*$W68*PRP!$J$8) -> 0 | BZ68: =IF($M68=0, ,VLOOKUP($M68,FÉ!$B$41:$L$59,9,FALSE)*$W68*PRP!$J$9) -> 0 | CA68: =IF($M68=0, ,VLOOKUP($M68,FÉ!$B$41:$L$59,10,FALSE)*$W68*PRP!$J$10) -> 0 | CB68: =SUM(BY68:CA68) -> 0 | CC68: =CB68/(10^6) -> 0 | CH68: =IF($M68=0, ,VLOOKUP($M68,FÉ!$B$41:$K$59,7,FALSE))*W68 -> 0
B69: =B68 -> 1.2A2 | F69: =IF(E69=0,"",MONTH(E69)) | W69: =T69*V69/100 -> 0 | X69: =IFERROR(VLOOKUP(M69,FÉ!$B$41:$L$59,5,FALSE),"") | BY69: =IF($M69=0, ,VLOOKUP($M69,FÉ!$B$41:$L$59,8,FALSE)*$W69*PRP!$J$8) -> 0 | BZ69: =IF($M69=0, ,VLOOKUP($M69,FÉ!$B$41:$L$59,9,FALSE)*$W69*PRP!$J$9) -> 0 | CA69: =IF($M69=0, ,VLOOKUP($M69,FÉ!$B$41:$L$59,10,FALSE)*$W69*PRP!$J$10) -> 0 | CB69: =SUM(BY69:CA69) -> 0 | CC69: =CB69/(10^6) -> 0 | CH69: =IF($M69=0, ,VLOOKUP($M69,FÉ!$B$41:$K$59,7,FALSE))*W69 -> 0
B70: =B69 -> 1.2A2 | F70: =IF(E70=0,"",MONTH(E70)) | W70: =T70*V70/100 -> 0 | X70: =IFERROR(VLOOKUP(M70,FÉ!$B$41:$L$59,5,FALSE),"") | BY70: =IF($M70=0, ,VLOOKUP($M70,FÉ!$B$41:$L$59,8,FALSE)*$W70*PRP!$J$8) -> 0 | BZ70: =IF($M70=0, ,VLOOKUP($M70,FÉ!$B$41:$L$59,9,FALSE)*$W70*PRP!$J$9) -> 0 | CA70: =IF($M70=0, ,VLOOKUP($M70,FÉ!$B$41:$L$59,10,FALSE)*$W70*PRP!$J$10) -> 0 | CB70: =SUM(BY70:CA70) -> 0 | CC70: =CB70/(10^6) -> 0 | CH70: =IF($M70=0, ,VLOOKUP($M70,FÉ!$B$41:$K$59,7,FALSE))*W70 -> 0
B71: =B70 -> 1.2A2 | F71: =IF(E71=0,"",MONTH(E71)) | W71: =T71*V71/100 -> 0 | X71: =IFERROR(VLOOKUP(M71,FÉ!$B$41:$L$59,5,FALSE),"") | BY71: =IF($M71=0, ,VLOOKUP($M71,FÉ!$B$41:$L$59,8,FALSE)*$W71*PRP!$J$8) -> 0 | BZ71: =IF($M71=0, ,VLOOKUP($M71,FÉ!$B$41:$L$59,9,FALSE)*$W71*PRP!$J$9) -> 0 | CA71: =IF($M71=0, ,VLOOKUP($M71,FÉ!$B$41:$L$59,10,FALSE)*$W71*PRP!$J$10) -> 0 | CB71: =SUM(BY71:CA71) -> 0 | CC71: =CB71/(10^6) -> 0 | CH71: =IF($M71=0, ,VLOOKUP($M71,FÉ!$B$41:$K$59,7,FALSE))*W71 -> 0
B72: =B71 -> 1.2A2 | F72: =IF(E72=0,"",MONTH(E72)) | W72: =T72*V72/100 -> 0 | X72: =IFERROR(VLOOKUP(M72,FÉ!$B$41:$L$59,5,FALSE),"") | BY72: =IF($M72=0, ,VLOOKUP($M72,FÉ!$B$41:$L$59,8,FALSE)*$W72*PRP!$J$8) -> 0 | BZ72: =IF($M72=0, ,VLOOKUP($M72,FÉ!$B$41:$L$59,9,FALSE)*$W72*PRP!$J$9) -> 0 | CA72: =IF($M72=0, ,VLOOKUP($M72,FÉ!$B$41:$L$59,10,FALSE)*$W72*PRP!$J$10) -> 0 | CB72: =SUM(BY72:CA72) -> 0 | CC72: =CB72/(10^6) -> 0 | CH72: =IF($M72=0, ,VLOOKUP($M72,FÉ!$B$41:$K$59,7,FALSE))*W72 -> 0
B73: =B72 -> 1.2A2 | F73: =IF(E73=0,"",MONTH(E73)) | W73: =T73*V73/100 -> 0 | X73: =IFERROR(VLOOKUP(M73,FÉ!$B$41:$L$59,5,FALSE),"") | BY73: =IF($M73=0, ,VLOOKUP($M73,FÉ!$B$41:$L$59,8,FALSE)*$W73*PRP!$J$8) -> 0 | BZ73: =IF($M73=0, ,VLOOKUP($M73,FÉ!$B$41:$L$59,9,FALSE)*$W73*PRP!$J$9) -> 0 | CA73: =IF($M73=0, ,VLOOKUP($M73,FÉ!$B$41:$L$59,10,FALSE)*$W73*PRP!$J$10) -> 0 | CB73: =SUM(BY73:CA73) -> 0 | CC73: =CB73/(10^6) -> 0 | CH73: =IF($M73=0, ,VLOOKUP($M73,FÉ!$B$41:$K$59,7,FALSE))*W73 -> 0
F74: =$B64 -> 1.2A2 | G74: =$B64 -> 1.2A2 | H74: =$B64 -> 1.2A2 | T74: =SUM(T64:T73) -> 40000 | W74: =SUM(W64:W73) -> 3400 | BY74: =SUM(BY64:BY73) -> 5512536.3 | BZ74: =SUM(BZ64:BZ73) -> 46231.64 | CA74: =SUM(CA64:CA73) -> 19056.221 | CB74: =SUM(CB64:CB73) -> 5577824.1 | CC74: =SUM(CC64:CC73) -> 5.5778241 | CE74: =SUM(CE64:CE73) -> 0 | CF74: =SUM(CF64:CF73) -> 0 | CH74: =SUM(CH64:CH73) -> 24664.791
B76: 1.2A3 - Véhicules (Par les coûts de carburants)
B78: Données d'activité | BQ78: Calculs et résultats
B79: # méthode | C79: Liste des véhicules ou des groupes de véhicules | D79: Description | E79: Date | F79: mois | G79: Site | H79: Produit | I79: Références | M79: Type de véhicule et type de carburant | N79: Coûts en carburants | O79: Prix moyenne du carburant | W79: Estimation de la quantité de carburant | BY79: Émissions GES | CB79: Total GES : | CE79: Total CO2 Biogénique : | CH79: Énergie équivalente
BY80: CO2 | BZ80: CH4 | CA80: N2O
D81: (Facultatif) | E81: (Facultatif) | G81: (Facultatif) | H81: (Facultatif) | I81: (Facultatif) | M81: (Sélectionner) | N81: [$] | O81: [$/L] | W81: Qte | BY81: [gCO2e] | BZ81: [gCO2e] | CA81: [gCO2e] | CB81: [gCO2e] | CC81: [tCO2e] | CE81: [gCO2e] | CF81: [tCO2e] | CH81: [kWh]
B82: 1.2A3 | F82: =IF(E82=0,"",MONTH(E82)) | W82: =N82*O82/100 -> 0 | X82: =IFERROR(VLOOKUP(M82,FÉ!$B$41:$L$59,5,FALSE),"") | BY82: =IF($M82=0, ,VLOOKUP($M82,FÉ!$B$41:$L$59,8,FALSE)*$W82*PRP!$J$8) -> 0 | BZ82: =IF($M82=0, ,VLOOKUP($M82,FÉ!$B$41:$L$59,9,FALSE)*$W82*PRP!$J$9) -> 0 | CA82: =IF($M82=0, ,VLOOKUP($M82,FÉ!$B$41:$L$59,10,FALSE)*$W82*PRP!$J$10) -> 0 | CB82: =SUM(BY82:CA82) -> 0 | CC82: =CB82/(10^6) -> 0 | CH82: =IF($M82=0, ,VLOOKUP($M82,FÉ!$B$41:$K$59,7,FALSE))*W82 -> 0
B83: =B82 -> 1.2A3 | E83: 45752 | F83: =IF(E83=0,"",MONTH(E83)) -> 4 | G83: Shop | M83: Voiture légère - Essence [L] | N83: 15000 | O83: 1.46 | W83: =N83*O83/100 -> 219 | X83: =IFERROR(VLOOKUP(M83,FÉ!$B$41:$L$59,5,FALSE),"") -> L | BY83: =IF($M83=0, ,VLOOKUP($M83,FÉ!$B$41:$L$59,8,FALSE)*$W83*PRP!$J$8) -> 505298.7 | BZ83: =IF($M83=0, ,VLOOKUP($M83,FÉ!$B$41:$L$59,9,FALSE)*$W83*PRP!$J$9) -> 724.4082 | CA83: =IF($M83=0, ,VLOOKUP($M83,FÉ!$B$41:$L$59,10,FALSE)*$W83*PRP!$J$10) -> 418.509 | CB83: =SUM(BY83:CA83) -> 506441.62 | CC83: =CB83/(10^6) -> 0.50644162 | CH83: =IF($M83=0, ,VLOOKUP($M83,FÉ!$B$41:$K$59,7,FALSE))*W83 -> 2122.11
B84: =B83 -> 1.2A3 | F84: =IF(E84=0,"",MONTH(E84)) | G84: Usine #2 | M84: Véhicule - Propane [lbs] | N84: 25000 | O84: 1.52 | W84: =N84*O84/100 -> 380 | X84: =IFERROR(VLOOKUP(M84,FÉ!$B$41:$L$59,5,FALSE),"") -> lbs | BY84: =IF($M84=0, ,VLOOKUP($M84,FÉ!$B$41:$L$59,8,FALSE)*$W84*PRP!$J$8) -> 522266.88 | BZ84: =IF($M84=0, ,VLOOKUP($M84,FÉ!$B$41:$L$59,9,FALSE)*$W84*PRP!$J$9) -> 6574.7022 | CA84: =IF($M84=0, ,VLOOKUP($M84,FÉ!$B$41:$L$59,10,FALSE)*$W84*PRP!$J$10) -> 2635.1208 | CB84: =SUM(BY84:CA84) -> 531476.7 | CC84: =CB84/(10^6) -> 0.5314767 | CH84: =IF($M84=0, ,VLOOKUP($M84,FÉ!$B$41:$K$59,7,FALSE))*W84 -> 2423.4562
B85: =B84 -> 1.2A3 | F85: =IF(E85=0,"",MONTH(E85)) | W85: =N85*O85/100 -> 0 | X85: =IFERROR(VLOOKUP(M85,FÉ!$B$41:$L$59,5,FALSE),"") | BY85: =IF($M85=0, ,VLOOKUP($M85,FÉ!$B$41:$L$59,8,FALSE)*$W85*PRP!$J$8) -> 0 | BZ85: =IF($M85=0, ,VLOOKUP($M85,FÉ!$B$41:$L$59,9,FALSE)*$W85*PRP!$J$9) -> 0 | CA85: =IF($M85=0, ,VLOOKUP($M85,FÉ!$B$41:$L$59,10,FALSE)*$W85*PRP!$J$10) -> 0 | CB85: =SUM(BY85:CA85) -> 0 | CC85: =CB85/(10^6) -> 0 | CH85: =IF($M85=0, ,VLOOKUP($M85,FÉ!$B$41:$K$59,7,FALSE))*W85 -> 0
B86: =B85 -> 1.2A3 | F86: =IF(E86=0,"",MONTH(E86)) | W86: =N86*O86/100 -> 0 | X86: =IFERROR(VLOOKUP(M86,FÉ!$B$41:$L$59,5,FALSE),"") | BY86: =IF($M86=0, ,VLOOKUP($M86,FÉ!$B$41:$L$59,8,FALSE)*$W86*PRP!$J$8) -> 0 | BZ86: =IF($M86=0, ,VLOOKUP($M86,FÉ!$B$41:$L$59,9,FALSE)*$W86*PRP!$J$9) -> 0 | CA86: =IF($M86=0, ,VLOOKUP($M86,FÉ!$B$41:$L$59,10,FALSE)*$W86*PRP!$J$10) -> 0 | CB86: =SUM(BY86:CA86) -> 0 | CC86: =CB86/(10^6) -> 0 | CH86: =IF($M86=0, ,VLOOKUP($M86,FÉ!$B$41:$K$59,7,FALSE))*W86 -> 0
B87: =B86 -> 1.2A3 | F87: =IF(E87=0,"",MONTH(E87)) | W87: =N87*O87/100 -> 0 | X87: =IFERROR(VLOOKUP(M87,FÉ!$B$41:$L$59,5,FALSE),"") | BY87: =IF($M87=0, ,VLOOKUP($M87,FÉ!$B$41:$L$59,8,FALSE)*$W87*PRP!$J$8) -> 0 | BZ87: =IF($M87=0, ,VLOOKUP($M87,FÉ!$B$41:$L$59,9,FALSE)*$W87*PRP!$J$9) -> 0 | CA87: =IF($M87=0, ,VLOOKUP($M87,FÉ!$B$41:$L$59,10,FALSE)*$W87*PRP!$J$10) -> 0 | CB87: =SUM(BY87:CA87) -> 0 | CC87: =CB87/(10^6) -> 0 | CH87: =IF($M87=0, ,VLOOKUP($M87,FÉ!$B$41:$K$59,7,FALSE))*W87 -> 0
B88: =B87 -> 1.2A3 | F88: =IF(E88=0,"",MONTH(E88)) | W88: =N88*O88/100 -> 0 | X88: =IFERROR(VLOOKUP(M88,FÉ!$B$41:$L$59,5,FALSE),"") | BY88: =IF($M88=0, ,VLOOKUP($M88,FÉ!$B$41:$L$59,8,FALSE)*$W88*PRP!$J$8) -> 0 | BZ88: =IF($M88=0, ,VLOOKUP($M88,FÉ!$B$41:$L$59,9,FALSE)*$W88*PRP!$J$9) -> 0 | CA88: =IF($M88=0, ,VLOOKUP($M88,FÉ!$B$41:$L$59,10,FALSE)*$W88*PRP!$J$10) -> 0 | CB88: =SUM(BY88:CA88) -> 0 | CC88: =CB88/(10^6) -> 0 | CH88: =IF($M88=0, ,VLOOKUP($M88,FÉ!$B$41:$K$59,7,FALSE))*W88 -> 0
B89: =B88 -> 1.2A3 | F89: =IF(E89=0,"",MONTH(E89)) | W89: =N89*O89/100 -> 0 | X89: =IFERROR(VLOOKUP(M89,FÉ!$B$41:$L$59,5,FALSE),"") | BY89: =IF($M89=0, ,VLOOKUP($M89,FÉ!$B$41:$L$59,8,FALSE)*$W89*PRP!$J$8) -> 0 | BZ89: =IF($M89=0, ,VLOOKUP($M89,FÉ!$B$41:$L$59,9,FALSE)*$W89*PRP!$J$9) -> 0 | CA89: =IF($M89=0, ,VLOOKUP($M89,FÉ!$B$41:$L$59,10,FALSE)*$W89*PRP!$J$10) -> 0 | CB89: =SUM(BY89:CA89) -> 0 | CC89: =CB89/(10^6) -> 0 | CH89: =IF($M89=0, ,VLOOKUP($M89,FÉ!$B$41:$K$59,7,FALSE))*W89 -> 0
B90: =B89 -> 1.2A3 | F90: =IF(E90=0,"",MONTH(E90)) | W90: =N90*O90/100 -> 0 | X90: =IFERROR(VLOOKUP(M90,FÉ!$B$41:$L$59,5,FALSE),"") | BY90: =IF($M90=0, ,VLOOKUP($M90,FÉ!$B$41:$L$59,8,FALSE)*$W90*PRP!$J$8) -> 0 | BZ90: =IF($M90=0, ,VLOOKUP($M90,FÉ!$B$41:$L$59,9,FALSE)*$W90*PRP!$J$9) -> 0 | CA90: =IF($M90=0, ,VLOOKUP($M90,FÉ!$B$41:$L$59,10,FALSE)*$W90*PRP!$J$10) -> 0 | CB90: =SUM(BY90:CA90) -> 0 | CC90: =CB90/(10^6) -> 0 | CH90: =IF($M90=0, ,VLOOKUP($M90,FÉ!$B$41:$K$59,7,FALSE))*W90 -> 0
B91: =B90 -> 1.2A3 | F91: =IF(E91=0,"",MONTH(E91)) | W91: =N91*O91/100 -> 0 | X91: =IFERROR(VLOOKUP(M91,FÉ!$B$41:$L$59,5,FALSE),"") | BY91: =IF($M91=0, ,VLOOKUP($M91,FÉ!$B$41:$L$59,8,FALSE)*$W91*PRP!$J$8) -> 0 | BZ91: =IF($M91=0, ,VLOOKUP($M91,FÉ!$B$41:$L$59,9,FALSE)*$W91*PRP!$J$9) -> 0 | CA91: =IF($M91=0, ,VLOOKUP($M91,FÉ!$B$41:$L$59,10,FALSE)*$W91*PRP!$J$10) -> 0 | CB91: =SUM(BY91:CA91) -> 0 | CC91: =CB91/(10^6) -> 0 | CH91: =IF($M91=0, ,VLOOKUP($M91,FÉ!$B$41:$K$59,7,FALSE))*W91 -> 0
F92: =$B82 -> 1.2A3 | G92: =$B82 -> 1.2A3 | H92: =$B82 -> 1.2A3 | N92: =SUM(N82:N91) -> 40000 | W92: =SUM(W82:W91) -> 599 | BY92: =SUM(BY82:BY91) -> 1027565.6 | BZ92: =SUM(BZ82:BZ91) -> 7299.1104 | CA92: =SUM(CA82:CA91) -> 3053.6298 | CB92: =SUM(CB82:CB91) -> 1037918.3 | CC92: =SUM(CC82:CC91) -> 1.0379183 | CE92: =SUM(CE82:CE91) -> 0 | CF92: =SUM(CF82:CF91) -> 0 | CH92: =SUM(CH82:CH91) -> 4545.5662
B94: 1.2B1 - Véhicules (Par la distance parcourue; Données Canadiennes)
B96: Données d'activité | BQ96: Calculs et résultats
B97: # méthode | C97: Liste des véhicules | D97: Description | E97: Date | F97: mois | G97: Site | H97: Produit | I97: Références | M97: Type de véhicule et type de carburant | P97: Année | Q97: Marque | R97: Modèle | T97: Distance parcourus | U97: Véhicule | V97: Véhicule à essence | Y97: Véhicule électrique | BY97: Émissions GES | CB97: Total GES : | CE97: Total CO2 Biogénique : | CH97: Énergie équivalente
V98: Consommation moyenne | W98: Estimation | Y98: Province | Z98: Consommation moyenne | AA98: Estimation | BY98: CO2 | BZ98: CH4 | CA98: N2O
D99: (Facultatif) | E99: (Facultatif) | G99: (Facultatif) | H99: (Facultatif) | I99: (Facultatif) | P99: (Sélectionner) | Q99: (Sélectionner) | R99: (Sélectionner) | T99: [km] | V99: [L/100km] | W99: Qte | Y99: (Sélectionner) | Z99: [kWh/100km] | AA99: Qte | BY99: [gCO2e] | BZ99: [gCO2e] | CA99: [gCO2e] | CB99: [gCO2e] | CC99: [tCO2e] | CE99: [gCO2e] | CF99: [tCO2e] | CH99: [kWh]
B100: 1.2B1 | F100: =IF(E100=0,"",MONTH(E100)) | M100: =IFERROR(VLOOKUP($U100,[1]!Tableau2[#Data],20,FALSE),) -> 0 | U100: =_xlfn.CONCAT(P100,", ",Q100,", ",R100) -> , , | V100: =IFERROR(VLOOKUP($U100,[1]!Tableau2[#Data],12,FALSE),) -> 0 | W100: =IFERROR($T100*V100/100,) -> 0 | X100: L | Z100: =IFERROR(VLOOKUP($U100,[1]!Tableau2[#Data],15,FALSE),) -> 0 | AA100: =IFERROR($T100*Z100/100,) -> 0 | AB100: kWh | BY100: =IFERROR(VLOOKUP($M100,FÉ!$B$41:$L$58,8,FALSE)*$W100*PRP!$J$8,) + IF($M100=FÉ!$B$57, IFERROR(VLOOKUP($Y100,FÉ!$B$385:$L$437,8,FALSE)*$AA100*PRP!$J$8,),0) -> 0 | BZ100: =IFERROR(VLOOKUP($M100,FÉ!$B$41:$L$58,9,FALSE)*$W100*PRP!$J$9,) + IF($M100=FÉ!$B$57, IFERROR(VLOOKUP($Y100,FÉ!$B$385:$L$437,9,FALSE)*$AA100*PRP!$J$9,),0) -> 0 | CA100: =IFERROR(VLOOKUP($M100,FÉ!$B$41:$L$58,10,FALSE)*$W100*PRP!$J$10,) + IF($M100=FÉ!$B$57, IFERROR(VLOOKUP($Y100,FÉ!$B$385:$L$437,10,FALSE)*$AA100*PRP!$J$10,),0) -> 0 | CB100: =SUM(BY100:CA100) -> 0 | CC100: =CB100/(10^6) -> 0 | CH100: =IFERROR(IF($M100=0, ,VLOOKUP($M100,FÉ!$B$41:$K$59,7,FALSE))*W100,) + AA100 -> 0
B101: =B100 -> 1.2B1 | E101: 45842 | F101: =IF(E101=0,"",MONTH(E101)) -> 7 | G101: Shop | M101: =IFERROR(VLOOKUP($U101,[1]!Tableau2[#Data],20,FALSE),) -> 0 | P101: 2013 | Q101: Honda | R101: Fit | T101: 20000 | U101: =_xlfn.CONCAT(P101,", ",Q101,", ",R101) -> 2013, Honda, Fit | V101: =IFERROR(VLOOKUP($U101,[1]!Tableau2[#Data],12,FALSE),) -> 0 | W101: =IFERROR($T101*V101/100,) -> 0 | X101: L | Z101: =IFERROR(VLOOKUP($U101,[1]!Tableau2[#Data],15,FALSE),) -> 0 | AA101: =IFERROR($T101*Z101/100,) -> 0 | AB101: kWh | BY101: =IFERROR(VLOOKUP($M101,FÉ!$B$41:$L$58,8,FALSE)*$W101*PRP!$J$8,) + IF($M101=FÉ!$B$57, IFERROR(VLOOKUP($Y101,FÉ!$B$385:$L$437,8,FALSE)*$AA101*PRP!$J$8,),0) -> 0 | BZ101: =IFERROR(VLOOKUP($M101,FÉ!$B$41:$L$58,9,FALSE)*$W101*PRP!$J$9,) + IF($M101=FÉ!$B$57, IFERROR(VLOOKUP($Y101,FÉ!$B$385:$L$437,9,FALSE)*$AA101*PRP!$J$9,),0) -> 0 | CA101: =IFERROR(VLOOKUP($M101,FÉ!$B$41:$L$58,10,FALSE)*$W101*PRP!$J$10,) + IF($M101=FÉ!$B$57, IFERROR(VLOOKUP($Y101,FÉ!$B$385:$L$437,10,FALSE)*$AA101*PRP!$J$10,),0) -> 0 | CB101: =SUM(BY101:CA101) -> 0 | CC101: =CB101/(10^6) -> 0 | CH101: =IFERROR(IF($M101=0, ,VLOOKUP($M101,FÉ!$B$41:$K$59,7,FALSE))*W101,) + AA101 -> 0
B102: =B101 -> 1.2B1 | F102: =IF(E102=0,"",MONTH(E102)) | G102: Bureau | M102: =IFERROR(VLOOKUP($U102,[1]!Tableau2[#Data],20,FALSE),) -> 0 | P102: 2016 | Q102: Nissan | R102: LEAF (24 kWh) | T102: 20000 | U102: =_xlfn.CONCAT(P102,", ",Q102,", ",R102) -> 2016, Nissan, LEAF (24 kWh) | V102: =IFERROR(VLOOKUP($U102,[1]!Tableau2[#Data],12,FALSE),) -> 0 | W102: =IFERROR($T102*V102/100,) -> 0 | X102: L | Y102: Québec | Z102: =IFERROR(VLOOKUP($U102,[1]!Tableau2[#Data],15,FALSE),) -> 0 | AA102: =IFERROR($T102*Z102/100,) -> 0 | AB102: kWh | BY102: =IFERROR(VLOOKUP($M102,FÉ!$B$41:$L$58,8,FALSE)*$W102*PRP!$J$8,) + IF($M102=FÉ!$B$57, IFERROR(VLOOKUP($Y102,FÉ!$B$385:$L$437,8,FALSE)*$AA102*PRP!$J$8,),0) -> 0 | BZ102: =IFERROR(VLOOKUP($M102,FÉ!$B$41:$L$58,9,FALSE)*$W102*PRP!$J$9,) + IF($M102=FÉ!$B$57, IFERROR(VLOOKUP($Y102,FÉ!$B$385:$L$437,9,FALSE)*$AA102*PRP!$J$9,),0) -> 0 | CA102: =IFERROR(VLOOKUP($M102,FÉ!$B$41:$L$58,10,FALSE)*$W102*PRP!$J$10,) + IF($M102=FÉ!$B$57, IFERROR(VLOOKUP($Y102,FÉ!$B$385:$L$437,10,FALSE)*$AA102*PRP!$J$10,),0) -> 0 | CB102: =SUM(BY102:CA102) -> 0 | CC102: =CB102/(10^6) -> 0 | CH102: =IFERROR(IF($M102=0, ,VLOOKUP($M102,FÉ!$B$41:$K$59,7,FALSE))*W102,) + AA102 -> 0
B103: =B102 -> 1.2B1 | F103: =IF(E103=0,"",MONTH(E103)) | M103: =IFERROR(VLOOKUP($U103,[1]!Tableau2[#Data],20,FALSE),) -> 0 | U103: =_xlfn.CONCAT(P103,", ",Q103,", ",R103) -> , , | V103: =IFERROR(VLOOKUP($U103,[1]!Tableau2[#Data],12,FALSE),) -> 0 | W103: =IFERROR($T103*V103/100,) -> 0 | X103: L | Z103: =IFERROR(VLOOKUP($U103,[1]!Tableau2[#Data],15,FALSE),) -> 0 | AA103: =IFERROR($T103*Z103/100,) -> 0 | AB103: kWh | BY103: =IFERROR(VLOOKUP($M103,FÉ!$B$41:$L$58,8,FALSE)*$W103*PRP!$J$8,) + IF($M103=FÉ!$B$57, IFERROR(VLOOKUP($Y103,FÉ!$B$385:$L$437,8,FALSE)*$AA103*PRP!$J$8,),0) -> 0 | BZ103: =IFERROR(VLOOKUP($M103,FÉ!$B$41:$L$58,9,FALSE)*$W103*PRP!$J$9,) + IF($M103=FÉ!$B$57, IFERROR(VLOOKUP($Y103,FÉ!$B$385:$L$437,9,FALSE)*$AA103*PRP!$J$9,),0) -> 0 | CA103: =IFERROR(VLOOKUP($M103,FÉ!$B$41:$L$58,10,FALSE)*$W103*PRP!$J$10,) + IF($M103=FÉ!$B$57, IFERROR(VLOOKUP($Y103,FÉ!$B$385:$L$437,10,FALSE)*$AA103*PRP!$J$10,),0) -> 0 | CB103: =SUM(BY103:CA103) -> 0 | CC103: =CB103/(10^6) -> 0 | CH103: =IFERROR(IF($M103=0, ,VLOOKUP($M103,FÉ!$B$41:$K$59,7,FALSE))*W103,) + AA103 -> 0
B104: =B103 -> 1.2B1 | F104: =IF(E104=0,"",MONTH(E104)) | M104: =IFERROR(VLOOKUP($U104,[1]!Tableau2[#Data],20,FALSE),) -> 0 | U104: =_xlfn.CONCAT(P104,", ",Q104,", ",R104) -> , , | V104: =IFERROR(VLOOKUP($U104,[1]!Tableau2[#Data],12,FALSE),) -> 0 | W104: =IFERROR($T104*V104/100,) -> 0 | X104: L | Z104: =IFERROR(VLOOKUP($U104,[1]!Tableau2[#Data],15,FALSE),) -> 0 | AA104: =IFERROR($T104*Z104/100,) -> 0 | AB104: kWh | BY104: =IFERROR(VLOOKUP($M104,FÉ!$B$41:$L$58,8,FALSE)*$W104*PRP!$J$8,) + IF($M104=FÉ!$B$57, IFERROR(VLOOKUP($Y104,FÉ!$B$385:$L$437,8,FALSE)*$AA104*PRP!$J$8,),0) -> 0 | BZ104: =IFERROR(VLOOKUP($M104,FÉ!$B$41:$L$58,9,FALSE)*$W104*PRP!$J$9,) + IF($M104=FÉ!$B$57, IFERROR(VLOOKUP($Y104,FÉ!$B$385:$L$437,9,FALSE)*$AA104*PRP!$J$9,),0) -> 0 | CA104: =IFERROR(VLOOKUP($M104,FÉ!$B$41:$L$58,10,FALSE)*$W104*PRP!$J$10,) + IF($M104=FÉ!$B$57, IFERROR(VLOOKUP($Y104,FÉ!$B$385:$L$437,10,FALSE)*$AA104*PRP!$J$10,),0) -> 0 | CB104: =SUM(BY104:CA104) -> 0 | CC104: =CB104/(10^6) -> 0 | CH104: =IFERROR(IF($M104=0, ,VLOOKUP($M104,FÉ!$B$41:$K$59,7,FALSE))*W104,) + AA104 -> 0
B105: =B104 -> 1.2B1 | F105: =IF(E105=0,"",MONTH(E105)) | M105: =IFERROR(VLOOKUP($U105,[1]!Tableau2[#Data],20,FALSE),) -> 0 | U105: =_xlfn.CONCAT(P105,", ",Q105,", ",R105) -> , , | V105: =IFERROR(VLOOKUP($U105,[1]!Tableau2[#Data],12,FALSE),) -> 0 | W105: =IFERROR($T105*V105/100,) -> 0 | X105: L | Z105: =IFERROR(VLOOKUP($U105,[1]!Tableau2[#Data],15,FALSE),) -> 0 | AA105: =IFERROR($T105*Z105/100,) -> 0 | AB105: kWh | BY105: =IFERROR(VLOOKUP($M105,FÉ!$B$41:$L$58,8,FALSE)*$W105*PRP!$J$8,) + IF($M105=FÉ!$B$57, IFERROR(VLOOKUP($Y105,FÉ!$B$385:$L$437,8,FALSE)*$AA105*PRP!$J$8,),0) -> 0 | BZ105: =IFERROR(VLOOKUP($M105,FÉ!$B$41:$L$58,9,FALSE)*$W105*PRP!$J$9,) + IF($M105=FÉ!$B$57, IFERROR(VLOOKUP($Y105,FÉ!$B$385:$L$437,9,FALSE)*$AA105*PRP!$J$9,),0) -> 0 | CA105: =IFERROR(VLOOKUP($M105,FÉ!$B$41:$L$58,10,FALSE)*$W105*PRP!$J$10,) + IF($M105=FÉ!$B$57, IFERROR(VLOOKUP($Y105,FÉ!$B$385:$L$437,10,FALSE)*$AA105*PRP!$J$10,),0) -> 0 | CB105: =SUM(BY105:CA105) -> 0 | CC105: =CB105/(10^6) -> 0 | CH105: =IFERROR(IF($M105=0, ,VLOOKUP($M105,FÉ!$B$41:$K$59,7,FALSE))*W105,) + AA105 -> 0
B106: =B105 -> 1.2B1 | F106: =IF(E106=0,"",MONTH(E106)) | M106: =IFERROR(VLOOKUP($U106,[1]!Tableau2[#Data],20,FALSE),) -> 0 | U106: =_xlfn.CONCAT(P106,", ",Q106,", ",R106) -> , , | V106: =IFERROR(VLOOKUP($U106,[1]!Tableau2[#Data],12,FALSE),) -> 0 | W106: =IFERROR($T106*V106/100,) -> 0 | X106: L | Z106: =IFERROR(VLOOKUP($U106,[1]!Tableau2[#Data],15,FALSE),) -> 0 | AA106: =IFERROR($T106*Z106/100,) -> 0 | AB106: kWh | BY106: =IFERROR(VLOOKUP($M106,FÉ!$B$41:$L$58,8,FALSE)*$W106*PRP!$J$8,) + IF($M106=FÉ!$B$57, IFERROR(VLOOKUP($Y106,FÉ!$B$385:$L$437,8,FALSE)*$AA106*PRP!$J$8,),0) -> 0 | BZ106: =IFERROR(VLOOKUP($M106,FÉ!$B$41:$L$58,9,FALSE)*$W106*PRP!$J$9,) + IF($M106=FÉ!$B$57, IFERROR(VLOOKUP($Y106,FÉ!$B$385:$L$437,9,FALSE)*$AA106*PRP!$J$9,),0) -> 0 | CA106: =IFERROR(VLOOKUP($M106,FÉ!$B$41:$L$58,10,FALSE)*$W106*PRP!$J$10,) + IF($M106=FÉ!$B$57, IFERROR(VLOOKUP($Y106,FÉ!$B$385:$L$437,10,FALSE)*$AA106*PRP!$J$10,),0) -> 0 | CB106: =SUM(BY106:CA106) -> 0 | CC106: =CB106/(10^6) -> 0 | CH106: =IFERROR(IF($M106=0, ,VLOOKUP($M106,FÉ!$B$41:$K$59,7,FALSE))*W106,) + AA106 -> 0
B107: =B106 -> 1.2B1 | F107: =IF(E107=0,"",MONTH(E107)) | M107: =IFERROR(VLOOKUP($U107,[1]!Tableau2[#Data],20,FALSE),) -> 0 | U107: =_xlfn.CONCAT(P107,", ",Q107,", ",R107) -> , , | V107: =IFERROR(VLOOKUP($U107,[1]!Tableau2[#Data],12,FALSE),) -> 0 | W107: =IFERROR($T107*V107/100,) -> 0 | X107: L | Z107: =IFERROR(VLOOKUP($U107,[1]!Tableau2[#Data],15,FALSE),) -> 0 | AA107: =IFERROR($T107*Z107/100,) -> 0 | AB107: kWh | BY107: =IFERROR(VLOOKUP($M107,FÉ!$B$41:$L$58,8,FALSE)*$W107*PRP!$J$8,) + IF($M107=FÉ!$B$57, IFERROR(VLOOKUP($Y107,FÉ!$B$385:$L$437,8,FALSE)*$AA107*PRP!$J$8,),0) -> 0 | BZ107: =IFERROR(VLOOKUP($M107,FÉ!$B$41:$L$58,9,FALSE)*$W107*PRP!$J$9,) + IF($M107=FÉ!$B$57, IFERROR(VLOOKUP($Y107,FÉ!$B$385:$L$437,9,FALSE)*$AA107*PRP!$J$9,),0) -> 0 | CA107: =IFERROR(VLOOKUP($M107,FÉ!$B$41:$L$58,10,FALSE)*$W107*PRP!$J$10,) + IF($M107=FÉ!$B$57, IFERROR(VLOOKUP($Y107,FÉ!$B$385:$L$437,10,FALSE)*$AA107*PRP!$J$10,),0) -> 0 | CB107: =SUM(BY107:CA107) -> 0 | CC107: =CB107/(10^6) -> 0 | CH107: =IFERROR(IF($M107=0, ,VLOOKUP($M107,FÉ!$B$41:$K$59,7,FALSE))*W107,) + AA107 -> 0
B108: =B107 -> 1.2B1 | F108: =IF(E108=0,"",MONTH(E108)) | M108: =IFERROR(VLOOKUP($U108,[1]!Tableau2[#Data],20,FALSE),) -> 0 | U108: =_xlfn.CONCAT(P108,", ",Q108,", ",R108) -> , , | V108: =IFERROR(VLOOKUP($U108,[1]!Tableau2[#Data],12,FALSE),) -> 0 | W108: =IFERROR($T108*V108/100,) -> 0 | X108: L | Z108: =IFERROR(VLOOKUP($U108,[1]!Tableau2[#Data],15,FALSE),) -> 0 | AA108: =IFERROR($T108*Z108/100,) -> 0 | AB108: kWh | BY108: =IFERROR(VLOOKUP($M108,FÉ!$B$41:$L$58,8,FALSE)*$W108*PRP!$J$8,) + IF($M108=FÉ!$B$57, IFERROR(VLOOKUP($Y108,FÉ!$B$385:$L$437,8,FALSE)*$AA108*PRP!$J$8,),0) -> 0 | BZ108: =IFERROR(VLOOKUP($M108,FÉ!$B$41:$L$58,9,FALSE)*$W108*PRP!$J$9,) + IF($M108=FÉ!$B$57, IFERROR(VLOOKUP($Y108,FÉ!$B$385:$L$437,9,FALSE)*$AA108*PRP!$J$9,),0) -> 0 | CA108: =IFERROR(VLOOKUP($M108,FÉ!$B$41:$L$58,10,FALSE)*$W108*PRP!$J$10,) + IF($M108=FÉ!$B$57, IFERROR(VLOOKUP($Y108,FÉ!$B$385:$L$437,10,FALSE)*$AA108*PRP!$J$10,),0) -> 0 | CB108: =SUM(BY108:CA108) -> 0 | CC108: =CB108/(10^6) -> 0 | CH108: =IFERROR(IF($M108=0, ,VLOOKUP($M108,FÉ!$B$41:$K$59,7,FALSE))*W108,) + AA108 -> 0
B109: =B108 -> 1.2B1 | F109: =IF(E109=0,"",MONTH(E109)) | M109: =IFERROR(VLOOKUP($U109,[1]!Tableau2[#Data],20,FALSE),) -> 0 | U109: =_xlfn.CONCAT(P109,", ",Q109,", ",R109) -> , , | V109: =IFERROR(VLOOKUP($U109,[1]!Tableau2[#Data],12,FALSE),) -> 0 | W109: =IFERROR($T109*V109/100,) -> 0 | X109: L | Z109: =IFERROR(VLOOKUP($U109,[1]!Tableau2[#Data],15,FALSE),) -> 0 | AA109: =IFERROR($T109*Z109/100,) -> 0 | AB109: kWh | BY109: =IFERROR(VLOOKUP($M109,FÉ!$B$41:$L$58,8,FALSE)*$W109*PRP!$J$8,) + IF($M109=FÉ!$B$57, IFERROR(VLOOKUP($Y109,FÉ!$B$385:$L$437,8,FALSE)*$AA109*PRP!$J$8,),0) -> 0 | BZ109: =IFERROR(VLOOKUP($M109,FÉ!$B$41:$L$58,9,FALSE)*$W109*PRP!$J$9,) + IF($M109=FÉ!$B$57, IFERROR(VLOOKUP($Y109,FÉ!$B$385:$L$437,9,FALSE)*$AA109*PRP!$J$9,),0) -> 0 | CA109: =IFERROR(VLOOKUP($M109,FÉ!$B$41:$L$58,10,FALSE)*$W109*PRP!$J$10,) + IF($M109=FÉ!$B$57, IFERROR(VLOOKUP($Y109,FÉ!$B$385:$L$437,10,FALSE)*$AA109*PRP!$J$10,),0) -> 0 | CB109: =SUM(BY109:CA109) -> 0 | CC109: =CB109/(10^6) -> 0 | CH109: =IFERROR(IF($M109=0, ,VLOOKUP($M109,FÉ!$B$41:$K$59,7,FALSE))*W109,) + AA109 -> 0
F110: =$B100 -> 1.2B1 | G110: =$B100 -> 1.2B1 | H110: =$B100 -> 1.2B1 | T110: =SUM(T100:T109) -> 40000 | W110: =SUM(W100:W109) -> 0 | AA110: =SUM(AA100:AA109) -> 0 | BY110: =SUM(BY100:BY109) -> 0 | BZ110: =SUM(BZ100:BZ109) -> 0 | CA110: =SUM(CA100:CA109) -> 0 | CB110: =SUM(CB100:CB109) -> 0 | CC110: =SUM(CC100:CC109) -> 0 | CE110: =SUM(CE100:CE109) -> 0 | CF110: =SUM(CF100:CF109) -> 0 | CH110: =SUM(CH100:CH109) -> 0
B112: 1.4A1 - Équipement de réfrigération et de climatisation fixe
B114: Données d'activité | BQ114: Calculs et résultats
B115: # méthode | C115: Liste des équipements | D115: Description | E115: Date | F115: mois | G115: Site | H115: Produit | I115: Références | AC115: Type d'équipement de réfrigéation | AD115: Type de réfrigérant | AE115: Quantité dans l'équipement | AF115: Fuites constaté par le frigoriste | BQ115: Probabilité de fuite | BR115: Fuite estimé à partir des probabilité | BS115: Fuites calculée | BT115: PRP | BY115: Émissions GES | CB115: Total GES : | CE115: Total CO2 Biogénique : | CH115: Énergie équivalente
BY116: CO2 | BZ116: CH4 | CA116: N2O
...

Sheet Résultats
B1: Résultats
B3: =Calculs!B3 -> # méthode | C3: =Calculs!BY3 -> CO2 | D3: =Calculs!BZ3 -> CH4 | E3: =Calculs!CA3 -> N2O | F3: =Calculs!CB3 -> Total GES : | I3: =Calculs!CE3 -> Total CO2 Biogénique : | L3: =Calculs!CH3 -> Énergie équivalente
B4: =Calculs!B4 -> 0 | C4: =Calculs!BY4 -> 0 | D4: =Calculs!BZ4 -> 0 | E4: =Calculs!CA4 -> 0 | F4: =Calculs!CB4 -> 0 | G4: =Calculs!CC4 -> 0 | I4: =Calculs!CE4 -> 0 | J4: =Calculs!CF4 -> 0 | L4: =Calculs!CH4 -> 0
B5: =Calculs!B5 -> 1.1A1 - Chauffage des bâtiments et équipements fixes | C5: =Calculs!BY5 -> 0 | D5: =Calculs!BZ5 -> 0 | E5: =Calculs!CA5 -> 0 | F5: =Calculs!CB5 -> 0 | G5: =Calculs!CC5 -> 0 | I5: =Calculs!CE5 -> 0 | J5: =Calculs!CF5 -> 0 | L5: =Calculs!CH5 -> 0
B6: =Calculs!B6 -> 0 | C6: =Calculs!BY6 -> 0 | D6: =Calculs!BZ6 -> 0 | E6: =Calculs!CA6 -> 0 | F6: =Calculs!CB6 -> 0 | G6: =Calculs!CC6 -> 0 | I6: =Calculs!CE6 -> 0 | J6: =Calculs!CF6 -> 0 | L6: =Calculs!CH6 -> 0
B7: =Calculs!B7 -> Données d'activité | C7: =Calculs!BY7 -> 0 | D7: =Calculs!BZ7 -> 0 | E7: =Calculs!CA7 -> 0 | F7: =Calculs!CB7 -> 0 | G7: =Calculs!CC7 -> 0 | I7: =Calculs!CE7 -> 0 | J7: =Calculs!CF7 -> 0 | L7: =Calculs!CH7 -> 0
B8: =Calculs!B8 -> # méthode | C8: =Calculs!BY8 -> Émissions GES | D8: =Calculs!BZ8 -> 0 | E8: =Calculs!CA8 -> 0 | F8: =Calculs!CB8 -> Total GES : | G8: =Calculs!CC8 -> 0 | I8: =Calculs!CE8 -> Total CO2 Biogénique : | J8: =Calculs!CF8 -> 0 | L8: =Calculs!CH8 -> Énergie équivalente
B9: =Calculs!B9 -> 0 | C9: =Calculs!BY9 -> CO2 | D9: =Calculs!BZ9 -> CH4 | E9: =Calculs!CA9 -> N2O | F9: =Calculs!CB9 -> 0 | G9: =Calculs!CC9 -> 0 | I9: =Calculs!CE9 -> 0 | J9: =Calculs!CF9 -> 0 | L9: =Calculs!CH9 -> 0
B10: =Calculs!B10 -> 0 | C10: =Calculs!BY10 -> [gCO2e] | D10: =Calculs!BZ10 -> [gCO2e] | E10: =Calculs!CA10 -> [gCO2e] | F10: =Calculs!CB10 -> [gCO2e] | G10: =Calculs!CC10 -> [tCO2e] | I10: =Calculs!CE10 -> [gCO2e] | J10: =Calculs!CF10 -> [tCO2e] | L10: =Calculs!CH10 -> [kWh]
B11: =Calculs!B11 -> 1.1A1 | C11: =Calculs!BY11 -> 0 | D11: =Calculs!BZ11 -> 0 | E11: =Calculs!CA11 -> 0 | F11: =Calculs!CB11 -> 0 | G11: =Calculs!CC11 -> 0 | I11: =Calculs!CE11 -> 0 | J11: =Calculs!CF11 -> 0 | L11: =Calculs!CH11 -> 0
B12: =Calculs!B12 -> 1.1A1 | C12: =Calculs!BY12 -> 2753000 | D12: =Calculs!BZ12 -> 5364 | E12: =Calculs!CA12 -> 8463 | F12: =Calculs!CB12 -> 2766827 | G12: =Calculs!CC12 -> 2.766827 | I12: =Calculs!CE12 -> 0 | J12: =Calculs!CF12 -> 0 | L12: =Calculs!CH12 -> 10770
B13: =Calculs!B13 -> 1.1A1 | C13: =Calculs!BY13 -> 0 | D13: =Calculs!BZ13 -> 25747.2 | E13: =Calculs!CA13 -> 31531.5 | F13: =Calculs!CB13 -> 57278.7 | G13: =Calculs!CC13 -> 0.0572787 | I13: =Calculs!CE13 -> 2698500 | J13: =Calculs!CF13 -> 2.6985 | L13: =Calculs!CH13 -> 7995
B14: =Calculs!B14 -> 1.1A1 | C14: =Calculs!BY14 -> 1515000 | D14: =Calculs!BZ14 -> 804.6 | E14: =Calculs!CA14 -> 29484 | F14: =Calculs!CB14 -> 1545288.6 | G14: =Calculs!CC14 -> 1.5452886 | I14: =Calculs!CE14 -> 0 | J14: =Calculs!CF14 -> 0 | L14: =Calculs!CH14 -> 7030
B15: =Calculs!B15 -> 1.1A1 | C15: =Calculs!BY15 -> 0 | D15: =Calculs!BZ15 -> 0 | E15: =Calculs!CA15 -> 0 | F15: =Calculs!CB15 -> 0 | G15: =Calculs!CC15 -> 0 | I15: =Calculs!CE15 -> 0 | J15: =Calculs!CF15 -> 0 | L15: =Calculs!CH15 -> 0
... B210: =Calculs!B210 -> 0 | C210: =Calculs!BY210 -> 0 | D210: =Calculs!BZ210 -> 0 | E210: =Calculs!CA210 -> 0 | F210: =Calculs!CB210 -> 0 | G210: =Calculs!CC210 -> 0 | I210: =Calculs!CE210 -> 0 | J210: =Calculs!CF210 -> 0 | L210: =Calculs!CH210 -> 0
B211: =Calculs!#REF! -> #REF! | C211: =Calculs!#REF! -> #REF! | D211: =Calculs!#REF! -> #REF! | E211: =Calculs!#REF! -> #REF! | F211: =Calculs!#REF! -> #REF! | G211: =Calculs!#REF! -> #REF! | I211: =Calculs!#REF! -> #REF! | J211: =Calculs!#REF! -> #REF! | L211: =Calculs!#REF! -> #REF!
B212: =Calculs!#REF! -> #REF! | C212: =Calculs!#REF! -> #REF! | D212: =Calculs!#REF! -> #REF! | E212: =Calculs!#REF! -> #REF! | F212: =Calculs!#REF! -> #REF! | G212: =Calculs!#REF! -> #REF! | I212: =Calculs!#REF! -> #REF! | J212: =Calculs!#REF! -> #REF! | L212: =Calculs!#REF! -> #REF!
B213: =Calculs!#REF! -> #REF! | C213: =Calculs!#REF! -> #REF! | D213: =Calculs!#REF! -> #REF! | E213: =Calculs!#REF! -> #REF! | F213: =Calculs!#REF! -> #REF! | G213: =Calculs!#REF! -> #REF! | I213: =Calculs!#REF! -> #REF! | J213: =Calculs!#REF! -> #REF! | L213: =Calculs!#REF! -> #REF!
B214: =Calculs!#REF! -> #REF! | C214: =Calculs!#REF! -> #REF! | D214: =Calculs!#REF! -> #REF! | E214: =Calculs!#REF! -> #REF! | F214: =Calculs!#REF! -> #REF! | G214: =Calculs!#REF! -> #REF! | I214: =Calculs!#REF! -> #REF! | J214: =Calculs!#REF! -> #REF! | L214: =Calculs!#REF! -> #REF!
B215: =Calculs!#REF! -> #REF! | C215: =Calculs!#REF! -> #REF! | D215: =Calculs!#REF! -> #REF! | E215: =Calculs!#REF! -> #REF! | F215: =Calculs!#REF! -> #REF! | G215: =Calculs!#REF! -> #REF! | I215: =Calculs!#REF! -> #REF! | J215: =Calculs!#REF! -> #REF! | L215: =Calculs!#REF! -> #REF!
B216: =Calculs!#REF! -> #REF! | C216: =Calculs!#REF! -> #REF! | D216: =Calculs!#REF! -> #REF! | E216: =Calculs!#REF! -> #REF! | F216: =Calculs!#REF! -> #REF! | G216: =Calculs!#REF! -> #REF! | I216: =Calculs!#REF! -> #REF! | J216: =Calculs!#REF! -> #REF! | L216: =Calculs!#REF! -> #REF!
B217: =Calculs!#REF! -> #REF! | C217: =Calculs!#REF! -> #REF! | D217: =Calculs!#REF! -> #REF! | E217: =Calculs!#REF! -> #REF! | F217: =Calculs!#REF! -> #REF! | G217: =Calculs!#REF! -> #REF! | I217: =Calculs!#REF! -> #REF! | J217: =Calculs!#REF! -> #REF! | L217: =Calculs!#REF! -> #REF!
B218: =Calculs!#REF! -> #REF! | C218: =Calculs!#REF! -> #REF! | D218: =Calculs!#REF! -> #REF! | E218: =Calculs!#REF! -> #REF! | F218: =Calculs!#REF! -> #REF! | G218: =Calculs!#REF! -> #REF! | I218: =Calculs!#REF! -> #REF! | J218: =Calculs!#REF! -> #REF! | L218: =Calculs!#REF! -> #REF!
B219: =Calculs!#REF! -> #REF! | C219: =Calculs!#REF! -> #REF! | D219: =Calculs!#REF! -> #REF! | E219: =Calculs!#REF! -> #REF! | F219: =Calculs!#REF! -> #REF! | G219: =Calculs!#REF! -> #REF! | I219: =Calculs!#REF! -> #REF! | J219: =Calculs!#REF! -> #REF! | L219: =Calculs!#REF! -> #REF!
B220: =Calculs!#REF! -> #REF! | C220: =Calculs!#REF! -> #REF! | D220: =Calculs!#REF! -> #REF! | E220: =Calculs!#REF! -> #REF! | F220: =Calculs!#REF! -> #REF! | G220: =Calculs!#REF! -> #REF! | I220: =Calculs!#REF! -> #REF! | J220: =Calculs!#REF! -> #REF! | L220: =Calculs!#REF! -> #REF!
B221: =Calculs!#REF! -> #REF! | C221: =Calculs!#REF! -> #REF! | D221: =Calculs!#REF! -> #REF! | E221: =Calculs!#REF! -> #REF! | F221: =Calculs!#REF! -> #REF! | G221: =Calculs!#REF! -> #REF! | I221: =Calculs!#REF! -> #REF! | J221: =Calculs!#REF! -> #REF! | L221: =Calculs!#REF! -> #REF!
B222: =Calculs!#REF! -> #REF! | C222: =Calculs!#REF! -> #REF! | D222: =Calculs!#REF! -> #REF! | E222: =Calculs!#REF! -> #REF! | F222: =Calculs!#REF! -> #REF! | G222: =Calculs!#REF! -> #REF! | I222: =Calculs!#REF! -> #REF! | J222: =Calculs!#REF! -> #REF! | L222: =Calculs!#REF! -> #REF!
... B228: =Calculs!#REF! -> #REF! | C228: =Calculs!#REF! -> #REF! | D228: =Calculs!#REF! -> #REF! | E228: =Calculs!#REF! -> #REF! | F228: =Calculs!#REF! -> #REF! | G228: =Calculs!#REF! -> #REF! | I228: =Calculs!#REF! -> #REF! | J228: =Calculs!#REF! -> #REF! | L228: =Calculs!#REF! -> #REF!
B229: =Calculs!B265 -> 3.5A1 - Déplacements d'affaires en voiture | C229: =Calculs!BY265 -> 0 | D229: =Calculs!BZ265 -> 0 | E229: =Calculs!CA265 -> 0 | F229: =Calculs!CB265 -> 0 | G229: =Calculs!CC265 -> 0 | I229: =Calculs!CE265 -> 0 | J229: =Calculs!CF265 -> 0 | L229: =Calculs!CH265 -> 0
B230: =Calculs!B266 -> 0 | C230: =Calculs!BY266 -> 0 | D230: =Calculs!BZ266 -> 0 | E230: =Calculs!CA266 -> 0 | F230: =Calculs!CB266 -> 0 | G230: =Calculs!CC266 -> 0 | I230: =Calculs!CE266 -> 0 | J230: =Calculs!CF266 -> 0 | L230: =Calculs!CH266 -> 0
B231: =Calculs!B267 -> Données d'activité | C231: =Calculs!BY267 -> 0 | D231: =Calculs!BZ267 -> 0 | E231: =Calculs!CA267 -> 0 | F231: =Calculs!CB267 -> 0 | G231: =Calculs!CC267 -> 0 | I231: =Calculs!CE267 -> 0 | J231: =Calculs!CF267 -> 0 | L231: =Calculs!CH267 -> 0
B232: =Calculs!B268 -> # méthode | C232: =Calculs!BY268 -> Émissions GES | D232: =Calculs!BZ268 -> 0 | E232: =Calculs!CA268 -> 0 | F232: =Calculs!CB268 -> Total GES : | G232: =Calculs!CC268 -> 0 | I232: =Calculs!CE268 -> Total CO2 Biogénique : | J232: =Calculs!CF268 -> 0 | L232: =Calculs!CH268 -> Énergie équivalente
B233: =Calculs!B269 -> 0 | C233: =Calculs!BY269 -> CO2 | D233: =Calculs!BZ269 -> CH4 | E233: =Calculs!CA269 -> N2O | F233: =Calculs!CB269 -> 0 | G233: =Calculs!CC269 -> 0 | I233: =Calculs!CE269 -> 0 | J233: =Calculs!CF269 -> 0 | L233: =Calculs!CH269 -> 0
B234: =Calculs!B270 -> 0 | C234: =Calculs!BY270 -> [gCO2e] | D234: =Calculs!BZ270 -> [gCO2e] | E234: =Calculs!CA270 -> [gCO2e] | F234: =Calculs!CB270 -> [gCO2e] | G234: =Calculs!CC270 -> [tCO2e] | I234: =Calculs!CE270 -> [gCO2e] | J234: =Calculs!CF270 -> [tCO2e] | L234: =Calculs!CH270 -> [kWh]
B235: =Calculs!B271 -> 3.5A1 | C235: =Calculs!BY271 -> 0 | D235: =Calculs!BZ271 -> 0 | E235: =Calculs!CA271 -> 0 | F235: =Calculs!CB271 -> 0 | G235: =Calculs!CC271 -> 0 | I235: =Calculs!CE271 -> 0 | J235: =Calculs!CF271 -> 0 | L235: =Calculs!CH271 -> 0
B236: =Calculs!B272 -> 3.5A1 | C236: =Calculs!BY272 -> 576825 | D236: =Calculs!BZ272 -> 506.6 | E236: =Calculs!CA272 -> 13650 | F236: =Calculs!CB272 -> 590981.6 | G236: =Calculs!CC272 -> 0.5909816 | I236: =Calculs!CE272 -> 0 | J236: =Calculs!CF272 -> 0 | L236: =Calculs!CH272 -> 2422.5
B237: =Calculs!B273 -> 3.5A1 | C237: =Calculs!BY273 -> 1340250 | D237: =Calculs!BZ273 -> 759.9 | E237: =Calculs!CA273 -> 30030 | F237: =Calculs!CB273 -> 1371039.9 | G237: =Calculs!CC273 -> 1.3710399 | I237: =Calculs!CE273 -> 0 | J237: =Calculs!CF273 -> 0 | L237: =Calculs!CH273 -> 5320
B238: =Calculs!B274 -> 3.5A1 | C238: =Calculs!BY274 -> 0 | D238: =Calculs!BZ274 -> 0 | E238: =Calculs!CA274 -> 0 | F238: =Calculs!CB274 -> 0 | G238: =Calculs!CC274 -> 0 | I238: =Calculs!CE274 -> 0 | J238: =Calculs!CF274 -> 0 | L238: =Calculs!CH274 -> 0
B239: =Calculs!B275 -> 3.5A1 | C239: =Calculs!BY275 -> 0 | D239: =Calculs!BZ275 -> 0 | E239: =Calculs!CA275 -> 0 | F239: =Calculs!CB275 -> 0 | G239: =Calculs!CC275 -> 0 | I239: =Calculs!CE275 -> 0 | J239: =Calculs!CF275 -> 0 | L239: =Calculs!CH275 -> 0
B240: =Calculs!B276 -> 3.5A1 | C240: =Calculs!BY276 -> 0 | D240: =Calculs!BZ276 -> 0 | E240: =Calculs!CA276 -> 0 | F240: =Calculs!CB276 -> 0 | G240: =Calculs!CC276 -> 0 | I240: =Calculs!CE276 -> 0 | J240: =Calculs!CF276 -> 0 | L240: =Calculs!CH276 -> 0
... B246: =Calculs!B282 -> 0 | C246: =Calculs!BY282 -> 0 | D246: =Calculs!BZ282 -> 0 | E246: =Calculs!CA282 -> 0 | F246: =Calculs!CB282 -> 0 | G246: =Calculs!CC282 -> 0 | I246: =Calculs!CE282 -> 0 | J246: =Calculs!CF282 -> 0 | L246: =Calculs!CH282 -> 0
B247: =Calculs!B319 -> 4.1A2 - Appareils numérique (non-amortie) | C247: =Calculs!BY319 -> 0 | D247: =Calculs!BZ319 -> 0 | E247: =Calculs!CA319 -> 0 | F247: =Calculs!CB319 -> 0 | G247: =Calculs!CC319 -> 0 | I247: =Calculs!CE319 -> 0 | J247: =Calculs!CF319 -> 0 | L247: =Calculs!CH319 -> 0
B248: =Calculs!B320 -> 0 | C248: =Calculs!BY320 -> 0 | D248: =Calculs!BZ320 -> 0 | E248: =Calculs!CA320 -> 0 | F248: =Calculs!CB320 -> 0 | G248: =Calculs!CC320 -> 0 | I248: =Calculs!CE320 -> 0 | J248: =Calculs!CF320 -> 0 | L248: =Calculs!CH320 -> 0
B249: =Calculs!B321 -> Données d'activité | C249: =Calculs!BY321 -> 0 | D249: =Calculs!BZ321 -> 0 | E249: =Calculs!CA321 -> 0 | F249: =Calculs!CB321 -> 0 | G249: =Calculs!CC321 -> 0 | I249: =Calculs!CE321 -> 0 | J249: =Calculs!CF321 -> 0 | L249: =Calculs!CH321 -> 0
B250: =Calculs!B322 -> # méthode | C250: =Calculs!BY322 -> Émissions GES | D250: =Calculs!BZ322 -> 0 | E250: =Calculs!CA322 -> 0 | F250: =Calculs!CB322 -> Total GES : | G250: =Calculs!CC322 -> 0 | I250: =Calculs!CE322 -> Total CO2 Biogénique : | J250: =Calculs!CF322 -> 0 | L250: =Calculs!CH322 -> Énergie équivalente
B251: =Calculs!B323 -> 0 | C251: =Calculs!BY323 -> CO2 | D251: =Calculs!BZ323 -> CH4 | E251: =Calculs!CA323 -> N2O | F251: =Calculs!CB323 -> 0 | G251: =Calculs!CC323 -> 0 | I251: =Calculs!CE323 -> 0 | J251: =Calculs!CF323 -> 0 | L251: =Calculs!CH323 -> 0
B252: =Calculs!B324 -> 0 | C252: =Calculs!BY324 -> [gCO2e] | D252: =Calculs!BZ324 -> [gCO2e] | E252: =Calculs!CA324 -> [gCO2e] | F252: =Calculs!CB324 -> [gCO2e] | G252: =Calculs!CC324 -> [tCO2e] | I252: =Calculs!CE324 -> [gCO2e] | J252: =Calculs!CF324 -> [tCO2e] | L252: =Calculs!CH324 -> [kWh]
B253: =Calculs!B325 -> 4.1A2 | C253: =Calculs!BY325 -> 619.5 | D253: =Calculs!BZ325 -> 0 | E253: =Calculs!CA325 -> 0 | F253: =Calculs!CB325 -> 619.5 | G253: =Calculs!CC325 -> 0.0006195 | I253: =Calculs!CE325 -> 0 | J253: =Calculs!CF325 -> 0 | L253: =Calculs!CH325 -> 0
B254: =Calculs!B326 -> 4.1A2 | C254: =Calculs!BY326 -> 3097 | D254: =Calculs!BZ326 -> 0 | E254: =Calculs!CA326 -> 0 | F254: =Calculs!CB326 -> 3097 | G254: =Calculs!CC326 -> 0.003097 | I254: =Calculs!CE326 -> 0 | J254: =Calculs!CF326 -> 0 | L254: =Calculs!CH326 -> 0
B255: =Calculs!B327 -> 4.1A2 | C255: =Calculs!BY327 -> 1474.5 | D255: =Calculs!BZ327 -> 0 | E255: =Calculs!CA327 -> 0 | F255: =Calculs!CB327 -> 1474.5 | G255: =Calculs!CC327 -> 0.0014745 | I255: =Calculs!CE327 -> 0 | J255: =Calculs!CF327 -> 0 | L255: =Calculs!CH327 -> 0
B256: =Calculs!B328 -> 4.1A2 | C256: =Calculs!BY328 -> 17760 | D256: =Calculs!BZ328 -> 0 | E256: =Calculs!CA328 -> 0 | F256: =Calculs!CB328 -> 17760 | G256: =Calculs!CC328 -> 0.01776 | I256: =Calculs!CE328 -> 0 | J256: =Calculs!CF328 -> 0 | L256: =Calculs!CH328 -> 0
B257: =Calculs!B329 -> 4.1A2 | C257: =Calculs!BY329 -> 2853.6 | D257: =Calculs!BZ329 -> 0 | E257: =Calculs!CA329 -> 0 | F257: =Calculs!CB329 -> 2853.6 | G257: =Calculs!CC329 -> 0.0028536 | I257: =Calculs!CE329 -> 0 | J257: =Calculs!CF329 -> 0 | L257: =Calculs!CH329 -> 0
B258: =Calculs!B330 -> 4.1A2 | C258: =Calculs!BY330 -> 9360 | D258: =Calculs!BZ330 -> 0 | E258: =Calculs!CA330 -> 0 | F258: =Calculs!CB330 -> 9360 | G258: =Calculs!CC330 -> 0.00936 | I258: =Calculs!CE330 -> 0 | J258: =Calculs!CF330 -> 0 | L258: =Calculs!CH330 -> 0
... B2252: =Calculs!B2324 -> 0 | C2252: =Calculs!BY2324 -> 0 | D2252: =Calculs!BZ2324 -> 0 | E2252: =Calculs!CA2324 -> 0 | F2252: =Calculs!CB2324 -> 0 | G2252: =Calculs!CC2324 -> 0 | I2252: =Calculs!CE2324 -> 0 | J2252: =Calculs!CF2324 -> 0 | L2252: =Calculs!CH2324 -> 0
B2253: =Calculs!B2455 -> 0 | C2253: =Calculs!BY2455 -> 0 | D2253: =Calculs!BZ2455 -> 0 | E2253: =Calculs!CA2455 -> 0 | F2253: =Calculs!CB2455 -> 0 | G2253: =Calculs!CC2455 -> 0 | I2253: =Calculs!CE2455 -> 0 | J2253: =Calculs!CF2455 -> 0 | L2253: =Calculs!CH2455 -> 0

Sheet Listes des méthodologies
B2: Liste des méthodologies de calculs | L2: Équivalent GHG PROTOCOL | N2: Mapping for Frontend programmation
B3: Catégorie | C3: Postes d'émissions | E3: Sources d'émissions | G3: Méthodologies
B4: [1@6] | C4: [1@22] | D4: Description | E4: [lettre] | F4: Description | G4: [no.] | H4: Description | I4: Code | J4: Notes | L4: Code | N4: Lines start | O4: Lines end
B5: Catégorie 1 | C5: 1.1 | D5: Émissions directes des sources de combustions fixes | E5: A | F5: Équipement fixe | G5: 1 | H5: Quantité de combustible comptabilisé à partir des factures | I5: 1.1A1 | L5: 1-1A1 | N5: =ROW(Debut_1A1)+1 -> 11 | O5: =ROW(Fin_1A1)-1 -> 30
G6: 2 | H6: Quantité de combustible estimé à partir de la moyenne de l'industrie | I6: 1A2 | L6: 1-1A2
C7: 1.2 | D7: Émissions directes des sources de combustions mobiles | E7: A | F7: Équipement mobile | G7: 1 | H7: Quantité de combustible comptabilisé à partir des factures | I7: 1.2A1 | J7: Liée à 10A1 | L7: 1-2A1 | N7: =ROW(Calculs!B38)+1 -> 39 | O7: =ROW(Calculs!B56)-1 -> 55
G8: 2 | H8: Par la distance parcourue (Consommation d'essence connue) | I8: 1.2A2 | L8: 1-2A2 | N8: =ROW(Calculs!B63)+1 -> 64 | O8: =ROW(Calculs!B74)-1 -> 73
G9: 3 | H9: À partir des coûts d'essence | I9: 1.2A3 | L9: 1-2A3 | N9: =ROW(Calculs!B81)+1 -> 82 | O9: =ROW(Calculs!B92)-1 -> 91
E10: B | F10: Véhicule | G10: 1 | H10: Par la distance parcourue (Consommation inconnue; Marque, modèle et année connus) | I10: 1.2B1 | J10: Liée à 10A3 | L10: 1-2B1 | N10: =ROW(Calculs!B99)+1 -> 100 | O10: =ROW(Calculs!B110)-1 -> 109
C11: 1.3 | D11: Émissions directes provenant des procédés et élevages d'animaux | E11: A | F11: Digestion entérique | G11: 1 | H11: Par tête | I11: 1.3A1 | J11: Liée à 3B2
E12: B | F12: Gestion du fumier | G12: 1 | H12: En kg par type d'élevage | I12: 1.3B1
G13: 2 | H13: Par tête | I13: 1.3B2 | J13: Liée à 3A1 (Nécessite 3A1)
E14: C | F14: Engrais azoté | G14: 1 | H14: Par quantité [kg] et % d'azote | I14: 1.3C1 | J14: Liée à 9F4
E15: D | F15: Procécéder | G15: 1 | H15: Nettoyage cryogénique | I15: 1.3D1 | J15: Liée à 9J1
C16: 1.4 | D16: Émissions fugitives directes (Réfrigérants) | E16: A | F16: Équipement fixe de climatisation et de réfrigération | G16: 1 | H16: Quantité rapporté par le frigoriste | I16: 1.4A1 | N16: =ROW(Calculs!B117)+1 -> 118 | O16: =ROW(Calculs!B128)-1 -> 127
G17: 2 | H17: Moyenne de l'industrie | I17: 1.4A2
E18: B | F18: Système de climatisation des véhicules | G18: 1 | H18: Moyenne de l'industrie | I18: 1.4B1 | J18: Liée à "Détails Entreprise" | N18: =ROW(Calculs!B135)+1 -> 136 | O18: =ROW(Calculs!B137)-1 -> 136
G19: 2 | H19: Données des véhicules | I19: 1.4B2 | N19: =ROW(Calculs!B144)+1 -> 145 | O19: =ROW(Calculs!B155)-1 -> 154
C20: 1.5 | D20: Émissions directes provenant de l'usage des sols (incluant agricoles) et de la foresterie | E20: A | F20: Déforestation | G20: 1 | H20: Par la surface et par le type de forêt | I20: 1.5A1 | J20: Liée à 5B1
E21: B | F21: Perte de séquestration | G21: 1 | H21: Par la surface et par le type de forêt (sur 100 ans) | I21: 1.5B1 | J21: Liée à 5A1 (Nécessite 5A1)
G22: 2 | H22: Par la surface et par le type de forêt (par année) | I22: 1.5B2
E23: C | F23: Plantation d'arbre | G23: 1 | H23: Nb d'arbres et année de plantation [kgCO2e capté/an] | I23: 1.5C1
G24: 2 | H24: Captation estimé sur X années | I24: 1.5C2
B25: Catégorie 2 | C25: 2.1 | D25: Émissions indirectes provenant de la consommation d'électricité | E25: A | F25: Consommation d'électricité (Location-based) | G25: 1 | H25: Quantité d'électricité comptabilisé à partir des factures | I25: 2.1A1 | L25: 2-1A1 | N25: =ROW(Calculs!B162)+1 -> 163 | O25: =ROW(Calculs!B173)-1 -> 172
G26: 2 | H26: Estimation à partir de la moyenne de l'industrie | I26: 2.1A2
E27: B | F27: Consommation d'électricité (Market-based) | G27: 1 | H27: Quantité d'électricité comptabilisé à partir des factures (avec certificat d'intensité carbone à l'appui) | I27: 2.1B1 | L27: 2-1B1 | N27: =ROW(Calculs!B180)+1 -> 181 | O27: =ROW(Calculs!B191)-1 -> 190
C28: 2.2 | D28: Émissions indirectes provenant de la consommation d'un réseau d'énergie (exclut l'électricité) | E28: A | F28: Importation d'énergie sous forme de chaleur | G28: 1 | H28: Quantité d'énergie produite et quantité d'énergie importée toutes deux connues | I28: 2.2A1 | L28: 2-2A1
G29: 2 | H29: Quantité de combustible attribuable à l'énergie importée | I29: 2.2A2 | L29: 2-2A2 | N29: =ROW(Calculs!B198)+1 -> 199 | O29: =ROW(Calculs!B210)-1 -> 209
G30: 3 | H30: Quantité d'énergie produite ESTIMÉE et quantité d'énergie importée connue | I30: 2.2A3
E31: B | F31: Importation d'énergie sous forme d'air comprimé | G31: 1 | H31: Quantité d'air comprimé acheté | I31: 2.2B1
B32: Catégorie 3 | C32: 3.1 | I32: 3.1A1 | N32: =ROW(Calculs!B216)+1 -> 217 | O32: =ROW(Calculs!B227)-1 -> 226
I33: 3.1A2
C34: 3.2 | I34: 3.2A1
I35: 3.2B1
C36: 3.3 | I36: 3.3A1
I37: 3.3A2
I38: 3.3A3
I39: 3.3B1
I40: 3.3B2
C41: 3.4 | I41: 3.4A1 | N41: =ROW(Calculs!B234)+1 -> 235 | O41: =ROW(Calculs!B245)-1 -> 244
I42: 3.4A2
I43: 3.4A3
I44: 3.4B1 | N44: =ROW(Calculs!B252)+1 -> 253 | O44: =ROW(Calculs!B263)-1 -> 262
C45: 3.5 | I45: 3.5A1 | N45: =ROW(Calculs!B270)+1 -> 271 | O45: =ROW(Calculs!B281)-1 -> 280
I46: 3.5A2
I47: 3.5A3
I48: 3.5B1 | N48: =ROW(Calculs!B288)+1 -> 289 | O48: =ROW(Calculs!B299)-1 -> 298
I49: 3.5B2
I50: 3.5C1 | N50: =ROW(Calculs!B306)+1 -> 307 | O50: =ROW(Calculs!B317)-1 -> 316
I51: 3.5D1
I52: 3.5E1
I53: 3.5F1
B54: Catégorie 4 | C54: 4.1 | I54: 4.1A1
I55: 4.1A2 | N55: =ROW(Calculs!B324)+1 -> 325 | O55: =ROW(Calculs!B335)-1 -> 334
I56: 4.1A3
I57: 4.1B1 | N57: =ROW(Calculs!B342)+1 -> 343 | O57: =ROW(Calculs!B353)-1 -> 352
I58: 4.1C1 | N58: =ROW(Calculs!B360)+1 -> 361 | O58: =ROW(Calculs!B371)-1 -> 370
I59: 4.1D1 | N59: =ROW(Calculs!B378)+1 -> 379 | O59: =ROW(Calculs!B389)-1 -> 388
I60: 4.1D2
I61: 4.1E1 | N61: =ROW(Calculs!B396)+1 -> 397 | O61: =ROW(Calculs!B407)-1 -> 406
I62: 4.1E2 | N62: =ROW(Calculs!B414)+1 -> 415 | O62: =ROW(Calculs!B425)-1 -> 424
I63: 4.1F1
I64: 4.1F2
I65: 4.1F3
I66: 4.1F4
I67: 4.1F5
I68: 4.1F6
I69: 4.1G1
I70: 4.1G2
I71: 4.1G6
I72: 4.1H1
I73: 4.1H2
I74: 4.1J1
... I82: 4.1X1.2B1
C84: 4.2 | I84: 4.2A1
I85: 4.2A2
I86: 4.2A3
I87: 4.2A4
I88: 4.2B1
I89: 4.2C1
C90: 4.3 | I90: 4.3A1 | N90: =ROW(Calculs!B432)+1 -> 433 | O90: =ROW(Calculs!B443)-1 -> 442
I91: 4.3B1
I92: 4.3B2
I93: 4.3B3
C94: 4.4 | I94: 4.4A1
I95: 4.4A2
I96: 4.4A3
I97: 4.4B1
I98: 4.4C1
C99: 4.5
I101: 4.5H1
I102: 4.5L1
I103: 4.5L2
I104: 4.5T1
I105: 4.5T2
B106: Catégorie 5 | C106: 5.1
C107: 5.2
C108: 5.3 | I108: 5.3A1
I109: 5.3B1
I110: 5.3B2
...

Sheet PRP
B2: Global Warming Potential (GWP)
B5: GREENHOUSE GASES | J5: GWP | L5: References
J6: (100 years)
B7: Name | C7: chemical formula
B8: Carbon Dioxyde | C8: CO2 | J8: 1 | L8: IPCC (2021), AR6 Chapitre 7, table 7.15 (GWP-100)
B9: Methan | C9: CH4 | J9: 29.8 | L9: IPCC (2021), AR6 Chapitre 7, table 7.15 (GWP-100)
B10: nitrous oxide | C10: N2O | J10: 273 | L10: IPCC (2021), AR6 Chapitre 7, table 7.15 (GWP-100)
B11: PFC-14 | C11: CF4 | J11: 7380 | L11: IPCC (2021), AR6 Chapitre 7, table 7.15 (GWP-100)
B12: Sulfur hexafluoride | C12: SF6 | J12: 22800 | L12: NIR (2022), PT1, tableau A1-1, p.19
B15: REFRIGERANTS | J15: GWP | L15: References
D16: Blends | J16: (100 years)
B17: REFRIGERANTS | C17: Use for | D17: R-32 | E17: R-125 | F17: R-134a | G17: R-143a | H17: R-1234ze | I17: R-1234yf
B18: CFC-11 | J18: 6226 | L18: IPCC (2021), AR6 Chapitre 7, table 7.15 (GWP-100)
B19: CFC-12 | J19: 10910 | L19: HRAI (2019) Refrigerant Table Lexplanation and Glossary of Terms - https://www.hrai.ca/uploads/userfiles/files/refrigerant_table_June2019.pdf
B20: R-22 | C20: Ref. and air cond. | J20: 1810 | L20: HRAI (2019) Refrigerant Table Lexplanation and Glossary of Terms - https://www.hrai.ca/uploads/userfiles/files/refrigerant_table_June2019.pdf
B21: R-23 | J21: 14800 | L21: NIR (2022), PT1, tableau A1-1, p.19
B22: R-32 | C22: Air conditioning | J22: 771 | L22: IPCC (2021), AR6 Chapitre 7, table 7.15 (GWP-100)
B23: R-125 | J23: 3500 | L23: NIR (2022), PT1, tableau A1-1, p.19
B24: R-134a | C24: Air conditioning | J24: 1526 | L24: IPCC (2021), AR6 Chapitre 7, table 7.15 (GWP-100)
B25: R-143a | J25: 4470 | L25: NIR (2022), PT1, tableau A1-1, p.19
B26: R-404a | C26: Refrigeration | D26: 0 | E26: 0.44 | F26: 0.04 | G26: 0.52 | H26: 0 | I26: 0 | J26: =D26*$J$22+E26*$J$23+G26*$J$25+F26*$J$24+H26*$J$37+I26*$J$36 -> 3925.44 | L26: HRAI (2019) Refrigerant Table Lexplanation and Glossary of Terms - https://www.hrai.ca/uploads/userfiles/files/refrigerant_table_June2019.pdf
B27: R-407a | C27: Refrigeration | D27: 0.2 | E27: 0.4 | F27: 0.4 | G27: 0 | H27: 0 | I27: 0 | J27: =D27*$J$22+E27*$J$23+G27*$J$25+F27*$J$24+H27*$J$37+I27*$J$36 -> 2164.6 | L27: Chemours (2017) Freon 407C and 407A Properties, Uses, Storage, and Handling. https://www.freon.com/fr/-/media/files/freon/freon-r407c-r407a-push-bulletin.pdf?rev=d1d347da1ed04b9684663ebba7bc6a1f
B28: R-407c | C28: Refrigeration | D28: 0.23 | E28: 0.25 | F28: 0.52 | G28: 0 | H28: 0 | I28: 0 | J28: =D28*$J$22+E28*$J$23+G28*$J$25+F28*$J$24+H28*$J$37+I28*$J$36 -> 1845.85 | L28: HRAI (2019) Refrigerant Table Lexplanation and Glossary of Terms - https://www.hrai.ca/uploads/userfiles/files/refrigerant_table_June2019.pdf
B29: R-410a | C29: Air conditioning | D29: 0.5 | E29: 0.5 | F29: 0 | G29: 0 | H29: 0 | I29: 0 | J29: =D29*$J$22+E29*$J$23+G29*$J$25+F29*$J$24+H29*$J$37+I29*$J$36 -> 2135.5 | L29: HRAI (2019) Refrigerant Table Lexplanation and Glossary of Terms - https://www.hrai.ca/uploads/userfiles/files/refrigerant_table_June2019.pdf
B30: R-448a | C30: Refrigeration | D30: 0.26 | E30: 0.26 | F30: 0.21 | G30: 0 | H30: 0.07 | I30: 0.2 | J30: =D30*$J$22+E30*$J$23+G30*$J$25+F30*$J$24+H30*$J$37+I30*$J$36 -> 1431.72 | L30: HRAI (2019) Refrigerant Table Lexplanation and Glossary of Terms - https://www.hrai.ca/uploads/userfiles/files/refrigerant_table_June2019.pdf
B31: R-449a | C31: Refrigeration | D31: 0.243 | E31: 0.247 | F31: 0.257 | G31: 0 | H31: 0 | I31: 0.053 | J31: =D31*$J$22+E31*$J$23+G31*$J$25+F31*$J$24+H31*$J$37+I31*$J$36 -> 1444.247 | L31: National Refrigerants Inc. - https://refrigerants.com/product/r-449a/
B32: R-454B | C32: Refrigeration | D32: 0.689 | E32: 0 | F32: 0 | G32: 0 | H32: 0 | I32: 0.311 | J32: =D32*$J$22+E32*$J$23+G32*$J$25+F32*$J$24+H32*$J$37+I32*$J$36 -> 532.463 | L32: Climalife (n.-d.) R454B Specifications commerciales garanties. https://climalife.com/fr/product/r-454b/#:~:text=Le%20R%2D454B%20est%20un,est%20g%C3%A9n%C3%A9ralement%20mis%20en%20%C5%93uvre.
B33: R-513a | C33: Refrigeration | D33: 0 | E33: 0 | F33: 0.44 | G33: 0 | H33: 0 | I33: 0.56 | J33: =D33*$J$22+E33*$J$23+G33*$J$25+F33*$J$24+H33*$J$37+I33*$J$36 -> 673.68 | L33: HRAI (2019) Refrigerant Table Lexplanation and Glossary of Terms - https://www.hrai.ca/uploads/userfiles/files/refrigerant_table_June2019.pdf
B34: R-290 | C34: Refrigeration | J34: 3 | L34: Farmacold (n.d.) Réfrigérant R290. https://www.framacold.com/framacold-produit/39-r290-froid-domestique-et-commercial-#:~:text=Le%20propane%20pur%20R290%20est,nombreuses%20applications%20en%20froid%20commercial.&text=De%20tr%C3%A8s%20haute%20puret%C3%A9%20(%3E%2099,classement%20ASHRAE%20A3%20hautement%20inflammable.
B35: R-600a | C35: Refrigeration | J35: 3 | L35: Gasservei (n.d.) R-600a. https://gas-servei.com/fr/producto/r-600a/
B36: R-1234yf | C36: Air conditioning | J36: 4 | L36: HRAI (2019) Refrigerant Table Lexplanation and Glossary of Terms - https://www.hrai.ca/uploads/userfiles/files/refrigerant_table_June2019.pdf
B37: R-1234ze | J37: 0 | L37: HRAI (2019) Refrigerant Table Lexplanation and Glossary of Terms - https://www.hrai.ca/uploads/userfiles/files/refrigerant_table_June2019.pdf
B38: CO2 | C38: Refrigeration | J38: 1 | L38: IPCC (2021), AR6 Chapitre 7, table 7.15 (GWP-100)
B39: NH3 | C39: Refrigeration | J39: 0

Sheet FÉ
B2: Facteurs d'émissions
B6: 1 - Équipements fixes et Chauffage | G6: (Référence E) | H6: (Référence A) | L6: Total | S6: Références
G7: Conversion | H7: Conversion énergie | I7: CO2 | J7: CH4 | K7: N2O | L7: CO2éq | N7: CO2 Biogénique Anthropique | Q7: CO2 Biogénique Anthropique
B8: Liste | C8: Utilisation | D8: Carburant | F8: Unité | G8: [kg/L] | H8: [kWh/L] | I8: [gCO2/unité] | J8: [gCH4/unité] | K8: [gN2O/unité] | L8: [gCO2eq/unité] | N8: [gCO2eq/kg] | Q8: [gCO2eq/kg]
B9: =_xlfn.CONCAT(C9, " - ", D9) -> Chauffage - Gaz naturel [m3] | C9: Chauffage | D9: Gaz naturel [m3] | F9: m3 | H9: 10.53 | I9: 1878 | J9: 0.037 | K9: 0.034 | L9: =I9*PRP!$J$8+J9*PRP!$J$9+K9*PRP!$J$10 -> 1888.3846 | S9: Transition Énergie Québec (2019) Facteurs d'émission et de conversion. https://transitionenergetique.gouv.qc.ca/fileadmin/medias/pdf/FacteursEmission.pdf
B10: =_xlfn.CONCAT(C10, " - ", D10) -> Chauffage - Propane [L] | C10: Chauffage | D10: Propane [L] | F10: L | H10: 7.03 | I10: 1515 | J10: 0.027 | K10: 0.108 | L10: =I10*PRP!$J$8+J10*PRP!$J$9+K10*PRP!$J$10 -> 1545.2886 | S10: NIR2023, PT2, annexe A6, tableau A6.1-4, p.259
B11: =_xlfn.CONCAT(C11, " - ", D11) -> Chauffage - Mazout [L] | C11: Chauffage | D11: Mazout [L] | F11: L | H11: 10.77 | I11: 2753 | J11: 0.006 | K11: 0.031 | L11: =I11*PRP!$J$8+J11*PRP!$J$9+K11*PRP!$J$10 -> 2761.6418 | S11: NIR2023, PT2, annexe A6, tableau A6.1-5, p.260
B12: =_xlfn.CONCAT(C12, " - ", D12) -> Chauffage - Bois [kg] | C12: Chauffage | D12: Bois [kg] | F12: kg | H12: 5.33 | I12: 0 | J12: 0.576 | K12: 0.077 | L12: =J12*PRP!$J$9+K12*PRP!$J$10 -> 38.1858 | N12: 1799 | Q12: 1799 | S12: Transition Énergie Québec (2019) Facteurs d'émission et de conversion. https://transitionenergetique.gouv.qc.ca/fileadmin/medias/pdf/FacteursEmission.pdf
B13: =_xlfn.CONCAT(C13, " - ", D13) -> Génératrice - Essence [L] | C13: Génératrice | D13: Essence [L] | F13: L | H13: 9.69 | I13: =I41 -> 2307.3 | J13: =J41 -> 0.111 | K13: =K41 -> 0.007 | L13: =I13*PRP!$J$8+J13*PRP!$J$9+K13*PRP!$J$10 -> 2312.5188 | S13: =S41 -> NIR2023, PT2, annexe A6, tableau A6.1-14, p.266
B14: =_xlfn.CONCAT(C14, " - ", D14) -> Génératrice - Diesel [L] | C14: Génératrice | D14: Diesel [L] | F14: L | H14: 10.64 | I14: =I51 -> 2680.5 | J14: =J51 -> 0.068 | K14: =K51 -> 0.22 | L14: =I14*PRP!$J$8+J14*PRP!$J$9+K14*PRP!$J$10 -> 2742.5864 | S14: =S51 -> NIR2023, PT2, annexe A6, tableau A6.1-14, p.275
B15: =_xlfn.CONCAT(C15, " - ", D15) -> Génératrice - Mazout [L] | C15: Génératrice | D15: Mazout [L] | F15: L | H15: =H11 -> 10.77 | I15: 2753 | J15: 0.18 | K15: 0.031 | L15: =I15*PRP!$J$8+J15*PRP!$J$9+K15*PRP!$J$10 -> 2766.827 | S15: NIR2023, PT2, annexe A6, tableau A6.1-5, p.260
B16: =_xlfn.CONCAT(C16, " - ", D16) -> Soudure - Acétylène [kg] | C16: Soudure | D16: Acétylène [kg] | F16: kg | I16: =(2*$C$1079/$C$1082)*1000 -> 3380.3672 | L16: =I16*PRP!$J$8+J16*PRP!$J$9+K16*PRP!$J$10 -> 3380.3672 | S16: CNESST, Fiche technique de l'acétylène - https://reptox.cnesst.gouv.qc.ca/pages/fiche-complete.aspx?no_produit=497
B17: =_xlfn.CONCAT(C17, " - ", D17) -> Soudure - Argoshield [kg] | C17: Soudure | D17: Argoshield [kg] | F17: kg | I17: =0.16*E1085*1000 -> 299.2 | L17: =I17*PRP!$J$8+J17*PRP!$J$9+K17*PRP!$J$10 -> 299.2 | S17: Linde, Composition de l'Argoshield - https://www.boc.com.au/shop/en/au/gases/welding-gas-mixtures/argoshield-universal
B18: =_xlfn.CONCAT(C18, " - ", D18) -> Autre - Gaz naturel [m3] | C18: Autre | D18: Gaz naturel [m3] | F18: m3 | H18: =H9 -> 10.53 | I18: 1878 | J18: 0.037 | K18: 0.034 | L18: =I18*PRP!$J$8+J18*PRP!$J$9+K18*PRP!$J$10 -> 1888.3846 | S18: Transition Énergie Québec (2019) Facteurs d'émission et de conversion. https://transitionenergetique.gouv.qc.ca/fileadmin/medias/pdf/FacteursEmission.pdf
B19: =_xlfn.CONCAT(C19, " - ", D19) -> Autre - Propane [L] | C19: Autre | D19: Propane [L] | F19: L | H19: =H10 -> 7.03 | I19: 1515 | J19: 0.024 | K19: 0.108 | L19: =I19*PRP!$J$8+J19*PRP!$J$9+K19*PRP!$J$10 -> 1545.1992 | S19: NIR2023, PT2, annexe A6, tableau A6.1-4, p.259
B20: =_xlfn.CONCAT(C20, " - ", D20) -> Autre - Propane [kg] | C20: Autre | D20: Propane [kg] | F20: kg | G20: 0.5 | H20: =H19/G20 -> 14.06 | I20: =I19/G20 -> 3030 | J20: =J19/G20 -> 0.048 | K20: =K19/G20 -> 0.216 | L20: =I20*PRP!$J$8+J20*PRP!$J$9+K20*PRP!$J$10 -> 3090.3984 | S20: NIR2023, PT2, annexe A6, tableau A6.1-4, p.259
B21: =_xlfn.CONCAT(C21, " - ", D21) -> Autre - Propane [lbs] | C21: Autre | D21: Propane [lbs] | F21: lbs | G21: =0.5*2.20462 -> 1.10231 | H21: =H19/G21 -> 6.3775163 | I21: =I19/G21 -> 1374.3865 | J21: =J19/G21 -> 0.02177246 | K21: =K19/G21 -> 0.097976068 | L21: =I21*PRP!$J$8+J21*PRP!$J$9+K21*PRP!$J$10 -> 1401.7828 | S21: NIR2023, PT2, annexe A6, tableau A6.1-4, p.259
B23: 2 - Intensité énergétique moyenne des bâtiments | L23: Total | S23: Références
E24: Intensité énergétique moyen
B25: Type de bâtiment | E25: [Gj/m2] | F25: [kWh/m2]
B26: Moyenne canadienne | E26: 1.14 | F26: =$C$1071*E26 -> 316.6692 | S26: Statistique Canada. (2016c, 16 septembre). Le Quotidien — Enquête sur la consommation d’énergie des secteurs commercial et institutionnel, 2014. https://www150.statcan.gc.ca/n1/daily-quotidien/160916/dq160916c-fra.htm
B27: Hôpitaux | E27: 2.45 | F27: =$C$1071*E27 -> 680.561 | S27: Statistique Canada. (2016c, 16 septembre). Le Quotidien — Enquête sur la consommation d’énergie des secteurs commercial et institutionnel, 2014. https://www150.statcan.gc.ca/n1/daily-quotidien/160916/dq160916c-fra.htm
B28: Établissements de soins infirmiers | E28: 1.3 | F28: =$C$1071*E28 -> 361.114 | S28: Statistique Canada. (2016c, 16 septembre). Le Quotidien — Enquête sur la consommation d’énergie des secteurs commercial et institutionnel, 2014. https://www150.statcan.gc.ca/n1/daily-quotidien/160916/dq160916c-fra.htm
B29: Immeubles à bureaux (services médicaux) | E29: 1.28 | F29: =$C$1071*E29 -> 355.5584 | S29: Statistique Canada. (2016c, 16 septembre). Le Quotidien — Enquête sur la consommation d’énergie des secteurs commercial et institutionnel, 2014. https://www150.statcan.gc.ca/n1/daily-quotidien/160916/dq160916c-fra.htm
B30: Immeubles à bureaux (services non médicaux) | E30: 1.12 | F30: =$C$1071*E30 -> 311.1136 | S30: Statistique Canada. (2016c, 16 septembre). Le Quotidien — Enquête sur la consommation d’énergie des secteurs commercial et institutionnel, 2014. https://www150.statcan.gc.ca/n1/daily-quotidien/160916/dq160916c-fra.htm
B31: Magasins d'alimentation (sauf les restaurants et les bars) | E31: 1.88 | F31: =$C$1071*E31 -> 522.2264 | S31: Statistique Canada. (2016c, 16 septembre). Le Quotidien — Enquête sur la consommation d’énergie des secteurs commercial et institutionnel, 2014. https://www150.statcan.gc.ca/n1/daily-quotidien/160916/dq160916c-fra.htm
B32: Magasins de détail (sauf les magasins d'alimentation) | E32: 1.12 | F32: =$C$1071*E32 -> 311.1136 | S32: Statistique Canada. (2016c, 16 septembre). Le Quotidien — Enquête sur la consommation d’énergie des secteurs commercial et institutionnel, 2014. https://www150.statcan.gc.ca/n1/daily-quotidien/160916/dq160916c-fra.htm
B33: École primaires ou secondaires | E33: 0.88 | F33: =$C$1071*E33 -> 244.4464 | S33: Statistique Canada. (2016c, 16 septembre). Le Quotidien — Enquête sur la consommation d’énergie des secteurs commercial et institutionnel, 2014. https://www150.statcan.gc.ca/n1/daily-quotidien/160916/dq160916c-fra.htm
B34: Hôtels, motels et/ou auberges | E34: 1.24 | F34: =$C$1071*E34 -> 344.4472 | S34: Statistique Canada. (2016c, 16 septembre). Le Quotidien — Enquête sur la consommation d’énergie des secteurs commercial et institutionnel, 2014. https://www150.statcan.gc.ca/n1/daily-quotidien/160916/dq160916c-fra.htm
B35: Entrepôts | E35: 0.82 | F35: =$C$1071*E35 -> 227.7796 | S35: Statistique Canada. (2016c, 16 septembre). Le Quotidien — Enquête sur la consommation d’énergie des secteurs commercial et institutionnel, 2014. https://www150.statcan.gc.ca/n1/daily-quotidien/160916/dq160916c-fra.htm
B36: Autres activités ou fonctions | E36: 1.19 | F36: =$C$1071*E36 -> 330.5582 | S36: Statistique Canada. (2016c, 16 septembre). Le Quotidien — Enquête sur la consommation d’énergie des secteurs commercial et institutionnel, 2014. https://www150.statcan.gc.ca/n1/daily-quotidien/160916/dq160916c-fra.htm
B38: 3 - Équipements mobiles | G38: (Référence E) | H38: (Référence A) | L38: Total | S38: Références
G39: Conversion | H39: Conversion énergie | I39: CO2 | J39: CH4 | K39: N2O | L39: CO2éq
B40: Liste de type de véhicule | C40: Utilisation | D40: Grosseur | E40: Carburant | F40: Unité | G40: [unité/L] | H40: [kWh/unité] | I40: [gCO2/L] | J40: [gCH4/L] | K40: [gN2O/L] | L40: [gCO2eq/L]
B41: =_xlfn.CONCAT(C41, " ", D41," - ", E41) -> Voiture légère - Essence [L] | C41: Voiture | D41: légère | E41: Essence [L] | F41: L | H41: =$H$13 -> 9.69 | I41: 2307.3 | J41: 0.111 | K41: 0.007 | L41: =I41*PRP!$J$8+J41*PRP!$J$9+K41*PRP!$J$10 -> 2312.5188 | S41: NIR2023, PT2, annexe A6, tableau A6.1-14, p.266
B42: =_xlfn.CONCAT(C42, " ", D42," - ", E42) -> Camion léger - Essence [L] | C42: Camion | D42: léger | E42: Essence [L] | F42: L | H42: =H41 -> 9.69 | I42: 2307.3 | J42: 0.111 | K42: 0.007 | L42: =I42*PRP!$J$8+J42*PRP!$J$9+K42*PRP!$J$10 -> 2312.5188 | S42: NIR2023, PT2, annexe A6, tableau A6.1-14, p.266
B43: =_xlfn.CONCAT(C43, " ", D43," - ", E43) -> Camion lourd - Essence [L] | C43: Camion | D43: lourd | E43: Essence [L] | F43: L | H43: =H41 -> 9.69 | I43: 2307.3 | J43: 0.068 | K43: 0.2 | L43: =I43*PRP!$J$8+J43*PRP!$J$9+K43*PRP!$J$10 -> 2363.9264 | S43: NIR2023, PT2, annexe A6, tableau A6.1-14, p.267
B44: =_xlfn.CONCAT(C44, " ", D44," - ", E44) -> Motocyclette - Essence [L] | C44: Motocyclette | E44: Essence [L] | F44: L | H44: =H41 -> 9.69 | I44: 2307.3 | J44: 0.77 | K44: 0.041 | L44: =I44*PRP!$J$8+J44*PRP!$J$9+K44*PRP!$J$10 -> 2341.439 | S44: NIR2023, PT2, annexe A6, tableau A6.1-14, p.268
B45: =_xlfn.CONCAT(C45, " ", D45," - ", E45) -> Hors route 2 temps - Essence [L] | C45: Hors route | D45: 2 temps | E45: Essence [L] | F45: L | H45: =H41 -> 9.69 | I45: 2307.3 | J45: 10.61 | K45: 0.013 | L45: =I45*PRP!$J$8+J45*PRP!$J$9+K45*PRP!$J$10 -> 2627.027 | S45: NIR2023, PT2, annexe A6, tableau A6.1-14, p.269
B46: =_xlfn.CONCAT(C46, " ", D46," - ", E46) -> Hors route 4 temps - Essence [L] | C46: Hors route | D46: 4 temps | E46: Essence [L] | F46: L | H46: =H41 -> 9.69 | I46: 2307.3 | J46: 5.08 | K46: 0.064 | L46: =I46*PRP!$J$8+J46*PRP!$J$9+K46*PRP!$J$10 -> 2476.156 | S46: NIR2023, PT2, annexe A6, tableau A6.1-14, p.270
B47: =_xlfn.CONCAT(C47, " ", D47," - ", E47) -> Bateau - Essence [L] | C47: Bateau | E47: Essence [L] | F47: L | H47: =$H$41 -> 9.69 | I47: 2307.3 | J47: 0.21931 | K47: 0.06266 | L47: =I47*PRP!$J$8+J47*PRP!$J$9+K47*PRP!$J$10 -> 2330.9416 | S47: NIR2023, PT2, annexe A6, tableau A6.1-14, p.271
B48: =_xlfn.CONCAT(C48, " ", D48," - ", E48) -> Bateau - Diesel [L] | C48: Bateau | E48: Diesel [L] | F48: L | H48: =$H$14 -> 10.64 | I48: 2680.5 | J48: 0.25193 | K48: 0.07198 | L48: =I48*PRP!$J$8+J48*PRP!$J$9+K48*PRP!$J$10 -> 2707.6581 | S48: NIR2023, PT2, annexe A6, tableau A6.1-14, p.272
B49: =_xlfn.CONCAT(C49, " ", D49," - ", E49) -> Bateau Cargo - Mazout [L] | C49: Bateau | D49: Cargo | E49: Mazout [L] | F49: L | H49: =H11 -> 10.77 | I49: 3156 | J49: 0.2856 | K49: 0.0816 | L49: =I49*PRP!$J$8+J49*PRP!$J$9+K49*PRP!$J$10 -> 3186.7877 | S49: NIR2023, PT2, annexe A6, tableau A6.1-14, p.273
B50: =_xlfn.CONCAT(C50, " ", D50," - ", E50) -> Voiture légère - Diesel [L] | C50: Voiture | D50: légère | E50: Diesel [L] | F50: L | H50: =H48 -> 10.64 | I50: 2680.5 | J50: 0.051 | K50: 0.22 | L50: =I50*PRP!$J$8+J50*PRP!$J$9+K50*PRP!$J$10 -> 2742.0798 | S50: NIR2023, PT2, annexe A6, tableau A6.1-14, p.274
B51: =_xlfn.CONCAT(C51, " ", D51," - ", E51) -> Camion léger - Diesel [L] | C51: Camion | D51: léger | E51: Diesel [L] | F51: L | H51: =H48 -> 10.64 | I51: 2680.5 | J51: 0.068 | K51: 0.22 | L51: =I51*PRP!$J$8+J51*PRP!$J$9+K51*PRP!$J$10 -> 2742.5864 | S51: NIR2023, PT2, annexe A6, tableau A6.1-14, p.275
B52: =_xlfn.CONCAT(C52, " ", D52," - ", E52) -> Camion lourd - Diesel [L] | C52: Camion | D52: lourd | E52: Diesel [L] | F52: L | H52: =H48 -> 10.64 | I52: 2680.5 | J52: 0.11 | K52: 0.151 | L52: =I52*PRP!$J$8+J52*PRP!$J$9+K52*PRP!$J$10 -> 2725.001 | S52: NIR2023, PT2, annexe A6, tableau A6.1-14, p.276
B53: =_xlfn.CONCAT(C53, " ", D53," - ", E53) -> Train - Diesel [L] | C53: Train | E53: Diesel [L] | F53: L | H53: =H50 -> 10.64 | I53: 2680.5 | J53: 0.149 | K53: 1.029 | L53: =I53*PRP!$J$8+J53*PRP!$J$9+K53*PRP!$J$10 -> 2965.8572 | S53: NIR2023, PT2, annexe A6, tableau A6.1-14, p.277
B54: =_xlfn.CONCAT(C54, " ", D54," - ", E54) -> Véhicule - Propane [L] | C54: Véhicule | E54: Propane [L] | F54: L | H54: =H10 -> 7.03 | I54: 1515 | J54: 0.64 | K54: 0.028 | L54: =I54*PRP!$J$8+J54*PRP!$J$9+K54*PRP!$J$10 -> 1541.716 | S54: NIR2023, PT2, annexe A6, tableau A6.1-14, p.278
B55: =_xlfn.CONCAT(C55, " ", D55," - ", E55) -> Véhicule - Propane [kg] | C55: Véhicule | E55: Propane [kg] | F55: kg | G55: 0.5 | H55: =H54/G55 -> 14.06 | I55: =I54/G55 -> 3030 | J55: =J54/G55 -> 1.28 | K55: =K54/G55 -> 0.056 | L55: =I55*PRP!$J$8+J55*PRP!$J$9+K55*PRP!$J$10 -> 3083.432 | S55: NIR2023, PT2, annexe A6, tableau A6.1-14, p.278
B56: =_xlfn.CONCAT(C56, " ", D56," - ", E56) -> Véhicule - Propane [lbs] | C56: Véhicule | E56: Propane [lbs] | F56: lbs | G56: =0.5*2.20462 -> 1.10231 | H56: =H54/G56 -> 6.3775163 | I56: =I54/G56 -> 1374.3865 | J56: =J54/G56 -> 0.58059892 | K56: =K54/G56 -> 0.025401203 | L56: =I56*PRP!$J$8+J56*PRP!$J$9+K56*PRP!$J$10 -> 1398.6229 | S56: NIR2023, PT2, annexe A6, tableau A6.1-14, p.278
B57: =_xlfn.CONCAT(C57, " ", D57," - ", E57) -> Véhicule - Électrique [kWh] | C57: Véhicule | E57: Électrique [kWh] | F57: kWh | H57: 1 | I57: =I385 -> 1.3 | J57: 0 | K57: 0 | L57: =I57*PRP!$J$8+J57*PRP!$J$9+K57*PRP!$J$10 -> 1.3
B58: =_xlfn.CONCAT(C58, " ", D58," - ", E58) -> Aviation - Kérosène [L] | C58: Aviation | E58: Kérosène [L] | F58: L | H58: 10.47 | I58: 2559.7 | J58: 0.029 | K58: 0.0711 | L58: =I58*PRP!$J$8+J58*PRP!$J$9+K58*PRP!$J$10 -> 2579.9745 | S58: NIR2023, PT2, annexe A6, tableau A6.1-14, p.266
B59: =_xlfn.CONCAT(C59, " ", D59," - ", E59) -> Aviation - Essence [L] | C59: Aviation | E59: Essence [L] | F59: L | H59: 9.31 | I59: 2325.4 | J59: 2.19 | K59: 0.23 | L59: =I59*PRP!$J$8+J59*PRP!$J$9+K59*PRP!$J$10 -> 2453.452 | S59: NIR2023, PT2, annexe A6, tableau A6.1-14, p.266
B61: 4 - Déplacements par km | H61: (Référence A)
H62: Conversion énergie | I62: CO2 | J62: CH4 | K62: N2O | L62: CO2éq
B63: Liste de moyens de transport | D63: Carburant | E63: [L/100km.passager] | F63: Unité | H63: [kWh/L] | I63: [gCO2/L] | J63: [gCH4/L] | K63: [gN2O/L] | L63: [gCO2eq/L]
B64: Voiture | D64: Essence [L] | E64: 9.7 | F64: L | H64: =$H$13 -> 9.69 | I64: 2307.3 | J64: 0.14 | K64: 0.022 | L64: =I64*PRP!$J$8+J64*PRP!$J$9+K64*PRP!$J$10 -> 2317.478 | S64: Transport Canada, 2014, Niveau d'Aggrégation: Véhicule Ratios. https://tc.canada.ca/fr/services-generaux/politiques/annuel-2014
B65: Véhicule utilitaire sport | D65: Essence [L] | E65: 12.6 | F65: L | H65: =$H$13 -> 9.69 | I65: 2307.3 | J65: 0.14 | K65: 0.022 | L65: =I65*PRP!$J$8+J65*PRP!$J$9+K65*PRP!$J$10 -> 2317.478 | S65: Transport Canada, 2014, Niveau d'Aggrégation: Véhicule Ratios. https://tc.canada.ca/fr/services-generaux/politiques/annuel-2014
B66: Pickup | D66: Essence [L] | E66: 16.3 | F66: L | H66: =$H$13 -> 9.69 | I66: 2307.3 | J66: 0.14 | K66: 0.022 | L66: =I66*PRP!$J$8+J66*PRP!$J$9+K66*PRP!$J$10 -> 2317.478 | S66: Transport Canada, 2014, Niveau d'Aggrégation: Véhicule Ratios. https://tc.canada.ca/fr/services-generaux/politiques/annuel-2014
B67: Voiture électrique | D67: Électrique [kWh] | E67: 18 | F67: kWh | H67: 1 | I67: =$I$385 -> 1.3 | J67: 0 | K67: 0 | L67: =I67*PRP!$J$8+J67*PRP!$J$9+K67*PRP!$J$10 -> 1.3
B68: Moto (600cc) | D68: Essence [L] | E68: 5.5 | F68: L | H68: =$H$13 -> 9.69 | I68: 2307.3 | J68: 0.14 | K68: 0.022 | L68: =I68*PRP!$J$8+J68*PRP!$J$9+K68*PRP!$J$10 -> 2317.478 | S68: Les furets (2022),Consommation d'essence d'une moto : ces gestes qui augmentent les dépenses - https://www.lesfurets.com/assurance-moto/guide/les-astuces-pour-diminuer-votre-consommation-de-carburant-a-moto
B69: Mobilette (125cc) | D69: Essence [L] | E69: 2.75 | F69: L | H69: =$H$13 -> 9.69 | I69: 2307.3 | J69: 0.14 | K69: 0.022 | L69: =I69*PRP!$J$8+J69*PRP!$J$9+K69*PRP!$J$10 -> 2317.478 | S69: Les furets (2022),Consommation d'essence d'une moto : ces gestes qui augmentent les dépenses - https://www.lesfurets.com/assurance-moto/guide/les-astuces-pour-diminuer-votre-consommation-de-carburant-a-moto
B70: Covoiturage | C70: (Valeur de la Voiture divisée par 2) | D70: Essence [L] | E70: =9.5/2 -> 4.75 | F70: L | H70: =$H$13 -> 9.69 | I70: 2307.3 | J70: 0.14 | K70: 0.022 | L70: =I70*PRP!$J$8+J70*PRP!$J$9+K70*PRP!$J$10 -> 2317.478
B71: Autobus | D71: Diesel [L] | E71: =E328*100 -> 2.4433019 | F71: L | H71: =$H$14 -> 10.64 | I71: =$E$328*I52 -> 65.492706 | J71: =$E$328*J52 -> 0.002687632 | K71: =$E$328*K52 -> 0.0036893858 | L71: =I71*PRP!$J$8+J71*PRP!$J$9+K71*PRP!$J$10 -> 66.58 | S71: Greenhouse Gas Protocole, Caculation Tools, version 2.6, 2015
B72: Autres transports en commun | E72: 0
B73: Marche ou vélo | E73: 0
B74: Télétravail | E74: 0
B76: 5 - Transports de passagers | L76: Total | S76: Références
H77: Conversion énergie | I77: CO2 | J77: CH4 | K77: N2O | L77: CO2éq
B78: Type | D78: Carburant | E78: [Litre / km.passager] | F78: km.passager en 2024 | G78: Carburant total 2024 | H78: [kWh/L] | I78: [gCO2/km.passager] | J78: [gCH4/km.passager] | K78: [gN2O/km.passager] | L78: [gCO2eq/km.passager]
B79: Intercity Rail | C79: (US) | D79: Diesel [L] | E79: =L79/$L$52 -> 0.033092713 | H79: =$H$14 -> 10.64 | I79: =144/$C$1070 -> 89.477452 | J79: =0.0085/$C$1070 -> 0.0052816551 | K79: =0.0032/$C$1070 -> 0.0019883878 | L79: =I79*PRP!$J$8+J79*PRP!$J$9+K79*PRP!$J$10 -> 90.177675 | S79: Emission Factors for Greenhouse Gas Inventories, US EPA, 2014 - https://www.epa.gov/sites/default/files/2015-07/documents/emission-factors_2014.pdf
B80: Train voyageur | C80: VIA RAIL | D80: Diesel [L] | E80: =G80/F80 -> 0.070032706 | F80: =(967000000)*1.60934 -> 1556231780 | G80: =194651000/1.786 -> 1.0898712e+08 | H80: =$H$14 -> 10.64 | I80: =$E80*I53 -> 187.72267 | J80: =$E80*J53 -> 0.010434873 | K80: =$E80*K53 -> 0.072063654 | L80: =I80*PRP!$J$8+J80*PRP!$J$9+K80*PRP!$J$10 -> 207.707 | S80: VIA-RAIL Rapport Annuel 2024 (VIA-RAIL, 2025) - https://media.viarail.ca/sites/default/files/publications/VIA-Rail_Rapport-Annuel_2024.pdf
B81: Commuter rail | C81: (US) | D81: Diesel [L] | E81: =L81/$L$52 -> 0.03995149 | H81: =$H$14 -> 10.64 | I81: =174/$C$1070 -> 108.11859 | J81: =0.0084/$C$1070 -> 0.005219518 | K81: =0.0035/$C$1070 -> 0.0021747992 | L81: =I81*PRP!$J$8+J81*PRP!$J$9+K81*PRP!$J$10 -> 108.86785 | S81: Emission Factors for Greenhouse Gas Inventories, US EPA, 2014 - https://www.epa.gov/sites/default/files/2015-07/documents/emission-factors_2014.pdf
B82: Transit - Subway / tram | C82: (US) | D82: Électrique [kWh] | I82: =133/$C$1070 -> 82.642369 | J82: =0.0026/$C$1070 -> 0.0016155651 | K82: =0.002/$C$1070 -> 0.0012427424 | L82: =I82*PRP!$J$8+J82*PRP!$J$9+K82*PRP!$J$10 -> 83.029781 | S82: Emission Factors for Greenhouse Gas Inventories, US EPA, 2014 - https://www.epa.gov/sites/default/files/2015-07/documents/emission-factors_2014.pdf
B83: Autobus | C83: (US) | D83: Diesel [L] | E83: =L83/$L$52 -> 0.013255167 | H83: =$H$14 -> 10.64 | I83: =58/$C$1070 -> 36.039529 | J83: =0.0007/$C$1070 -> 0.00043495983 | K83: =0.0004/$C$1070 -> 0.00024854848 | L83: =I83*PRP!$J$8+J83*PRP!$J$9+K83*PRP!$J$10 -> 36.120345 | S83: Emission Factors for Greenhouse Gas Inventories, US EPA, 2014 - https://www.epa.gov/sites/default/files/2015-07/documents/emission-factors_2014.pdf
D85: Distance min | E85: Distance max | I85: CO2 | J85: CH4 | K85: N2O | L85: CO2éq
B86: Type | D86: [km] | E86: [km] | I86: [gCO2/km.passager] | J86: [gCH4/km.passager] | K86: [gN2O/km.passager] | L86: [gCO2eq/km.passager]
B87: Avion | C87: (US) | D87: 0 | E87: =300*$C$1070 -> 482.8032 | I87: =275/$C$1070 -> 170.87708 | J87: =0.0091/$C$1070 -> 0.0056544778 | K87: =0.0087/$C$1070 -> 0.0054059294 | L87: =I87*PRP!$J$8+J87*PRP!$J$9+K87*PRP!$J$10 -> 172.5214 | S87: Emission Factors for Greenhouse Gas Inventories, US EPA, 2014 - https://www.epa.gov/sites/default/files/2015-07/documents/emission-factors_2014.pdf
C88: (US) | D88: =300*$C$1070 -> 482.8032 | E88: =2300*$C$1070 -> 3701.4912 | I88: =162/$C$1070 -> 100.66213 | J88: =0.0008/$C$1070 -> 0.00049709695 | K88: =0.0052/$C$1070 -> 0.0032311302 | L88: =I88*PRP!$J$8+J88*PRP!$J$9+K88*PRP!$J$10 -> 101.55905 | S88: Emission Factors for Greenhouse Gas Inventories, US EPA, 2014 - https://www.epa.gov/sites/default/files/2015-07/documents/emission-factors_2014.pdf
C89: (US) | D89: =2300*$C$1070 -> 3701.4912 | E89: et plus | I89: =191/$C$1070 -> 118.6819 | J89: =0.0008/$C$1070 -> 0.00049709695 | K89: =0.006/$C$1070 -> 0.0037282272 | L89: =I89*PRP!$J$8+J89*PRP!$J$9+K89*PRP!$J$10 -> 119.71452 | S89: Emission Factors for Greenhouse Gas Inventories, US EPA, 2014 - https://www.epa.gov/sites/default/files/2015-07/documents/emission-factors_2014.pdf
D91: Distance | H91: Conversion énergie | I91: CO2 | J91: CH4 | K91: N2O | L91: CO2éq | N91: CO2 | O91: CH4 | P91: N2O
B92: Type | C92: Traverse | D92: [km] | E92: Carburant | H92: [kWh/L] | I92: [gCO2/traverse.passager] | J92: [gCH4/traverse.passager] | K92: [gN2O/traverse.passager] | L92: [gCO2eq/traverse.passager] | N92: [gCO2/traverse.véhicule] | O92: [gCH4/traverse.véhicule] | P92: [gN2O/traverse.véhicule] | Q92: [gCO2eq/traverse.véhicule]
B93: Traversier | C93: Sorel-Tracy @ Saint-Ignace-de-Loyola | D93: 1.8 | E93: Mazout [L] | H93: =$H$49 -> 10.77 | I93: =$L93*I$49/$L$49 -> 416.5761 | J93: =$L93*J$49/$L$49 -> 0.037697761 | K93: =$L93*K$49/$L$49 -> 0.010770789 | L93: =$L$107*D93 -> 420.63991 | N93: =$Q93*I$49/$L$49 -> 1562.1604 | O93: =$Q93*J$49/$L$49 -> 0.1413666 | P93: =$Q93*K$49/$L$49 -> 0.040390458 | Q93: =$Q$107*$D93 -> 1577.3997 | S93: Facteurs calculés à partir de : STQ (2023) Rapport annuel de gestion 2022-2023, page 13, 23 et 77. + Régie de l'énergie (2023) Mazout Léger - Relevé Hebdomadaire des prix.
C94: Québec @ Lévis | D94: 1.1 | E94: Mazout [L] | H94: =$H$49 -> 10.77 | I94: =$L94*I$49/$L$49 -> 254.57428 | J94: =$L94*J$49/$L$49 -> 0.02303752 | K94: =$L94*K$49/$L$49 -> 0.0065821487 | L94: =$L$107*D94 -> 257.05773 | N94: =$Q94*I$49/$L$49 -> 954.65355 | O94: =$Q94*J$49/$L$49 -> 0.086390702 | P94: =$Q94*K$49/$L$49 -> 0.024683058 | Q94: =$Q$107*$D94 -> 963.96647 | S94: Facteurs calculés à partir de : STQ (2023) Rapport annuel de gestion 2022-2023, page 13, 23 et 77. + Régie de l'énergie (2023) Mazout Léger - Relevé Hebdomadaire des prix.
C95: L'Isle-aux-Grues @ Montmagny | D95: 8.6 | E95: Mazout [L] | H95: =$H$49 -> 10.77 | I95: =$L95*I$49/$L$49 -> 1990.308 | J95: =$L95*J$49/$L$49 -> 0.18011152 | K95: =$L95*K$49/$L$49 -> 0.051460435 | L95: =$L$107*D95 -> 2009.724 | N95: =$Q95*I$49/$L$49 -> 7463.6551 | O95: =$Q95*J$49/$L$49 -> 0.67541821 | P95: =$Q95*K$49/$L$49 -> 0.19297663 | Q95: =$Q$107*$D95 -> 7536.4651 | S95: Facteurs calculés à partir de : STQ (2023) Rapport annuel de gestion 2022-2023, page 13, 23 et 77. + Régie de l'énergie (2023) Mazout Léger - Relevé Hebdomadaire des prix.
C96: L'Isle-aux-Coudes @ Saint-Joseph-de-la-Rive | D96: 4.1 | E96: Mazout [L] | H96: =$H$49 -> 10.77 | I96: =$L96*I$49/$L$49 -> 948.86777 | J96: =$L96*J$49/$L$49 -> 0.085867122 | K96: =$L96*K$49/$L$49 -> 0.024533463 | L96: =$L$107*D96 -> 958.12425 | N96: =$Q96*I$49/$L$49 -> 3558.2542 | O96: =$Q96*J$49/$L$49 -> 0.32200171 | P96: =$Q96*K$49/$L$49 -> 0.092000488 | Q96: =$Q$107*$D96 -> 3592.9659 | S96: Facteurs calculés à partir de : STQ (2023) Rapport annuel de gestion 2022-2023, page 13, 23 et 77. + Régie de l'énergie (2023) Mazout Léger - Relevé Hebdomadaire des prix.
C97: Tadoussac @ Baie-Sainte-Catherine | D97: 1.5 | E97: Mazout [L] | H97: =$H$49 -> 10.77 | I97: =$L97*I$49/$L$49 -> 347.14675 | J97: =$L97*J$49/$L$49 -> 0.031414801 | K97: =$L97*K$49/$L$49 -> 0.0089756573 | L97: =$L$107*D97 -> 350.53326 | N97: =$Q97*I$49/$L$49 -> 1301.8003 | O97: =$Q97*J$49/$L$49 -> 0.1178055 | P97: =$Q97*K$49/$L$49 -> 0.033658715 | Q97: =$Q$107*$D97 -> 1314.4997 | S97: Facteurs calculés à partir de : STQ (2023) Rapport annuel de gestion 2022-2023, page 13, 23 et 77. + Régie de l'énergie (2023) Mazout Léger - Relevé Hebdomadaire des prix.
C98: L'Île-Verte | D98: 5 | E98: Mazout [L] | H98: =$H$49 -> 10.77 | I98: =$L98*I$49/$L$49 -> 1157.1558 | J98: =$L98*J$49/$L$49 -> 0.104716 | K98: =$L98*K$49/$L$49 -> 0.029918858 | L98: =$L$107*D98 -> 1168.4442 | N98: =$Q98*I$49/$L$49 -> 4339.3343 | O98: =$Q98*J$49/$L$49 -> 0.39268501 | P98: =$Q98*K$49/$L$49 -> 0.11219572 | Q98: =$Q$107*$D98 -> 4381.6658 | S98: Facteurs calculés à partir de : STQ (2023) Rapport annuel de gestion 2022-2023, page 13, 23 et 77. + Régie de l'énergie (2023) Mazout Léger - Relevé Hebdomadaire des prix.
C99: Matane @ Baie-Comeau | D99: 60.6 | E99: Mazout [L] | H99: =$H$49 -> 10.77 | I99: =$L99*I$49/$L$49 -> 14024.729 | J99: =$L99*J$49/$L$49 -> 1.2691579 | K99: =$L99*K$49/$L$49 -> 0.36261656 | L99: =$L$107*D99 -> 14161.544 | N99: =$Q99*I$49/$L$49 -> 52592.732 | O99: =$Q99*J$49/$L$49 -> 4.7593423 | P99: =$Q99*K$49/$L$49 -> 1.3598121 | Q99: =$Q$107*$D99 -> 53105.789 | S99: Facteurs calculés à partir de : STQ (2023) Rapport annuel de gestion 2022-2023, page 13, 23 et 77. + Régie de l'énergie (2023) Mazout Léger - Relevé Hebdomadaire des prix.
C100: Matane @ Godbout | D100: 53.7 | E100: Mazout [L] | H100: =$H$49 -> 10.77 | I100: =$L100*I$49/$L$49 -> 12427.854 | J100: =$L100*J$49/$L$49 -> 1.1246499 | K100: =$L100*K$49/$L$49 -> 0.32132853 | L100: =$L$107*D100 -> 12549.091 | N100: =$Q100*I$49/$L$49 -> 46604.451 | O100: =$Q100*J$49/$L$49 -> 4.217437 | P100: =$Q100*K$49/$L$49 -> 1.204982 | Q100: =$Q$107*$D100 -> 47059.09 | S100: Facteurs calculés à partir de : STQ (2023) Rapport annuel de gestion 2022-2023, page 13, 23 et 77. + Régie de l'énergie (2023) Mazout Léger - Relevé Hebdomadaire des prix.
C101: Harrington Harbour @ Chevery | D101: 11.8 | E101: Mazout [L] | H101: =$H$49 -> 10.77 | I101: =$L101*I$49/$L$49 -> 2730.8877 | J101: =$L101*J$49/$L$49 -> 0.24712977 | K101: =$L101*K$49/$L$49 -> 0.070608504 | L101: =$L$107*D101 -> 2757.5283 | N101: =$Q101*I$49/$L$49 -> 10240.829 | O101: =$Q101*J$49/$L$49 -> 0.92673662 | P101: =$Q101*K$49/$L$49 -> 0.26478189 | Q101: =$Q$107*$D101 -> 10340.731 | S101: Facteurs calculés à partir de : STQ (2023) Rapport annuel de gestion 2022-2023, page 13, 23 et 77. + Régie de l'énergie (2023) Mazout Léger - Relevé Hebdomadaire des prix.
C102: Pakuashipi @ Saint-Augustin | D102: 1 | E102: Mazout [L] | H102: =$H$49 -> 10.77 | I102: =$L102*I$49/$L$49 -> 231.43116 | J102: =$L102*J$49/$L$49 -> 0.0209432 | K102: =$L102*K$49/$L$49 -> 0.0059837716 | L102: =$L$107*D102 -> 233.68884 | N102: =$Q102*I$49/$L$49 -> 867.86687 | O102: =$Q102*J$49/$L$49 -> 0.078537002 | P102: =$Q102*K$49/$L$49 -> 0.022439143 | Q102: =$Q$107*$D102 -> 876.33316 | S102: Facteurs calculés à partir de : STQ (2023) Rapport annuel de gestion 2022-2023, page 13, 23 et 77. + Régie de l'énergie (2023) Mazout Léger - Relevé Hebdomadaire des prix.
C103: Souris (Î-P-É) @ Cap-aux-Meules (Îles de la Madeleine) | D103: 148 | E103: Mazout [L] | H103: =$H$49 -> 10.77 | I103: =$L103*I$49/$L$49 -> 34251.812 | J103: =$L103*J$49/$L$49 -> 3.0995937 | K103: =$L103*K$49/$L$49 -> 0.88559819 | L103: =$L$107*D103 -> 34585.949 | N103: =$Q103*I$49/$L$49 -> 128444.3 | O103: =$Q103*J$49/$L$49 -> 11.623476 | P103: =$Q103*K$49/$L$49 -> 3.3209932 | Q103: =$Q$107*$D103 -> 129697.31 | S103: Facteurs calculés à partir de : STQ (2023) Rapport annuel de gestion 2022-2023, page 13, 23 et 77. + Régie de l'énergie (2023) Mazout Léger - Relevé Hebdomadaire des prix.
C104: Rivière-du-Loup @ Saint-Siméon | D104: 26.2 | E104: Mazout [L] | H104: =$H$49 -> 10.77 | I104: =$L104*I$49/$L$49 -> 6063.4965 | J104: =$L104*J$49/$L$49 -> 0.54871185 | K104: =$L104*K$49/$L$49 -> 0.15677481 | L104: =$L$107*$D104 -> 6122.6476 | N104: =$Q104*I$49/$L$49 -> 22738.112 | O104: =$Q104*J$49/$L$49 -> 2.0576694 | P104: =$Q104*K$49/$L$49 -> 0.58790556 | Q104: =$Q$107*$D104 -> 22959.929 | S104: Facteurs calculés à partir de : STQ (2023) Rapport annuel de gestion 2022-2023, page 13, 23 et 77. + Régie de l'énergie (2023) Mazout Léger - Relevé Hebdomadaire des prix.
I106: [gCO2/km.passager] | J106: [gCH4/km.passager] | K106: [gN2O/km.passager] | L106: [gCO2eq/km.passager] | N106: [gCO2/km.véhicule] | O106: [gCH4/km.véhicule] | P106: [gN2O/km.véhicule] | Q106: [gCO2eq/km.véhicule]
C107: Autres | E107: Mazout [L] | H107: =$H$49 -> 10.77 | I107: =$L$107*I49/$L$49 -> 231.43116 | J107: =$L$107*J49/$L$49 -> 0.0209432 | K107: =$L$107*K49/$L$49 -> 0.0059837716 | L107: 233.68884 | N107: =$Q$107*I49/$L$49 -> 867.86687 | O107: =$Q$107*J49/$L$49 -> 0.078537002 | P107: =$Q$107*K49/$L$49 -> 0.022439143 | Q107: 876.33316 | S107: Facteurs calculés à partir de : STQ (2023) Rapport annuel de gestion 2022-2023, page 13, 23 et 77. + Régie de l'énergie (2023) Mazout Léger - Relevé Hebdomadaire des prix.
B110: 5.3 - Bateau de Croisière | L110: Total | S110: Références
D111: Consommation par personne | G111: Conversion | H111: Conversion énergie | I111: CO2 | J111: CH4 | K111: N2O | L111: CO2éq | O111: Nombre de passager | P111: Tonnage du navire | Q111: Consommation par jour
B112: Type | C112: Nom du bateau de croisière | D112: [L/jour.passager] | E112: Carburant | F112: Unité | G112: [kg/L] | H112: [kWh/L] | I112: [gCO2/jour.passager] | J112: [gCH4/jour.passager] | K112: [gN2O/jour.passager] | L112: [gCO2eq/jour.passager] | O112: [passager] | P112: [tonnage] | Q112: [L/jour]
B113: Bateau de croisière | C113: Azamara Journey | D113: =Q113/O113 -> 121.60348 | E113: Mazout [L] | F113: L | G113: 0.89013 | H113: =$H$49 -> 10.77 | I113: =$D113*I$49 -> 383780.57 | J113: =$D113*J$49 -> 34.729953 | K113: =$D113*K$49 -> 9.9228436 | L113: =I113*PRP!$J$8+J113*PRP!$J$9+K113*PRP!$J$10 -> 387524.46 | O113: 710 | P113: 30277 | Q113: =(16.904 + 0.00198*P113 )*1000/G113 -> 86338.467 | S113: Star Croisière (consulté le 13 juin 2024) Capacité en nombre de passager. https://www.starcroisieres.com/bateaux-de-croisiere + IPCC Volume 2, Chapitre 3, Tableau 3.5.6. https://www.ipcc-nggip.iges.or.jp/public/2006gl/french/pdf/2_Volume2/V2_3_Ch3_Mobile_Combustion.pdf + Conversion de Tonnes de mazout en litres (consulté le 13 juin 2024). https://www.thecalculatorsite.com/conversions/common/liters-to-metric-tons.php
...

Sheet Listes déroulantes FÉ
B2: Listes déroulantes des FÉ
B4: Tableau 1 | C4: Tableau 2 | D4: Tableau 3 | E4: Tableau 4 | F4: Tableau 5 | G4: Tableau 5.3 | H4: Tableau 6 | I4: Tableau 7 | K4: Tableau 8 | M4: Tableau 20
B5: Équipements_fixes | C5: Intensité_type_bâtiments | D5: Équipements_mobiles | E5: Moyennes_de_transport | I5: Type de réfrigérant | J5: Type d'équipement | K5: Réseaux électrique | M5: Aliments | N5: Repas et boisson
B6: {=_xlfn.UNIQUE(Équipements_fixes)} -> Chauffage - Gaz naturel [m3] | C6: {=_xlfn.UNIQUE(Intensité_type_bâtiments)} -> Moyenne canadienne | D6: {=_xlfn.UNIQUE(Équipements_mobiles)} -> Voiture légère - Essence [L] | E6: {=_xlfn.UNIQUE(Moyennes_de_transport)} -> Voiture | I6: {=_xlfn.UNIQUE(FÉ!B365:B380)} -> CFC-12 | J6: {=_xlfn.UNIQUE(FÉ!C367:C372)} -> Climatisation commerciale/industrielle | K6: {=_xlfn.UNIQUE(Grid)} -> Québec | M6: {=_xlfn.UNIQUE(FÉ!C762:C799)} -> Bœuf (Troupeau de bœuf) | N6: {=_xlfn.UNIQUE(FÉ!C801:C814)} -> Repas végétalien
B7: Chauffage - Propane [L] | C7: Hôpitaux | D7: Camion léger - Essence [L] | E7: Véhicule utilitaire sport | I7: R-22 | J7: Réfrigération - Commerciale / industriel | K7: Québec (Îles de la Madeleine) | M7: Chocolat noir | N7: Repas végétarien
B8: Chauffage - Mazout [L] | C8: Établissements de soins infirmiers | D8: Camion lourd - Essence [L] | E8: Pickup | I8: R-32 | J8: Climatisation - Résidentiel | K8: Ontario | M8: Agneau et Mouton | N8: Repas avec du poisson gras
B9: Chauffage - Bois [kg] | C9: Immeubles à bureaux (services médicaux) | D9: Motocyclette - Essence [L] | E9: Voiture électrique | I9: R-134a | J9: Réfrigération - Résidentiel | K9: Terre-Neuve Labrador | M9: Bœuf (Troupeau laitier) | N9: Repas avec du poulet
B10: Génératrice - Essence [L] | C10: Immeubles à bureaux (services non médicaux) | D10: Hors route 2 temps - Essence [L] | E10: Moto (600cc) | I10: R-404a | J10: Réfrigération - Transport commercial | K10: Nouvelle Écosse | M10: Crevettes (d'élevage) | N10: Repas avec du poisson blanc
B11: Génératrice - Diesel [L] | C11: Magasins d'alimentation (sauf les restaurants et les bars) | D11: Hors route 4 temps - Essence [L] | E11: Mobilette (125cc) | I11: R-407a | J11: Climatisation - Automobile | K11: Nouveau Brunswick | M11: Fromage | N11: Repas avec du bœuf
B12: Génératrice - Mazout [L] | C12: Magasins de détail (sauf les magasins d'alimentation) | D12: Bateau - Essence [L] | E12: Covoiturage | I12: R-407c | K12: île du Prince Édouard | M12: Poisson (d'élevage) | N12: Thé (Par portion)
B13: Soudure - Acétylène [kg] | C13: École primaires ou secondaires | D13: Bateau - Diesel [L] | E13: Autobus | I13: R-410a | K13: Manitoba | M13: Viande de volailles | N13: Bouteille d'eau
B14: Soudure - Argoshield [kg] | C14: Hôtels, motels et/ou auberges | D14: Bateau Cargo - Mazout [L] | E14: Autres transports en commun | I14: R-448a | K14: Saskatchewan | M14: Œufs | N14: Boisson au soja (Par portion)
B15: Autre - Gaz naturel [m3] | C15: Entrepôts | D15: Voiture légère - Diesel [L] | E15: Marche ou vélo | I15: R-449a | K15: Alberta | M15: Riz | N15: Soda (Par portion)
B16: Autre - Propane [L] | C16: Autres activités ou fonctions | D16: Camion léger - Diesel [L] | E16: Télétravail | I16: R-454B | K16: Colombie-Britanique | M16: Arachides | N16: Café (Par portion)
B17: Autre - Propane [kg] | D17: Camion lourd - Diesel [L] | I17: R-513a | K17: Yukon | M17: Sucre de canne | N17: Bière (Par portion)
B18: Autre - Propane [lbs] | D18: Train - Diesel [L] | I18: R-290 | K18: Territoires du Nord-Ouest | M18: Tofu | N18: Lait de vache (Par portion)
D19: Véhicule - Propane [L] | I19: R-600a | K19: Nunavut | M19: Lait | N19: Vin (Par portion)
D20: Véhicule - Propane [kg] | I20: CO2 | K20: États-Unis (Moyenne) | M20: Café
D21: Véhicule - Propane [lbs] | I21: NH3 | K21: États-Unis - ASCC Alaska Grid | M21: Avoine
D22: Véhicule - Électrique [kWh] | K22: États-Unis - ASCC Miscellaneous | M22: Tomates
D23: Aviation - Kérosène [L] | K23: États-Unis - WECC Southwest | M23: Sucre de bettraves
D24: Aviation - Essence [L] | K24: États-Unis - WECC California | M24: Autres légumineuses
K25: États-Unis - ERCOT All | M25: Vin
K26: États-Unis - FRCC All | M26: Maïs
K27: États-Unis - HICC Miscellaneous | M27: Blé et seigle
K28: États-Unis - HICC Oahu | M28: Raisins et baies
K29: États-Unis - MRO East | M29: Manioc
K30: États-Unis - MRO West | M30: Porc
K31: États-Unis - NPCC New England | M31: Orge
K32: États-Unis - WECC Northwest | M32: Autres fruits
K33: États-Unis - NPCC NYC/Westchester | M33: Pois vert
K34: États-Unis - NPCC Long Island | M34: Lait de soya
K35: États-Unis - NPCC Upstate NY | M35: Bananes
K36: États-Unis - Puerto Rico Miscellaneous | M36: Autres légumes
... K43: États-Unis - SERC Mississippi Valley | M43: Agrumes
K44: États-Unis - SERC Midwest
K45: États-Unis - SERC South
K46: États-Unis - SERC Tennessee Valley
K47: États-Unis - SERC Virginia/Carolina
K48: Australie
K49: Azerbaïdjan
K50: Bangladesh
K51: Chine
K52: Inde
K53: Indonésie
K54: Mexique
K55: Pakistan
... K58: Taiwan

Sheet Listes déroulantes, autres
B2: Autres listes déroulantes
A4: Code : | B4: =_xlfn.CONCAT("=liste ",B8,"_""_",B9,"_""_",B10,"_""_",B11,"_""_",B12) -> =liste État d'inventaire_"_N/A_"_À ajouter_"_Complet_"_À améliorer
B5: Dashboard ISO14069 | D5: Données sur les véhicules canadiens | H5: Mois | J5: Mode de transport
D6: Utilisé dans : 2B1, ____
A8: Base du code front-end : | B8: État d'inventaire | C8: Oui_Non | D8: Année | E8: Marque | F8: Modèle | G8: Transmission
B9: N/A | C9: Oui | D9: 1995 | E9: Acura | F9: Integra | G9: Automatique | H9: Janvier | I9: 1 | J9: Avion
B10: À ajouter | C10: Non | D10: 1996 | E10: Alfa Romeo | F10: Integra GS-R | G10: Manuel | H10: Février | I10: 2 | J10: Train
B11: Complet | D11: 1997 | E11: Audi | F11: Legend | H11: Mars | I11: 3 | J11: Bus
B12: À améliorer | D12: 1998 | E12: Bentley | F12: Legend Coupe | H12: Avril | I12: 4
D13: 1999 | E13: BMW | F13: NSX | H13: Mai | I13: 5
D14: 2000 | E14: Buick | F14: 164 LS | H14: Juin | I14: 6
D15: 2001 | E15: Cadillac | F15: 90 | H15: Juillet | I15: 7
D16: 2002 | E16: Chevrolet | F16: 90 quattro | H16: Août | I16: 8
D17: 2003 | E17: Chrysler | F17: A6 | H17: Septembre | I17: 9
D18: 2004 | E18: Dodge | F18: A6 quattro | H18: Octobre | I18: 10
D19: 2005 | E19: Eagle | F19: A6 Wagon | H19: Novembre | I19: 11
D20: 2006 | E20: Ferrari | F20: A6 quattro Wagon | H20: Décembre | I20: 12
D21: 2007 | E21: Ford | F21: Cabriolet | H21: Tous | I21: =""
D22: 2008 | E22: Geo | F22: S6
D23: 2009 | E23: GMC | F23: Brooklands
D24: 2010 | E24: Honda | F24: Brooklands LWB
D25: 2011 | E25: Hyundai | F25: Continental
D26: 2012 | E26: Infiniti | F26: Continental Turbo
D27: 2013 | E27: Isuzu | F27: Continental R Turbo
D28: 2014 | E28: Jaguar | F28: Limousine
D29: 2015 | E29: Jeep | F29: Turbo R
D30: 2016 | E30: Land Rover | F30: Turbo RL
D31: 2017 | E31: Lexus | F31: 318i/318is
D32: 2018 | E32: Lincoln | F32: 318i Convertible
D33: 2019 | E33: Mazda | F33: 318ti
... D38: 2024 | E38: Plymouth | F38: 530i
E39: Pontiac | F39: 530i Touring Wagon
E40: Porsche | F40: 540i
E41: Rolls-Royce | F41: 740i
E42: Saab | F42: 740il
E43: Saturn | F43: 750il
E44: Subaru | F44: 840ci
E45: Suzuki | F45: 850ci
E46: Toyota | F46: Century
E47: Volkswagen | F47: Century Wagon
E48: Volvo | F48: LeSabre
E49: Daewoo | F49: Park Avenue
E50: Kia | F50: Park Avenue #
... E71: VinFast | F71: C1500 Suburban
F72: C2500
F73: C2500 Diesel
F74: C2500 Turbo Diesel
F75: Camaro
F76: Caprice
F77: Caprice Wagon
F78: Cavalier
F79: Corsica
F80: Corvette
F81: Corvette #
F82: G10/G20 Van
F83: G10/G20 Van Diesel
... F252: Town Car
F253: 323
F254: 323 #
F255: 323 S
F256: 626
F257: 929 Serenia #
F258: B2300
F259: B2300 4X4
F260: B3000
F261: B3000 4X4
F262: Millenia
F263: MPV 2.6L
F264: MPV 3.0L
F265: MPV 3.0L 4X4
F266: MX-3 Precidia #
F267: MX-3 Precidia
F268: MX-5 Miata #
... F339: Trans Sport
F340: 968
F341: 911 Carrera
F342: 911 Carrera 4
F343: 928 GTS
F344: Corniche IV
F345: Corniche S Turbo
F346: Flying Spur Turbo
F347: Silver Dawn
F348: Silver Spirit III
F349: Silver Spur III
F350: Silver Spur III Limousine
F351: 900 S
F352: 900 S Turbo
... F421: 850 4-valve Wagon
F422: 940
F423: 940 Wagon
F424: 940 Turbo
F425: 940 Turbo Wagon
F426: 960
F427: 960 Wagon
F428: 2.5TL
F429: 3.2TL
F430: 3.5RL
F431: A4
F432: A4 quattro
F433: Azure Turbo
...

Sheet Liste Métho par client
C2: Client
B3: # de méthode | C3: Cégep Gaspésie
B4: 1.1A1 | C4: Oui
B5: 1.1A2
B6: 1.2A1
B7: 1.2A2 | C7: Oui
B8: 1.2A3
B9: 1.2B1
B10: 1.3A1
B11: 1.3B1
B12: 1.3B2
B13: 1.3C1
B14: 1.3D1
B15: 1.4A1 | C15: Oui
B16: 1.4A2
B17: 1.4B1
B18: 1.4B2 | C18: Oui
B19: 1.4C1
B20: 1.4D1
B21: 1.4D2
B22: 1.4E1
B23: 1.5A1
B24: 1.5B1
B25: 1.5B2
B26: 1.5C1
B27: 1.5C2
B28: 2.1A1 | C28: Oui
B29: 2.1A2
B30: 2.1B1
B31: 2.2A1
B32: 2.2A2 | C32: Oui
B33: 2.2A3
B34: 2.2B1
B35: 3.1A1
B36: 3.1A2
B37: 3.2A1
B38: 3.2B1
B39: 3.3A1 | C39: Oui
B40: 3.3A2 | C40: Oui
B41: 3.3A3
B42: 3.3B1
B43: 3.3B2
B44: 3.4A1 | C44: Oui
B45: 3.4A2
B46: 3.4A3
B47: 3.4B1 | C47: Oui
B48: 3.5A1 | C48: Oui
B49: 3.5A2
B50: 3.5A3
B51: 3.5B1 | C51: Oui
B52: 3.5B2
B53: 3.5C1 | C53: Oui
B54: 3.5D1
B55: 3.5E1
B56: 3.5F1
B57: 4.1A1
B58: 4.1A2 | C58: Oui
B59: 4.1A3
B60: 4.1B1 | C60: Oui
B61: 4.1C1 | C61: Oui
B62: 4.1D1 | C62: Oui
B63: 4.1D2
B64: 4.1E1
B65: 4.1E2
B66: 4.1F1
B67: 4.1F2
B68: 4.1F3
B69: 4.1F4
B70: 4.1F5
B71: 4.1F6
B72: 4.1G1
B73: 4.1G2
B74: 4.1G6
... B92: 4.2C1
B93: 4.3A1 | C93: Oui
B94: 4.3B1
B95: 4.3B2
B96: 4.3B3
B97: 4.4A1
B98: 4.4A2
B99: 4.4A3
B100: 4.4B1
B101: 4.4C1
B104: 4.5H1
B105: 4.5L1
B106: 4.5L2
B107: 4.5T1
... B115: 5.4A2
